Workbook

Sheet Resumo
A1: 25-
B9: Клиент | F9: Matthew Renier
B11: Местоположение | F11: Das Gaivotas, Mata Porcas, Praia da Luz
B13: Описание работ
B15: Общая площадь застройки (м²) | F15: 392.8
B17: Прочее (цоколь, бассейн, пристройки, стены): | F17: 782.27
B19: Бассейн (м²) | F19: 100
B21: Дата | F21: 45812
B23: АРТ º | D23: ОПИСАНИЕ РАБОТ | J23: ИТОГО ПО РАЗДЕЛУ | L23: СТОИМОСТЬ (м2)
B25: ='Orcamento RU'!A4 -> 1 | D25: ='Orcamento RU'!B4 -> СТРОИТЕЛЬНАЯ ПЛОЩАДКА | J25: ='Orcamento RU'!C4 -> 173610.4 | L25: =+J25/$F$15 -> 441.98167
B26: ='Orcamento RU'!A10 -> 2.1 | D26: ='Orcamento RU'!B10 -> КАМЕННАЯ КЛАДКА И ЛЁГКИЕ ОГРАЖДАЮЩИЕ КОНСТРУКЦИИ | J26: ='Orcamento RU'!C10 -> 27737.99 | L26: =+J26/$F$15 -> 70.616064
B27: ='Orcamento RU'!A42 -> 2.2 | D27: ='Orcamento RU'!B42 -> КАМЕННЫЕ ИЗДЕЛИЯ | J27: ='Orcamento RU'!C42 -> 1453.17 | L27: =+J27/$F$15 -> 3.6995163
B28: ='Orcamento RU'!A68 -> 2.3 | D28: ='Orcamento RU'!B68 -> ГИДРОИЗОЛЯЦИЯ И ТЕПЛОИЗОЛЯЦИЯ | J28: ='Orcamento RU'!C68 -> 23753.39 | L28: =+J28/$F$15 -> 60.47197
B29: ='Orcamento RU'!A114 -> 2.4 | D29: ='Orcamento RU'!B114 -> КРОВЛЯ | J29: ='Orcamento RU'!C114 -> 60033.74 | L29: =+J29/$F$15 -> 152.83539
B30: ='Orcamento RU'!A124 -> 2.5 | D30: ='Orcamento RU'!B124 -> ОТДЕЛКА ПОТОЛКОВ | J30: ='Orcamento RU'!C124 -> 15456.87 | L30: =+J30/$F$15 -> 39.350484
B31: ='Orcamento RU'!A142 -> 2.6 | D31: ='Orcamento RU'!B142 -> ОТДЕЛКА СТЕН | J31: ='Orcamento RU'!C142 -> 90725.32 | L31: =+J31/$F$15 -> 230.97077
B32: ='Orcamento RU'!A174 -> 2.7 | D32: ='Orcamento RU'!B174 -> ОТДЕЛКА ПОЛОВ И ПЛИНТУСОВ | J32: ='Orcamento RU'!C174 -> 125744.31 | L32: =+J32/$F$15 -> 320.12299
B33: ='Orcamento RU'!A220 -> 2.8 | D33: ='Orcamento RU'!B220 -> СТОЛЯРНЫЕ РАБОТЫ | J33: ='Orcamento RU'!C220 -> 93859.78 | L33: =+J33/$F$15 -> 238.95056
B34: ='Orcamento RU'!A354 -> 2.9 | D34: ='Orcamento RU'!B354 -> МЕТАЛЛОКОНСТРУКЦИИ И ОКОННЫЕ РАМЫ | J34: ='Orcamento RU'!C354 -> 279339.11 | L34: =+J34/$F$15 -> 711.14845
B35: ='Orcamento RU'!A520 -> 2.1 | D35: ='Orcamento RU'!B520 -> САНТЕХНИЧЕСКОЕ ОБОРУДОВАНИЕ | J35: ='Orcamento RU'!C520 -> 56234.54 | L35: =+J35/$F$15 -> 143.16329
B36: ='Orcamento RU'!A590 -> 2.11 | D36: ='Orcamento RU'!B590 -> ОБОРУДОВАНИЕ КУХНИ И ПРАЧЕЧНОЙ | J36: ='Orcamento RU'!C590 -> 19361 | L36: =+J36/$F$15 -> 49.289715
B37: ='Orcamento RU'!A638 -> 2.12 | D37: ='Orcamento RU'!B638 -> ПРОЧЕЕ | J37: ='Orcamento RU'!C638 -> 34068.69 | L37: =+J37/$F$15 -> 86.732918
B38: ='Orcamento RU'!A698 -> 2.13 | D38: ='Orcamento RU'!B698 -> БЛАГОУСТРОЙСТВО УЧАСТКА | J38: ='Orcamento RU'!C698 -> 75835.91 | L38: =+J38/$F$15 -> 193.06494
B39: ='Orcamento RU'!A749 -> 1 | D39: ='Orcamento RU'!B749 -> ЗЕМЛЯНЫЕ РАБОТЫ | J39: ='Orcamento RU'!C749 -> 51415.45 | L39: =+J39/$F$15 -> 130.89473
B40: ='Orcamento RU'!A761 -> 2 | D40: ='Orcamento RU'!B761 -> ФУНДАМЕНТ И НЕСУЩИЕ КОНСТРУКЦИИ | J40: ='Orcamento RU'!C761 -> 558392.25 | L40: =+J40/$F$15 -> 1421.5689
B41: ='Orcamento RU'!A1043 -> 3 | D41: ='Orcamento RU'!B1043 -> ВНУТРЕННЯЯ СЕТЬ ВОДОСНАБЖЕНИЯ, БАССЕЙН И ВОДНЫЕ ЗЕРКАЛА | J41: ='Orcamento RU'!C1043 -> 40338.6 | L41: =+J41/$F$15 -> 102.69501
B42: ='Orcamento RU'!A1166 -> 4 | D42: ='Orcamento RU'!B1166 -> ВНУТРЕННЯЯ СЕТЬ БЫТОВЫХ И ДОЖДЕВЫХ СТОЧНЫХ ВОД | J42: ='Orcamento RU'!C1166 -> 74220.75 | L42: =+J42/$F$15 -> 188.95303
B43: ='Orcamento RU'!A1299 -> 5 | D43: ='Orcamento RU'!B1299 -> ГАЗОВАЯ СЕТЬ | J43: ='Orcamento RU'!C1299 -> 2768.18 | L43: =+J43/$F$15 -> 7.0473014
B44: ='Orcamento RU'!A1321 -> 6 | D44: ='Orcamento RU'!B1321 -> ПОСТАВКА И МОНТАЖ ОБОРУДОВАНИЯ И СИСТЕМ КОНДИЦИОНИРОВАНИЯ И ПРОИЗВОДСТВА ГОРЯЧЕЙ САНИТАРНОЙ ВОДЫ | J44: ='Orcamento RU'!C1321 -> 181241 | L44: =+J44/$F$15 -> 461.40784
B45: ='Orcamento RU'!A1543 -> 7 | D45: ='Orcamento RU'!B1543 -> ЭЛЕКТРИЧЕСКАЯ СЕТЬ | J45: ='Orcamento RU'!C1543 -> 213667.64 | L45: =+J45/$F$15 -> 543.96039
B46: ='Orcamento RU'!A2127 -> 8 | D46: ='Orcamento RU'!B2127 -> ТЕЛЕКОММУНИКАЦИОННЫЕ УСТАНОВКИ | J46: ='Orcamento RU'!C2127 -> 14218.6 | L46: =+J46/$F$15 -> 36.198065
B47: ='Orcamento RU'!A2206 -> 1.1 | D47: ='Orcamento RU'!B2206 -> ПОДГОТОВИТЕЛЬНЫЕ РАБОТЫ | J47: ='Orcamento RU'!C2206 -> 4600 | L47: =+J47/$F$15 -> 11.710794
B48: ='Orcamento RU'!A2217 -> 1.2 | D48: ='Orcamento RU'!B2217 -> ЗЕМЛЯНЫЕ РАБОТЫ | J48: ='Orcamento RU'!C2217 -> 22379.02 | L48: =+J48/$F$15 -> 56.973065
B49: ='Orcamento RU'!A2231 -> 1.3 | D49: ='Orcamento RU'!B2231 -> ПОЛЫ, ПОКРЫТИЯ И СТРОИТЕЛЬНЫЕ ЭЛЕМЕНТЫ | J49: ='Orcamento RU'!C2231 -> 38104.7 | L49: =+J49/$F$15 -> 97.007892
B50: ='Orcamento RU'!A2261 -> 1.4 | D50: ='Orcamento RU'!B2261 -> ОСВЕЩЕНИЕ - СВЕТОВЫЕ ТОЧКИ | J50: ='Orcamento RU'!C2261 -> 0 | L50: =+J50/$F$15 -> 0
B51: ='Orcamento RU'!A2283 -> 1.5 | D51: ='Orcamento RU'!B2283 -> ОБОРУДОВАНИЕ | J51: ='Orcamento RU'!C2283 -> 10548 | L51: =+J51/$F$15 -> 26.85336
B52: ='Orcamento RU'!A2295 -> II | D52: ='Orcamento RU'!B2295 -> ПОСАДКИ И ПОСЕВЫ | J52: ='Orcamento RU'!C2295 -> 73360.69 | L52: =+J52/$F$15 -> 186.76347
B53: ='Orcamento RU'!A2421 -> III | D53: ='Orcamento RU'!B2421 -> ПОЛИВ | J53: ='Orcamento RU'!C2421 -> 33665.94 | L53: =+J53/$F$15 -> 85.707587
B54: ='Orcamento RU'!A2497 -> IV | D54: ='Orcamento RU'!B2497 -> ОБСЛУЖИВАНИЕ ЗЕЛЕНЫХ ЗОН | J54: ='Orcamento RU'!C2497 -> 9600 | L54: =+J54/$F$15 -> 24.439919
B56: ИТОГО ЗА ЖИЛЬЕ | J56: =SUM(J25:J54) -> 2405735 | L56: =+J56/$F$15 -> 6124.58
B57: IVA (23%) | J57: =+J56*0.23 -> 553319.06
B58: ИТОГО С IVA | J58: =+J57+J56 -> 2959054.1
B60: ИТОГО ЗА БАССЕЙН | L60: =+J60/$F$19 -> 0
B61: IVA (23%) | J61: =+J60*0.23 -> 0
B62: ИТОГО С IVA | J62: =+J61+J60 -> 0
B64: ОБЩИЙ ИТОГ | J64: =J56+J60 -> 2405735
B65: IVA (23%) | J65: =+J64*0.23 -> 553319.06
B66: ИТОГО С IVA | J66: =+J65+J64 -> 2959054.1

Sheet Orcamento RU
A1: № | B1: ОПИСАНИЕ РАБОТ | C1: ЕД. ИЗМ. | D1: КОЛ-ВО | E1: ЦЕНА ЗА ЕДИНИЦУ | F1: ОБЩАЯ СТОИМОСТЬ | G1: My Unit Price | H1: My total Price | I1: My Savings | J1: FALSE
J2: FALSE
J3: FALSE
A4: 1 | B4: СТРОИТЕЛЬНАЯ ПЛОЩАДКА | C4: =F8 -> 173610.4 | E4: 85000 | J4: FALSE
J5: FALSE
A6: 1.1 | B6: СТРОИТЕЛЬНАЯ ПЛОЩАДКА И ДОПОЛНИТЕЛЬНЫЕ РАБОТЫ | J6: FALSE
J7: FALSE
A8: 1.1.1 | B8: Монтаж, строительство, обслуживание, демонтаж и снос строительной площадки, включая соответствующие установки, временные сети водоснабжения, канализации, электричества и средства телекоммуникаций, внутренние пути движения и все остальное необходимое в соответствии с Декретом-Законом № 18/08 от 29 января, удовлетворяющее предписаниям по безопасности, гигиене и охране труда, в соответствии с Декретом-Законом № 273/2003 от 29 октября и прочим действующим законодательством, разработка и внедрение плана предотвращения и управления отходами строительства и сноса (в понимании Д.З. № 46/2008 от 12 марта). | C8: vg | D8: 1 | E8: 173610.4 | F8: 173610.4 | J8: TRUE
J9: FALSE
A10: 2.1 | B10: КАМЕННАЯ КЛАДКА И ЛЁГКИЕ ОГРАЖДАЮЩИЕ КОНСТРУКЦИИ | C10: =SUM(F14:F40) -> 27737.99 | E10: 27000 | J10: FALSE
J11: FALSE
A12: 2.1.1 | B12: НАРУЖНАЯ КЛАДКА | J12: FALSE
J13: FALSE
A14: 2.1.1.1 | B14: Поставка и выполнение наружной стены с 1 слоем термического кирпича Preceram толщиной 25 см, включая кладочный раствор в пропорции 1:4, железобетонные перемычки над проемами, анкеры из нержавеющей стали для связи между кладкой и бетонной конструкцией и все подготовительные работы и аксессуары, необходимые для идеального завершения. (PE-A) (PE-B) (PE-C) (PE-D) (PE-E) (PE-P) (PE-F) | C14: m2 | D14: 155.42 | E14: 50.66 | F14: 7873.58 | J14: FALSE
J15: FALSE
A16: 2.1.1.2 | B16: Поставка и выполнение наружной стены с 1 слоем кладки из керамического кирпича размером 30x20x15 см, включая кладочный раствор в пропорции 1:4, железобетонные перемычки над проемами и все подготовительные работы и аксессуары, необходимые для идеального завершения. (PE-M) (PE-N) | C16: m2 | D16: 32.57 | E16: 32 | F16: 1042.24 | J16: FALSE
J17: FALSE
A18: 2.1.1.3 | B18: Поставка и выполнение наружной стены с 1 слоем кладки из керамического кирпича размером 30x20x11 см, включая кладочный раствор в пропорции 1:4, железобетонные перемычки над проемами, в промежутках воздушных камер предусмотреть желоб в стяжке с уклоном для отвода конденсационной воды к сливу с выходом, и все подготовительные работы и аксессуары, необходимые для идеального завершения. (PE-H) (PE-K) (PE-L) | C18: m2 | D18: 144.31 | E18: 28.06 | F18: 4049.34 | J18: FALSE
J19: FALSE
A20: 2.1.2 | B20: ВНУТРЕННЯЯ КЛАДКА | J20: FALSE
J21: FALSE
A22: 2.1.2.1 | B22: Поставка и выполнение внутренних стен с 1 слоем кладки из керамического кирпича размером 30x20x15 см, включая кладочный раствор в пропорции 1:4, железобетонные перемычки над проемами и все подготовительные работы и аксессуары, необходимые для идеального завершения. (PI-A) (PI-B) | C22: m2 | D22: 152.25 | E22: 32 | F22: 4872 | J22: FALSE
J23: FALSE
A24: 2.1.2.2 | B24: Поставка и выполнение внутренних стен с 1 слоем кладки из керамического кирпича размером 30x20x7 см, включая кладочный раствор в пропорции 1:4, железобетонные перемычки над проемами и все подготовительные работы и аксессуары, необходимые для идеального завершения. (PI-C) | C24: m2 | D24: 14.64 | E24: 25.22 | F24: 369.22 | J24: FALSE
J25: FALSE
A26: 2.1.2.3 | B26: Поставка и выполнение внутренних стен с 2 слоями кладки из керамического кирпича размером 30x20x11 см + воздушная камера 3 см + 30x20x11 см, включая кладочный раствор в пропорции 1:4, железобетонные перемычки над проемами и все подготовительные работы и аксессуары, необходимые для идеального завершения. (PI-D) (PI-E) | C26: m2 | D26: 48.01 | E26: 56.13 | F26: 2694.8 | J26: FALSE
J27: FALSE
A28: 2.1.3 | B28: ЛЕГКИЕ ВНУТРЕННИЕ ПЕРЕГОРОДКИ | J28: FALSE
J29: FALSE
A30: 2.1.3.1 | B30: Поставка и выполнение облицовки гипсокартонными плитами толщиной 12 мм на внутренних поверхностях наружных стен, система двойной обшивки, внутреннее заполнение минеральной ватой толщиной 9 см, включая профилированную конструкцию для поддержки плит со стойками 90 мм, систему крепления, обработку швов, шпатлевку и финишную подготовку под покраску или финишную отделку и все подготовительные работы и аксессуары, необходимые для идеального завершения. (PE-P) | C30: m2 | D30: 19.35 | E30: 54.18 | F30: 1048.38 | J30: FALSE
J31: FALSE
A32: 2.1.3.2 | B32: Поставка и выполнение облицовки стандартными гипсокартонными плитами толщиной 12 мм на внутренних поверхностях наружных стен, система двойной обшивки, внутреннее заполнение минеральной ватой толщиной 5 см, включая профилированную конструкцию для поддержки плит со стойками 48 мм, систему крепления, обработку швов, шпатлевку и финишную подготовку под покраску или финишную отделку и все подготовительные работы и аксессуары, необходимые для идеального завершения. (PE-C) (PE-D) (PI-G) | C32: m2 | D32: 37.64 | E32: 52.76 | F32: 1985.89 | J32: FALSE
J33: FALSE
A34: 2.1.3.3 | B34: Поставка и выполнение облицовки влагостойкими гипсокартонными плитами толщиной 12 мм на внутренних поверхностях наружных стен, система двойной обшивки, внутреннее заполнение минеральной ватой толщиной 5 см, включая профилированную конструкцию для поддержки плит со стойками 48 мм, систему крепления, обработку швов, шпатлевку и финишную подготовку под покраску или финишную отделку и все подготовительные работы и аксессуары, необходимые для идеального завершения. (PE-I) (PI-H) | C34: m2 | D34: 20.27 | E34: 62.72 | F34: 1271.33 | J34: FALSE
J35: FALSE
A36: 2.1.3.4 | B36: Поставка и выполнение облицовки влагостойкими гипсокартонными плитами толщиной 12 мм на внутренних поверхностях наружных стен, система двойной обшивки, внутреннее заполнение минеральной ватой толщиной 3 см, включая профилированную конструкцию для поддержки плит со стойками 30 мм, систему крепления, обработку швов, шпатлевку и финишную подготовку под покраску или финишную отделку и все подготовительные работы и аксессуары, необходимые для идеального завершения. (PE-J) | C36: m2 | D36: 10.99 | E36: 60.65 | F36: 666.54 | J36: FALSE
J37: FALSE
A38: 2.1.3.5 | B38: Поставка и монтаж легких перегородок с двойной обшивкой влагостойким гипсокартоном толщиной 12 мм с каждой стороны, внутренняя облицовка акустической изоляцией из минеральной ваты толщиной 5 см, включая профилированную конструкцию для поддержки плит со стойками 48 мм, систему крепления, обработку швов, шпатлевку и финишную подготовку под покраску и все подготовительные работы и аксессуары, необходимые для идеального завершения. (PI-F) | C38: m2 | D38: 17.94 | E38: 52.76 | F38: 946.51 | J38: FALSE
J39: FALSE
A40: 2.1.3.6 | B40: Поставка и монтаж легких перегородок с простой обшивкой влагостойким МДФ толщиной 19 мм, лакированным с каждой стороны, с матовым покрытием цвета RAL 9003, внутренняя облицовка акустической изоляцией из минеральной ваты толщиной 4 см, включая конструкцию из труб FACAR диаметром 4 см для поддержки плит, систему крепления и все подготовительные работы и аксессуары, необходимые для идеального завершения. (PI-I) (PR06) | C40: m2 | D40: 12.91 | E40: 71.12 | F40: 918.16 | J40: FALSE
J41: FALSE
A42: 2.2 | B42: КАМЕННЫЕ ИЗДЕЛИЯ | C42: =SUM(F48:F66) -> 1453.17 | E42: 3445 | J42: FALSE
J43: FALSE
A44: 2.2.1 | B44: БЕТОННЫЕ ПОРОГИ | J44: FALSE
J45: FALSE
A46: 2.2.1.1 | B46: Поставка и выполнение бетонных порогов со шпатлевкой, согласно детали PORM10, приподнятых на 1 см с резиновыми опорами по усмотрению исполнителя, включая резку, отделку и все подготовительные работы и аксессуары, необходимые для идеального завершения. | J46: FALSE
J47: FALSE
A48: 2.2.1.1.1 | B48: Порог VE 01.1 - Размер 1,10 м. | C48: un | D48: 1 | E48: 45.48 | F48: 45.48 | J48: FALSE
J49: FALSE
A50: 2.2.1.1.2 | B50: Порог VE 01.2 - Размер 4,68 м. | C50: un | D50: 1 | E50: 193.49 | F50: 193.49 | J50: FALSE
J51: FALSE
A52: 2.2.1.1.3 | B52: Порог VE 01.3 - Размер 4,61 м. | C52: un | D52: 1 | E52: 190.6 | F52: 190.6 | J52: FALSE
J53: FALSE
A54: 2.2.1.1.4 | B54: Порог VE 01.4 - Размер 3,04 м. | C54: un | D54: 1 | E54: 125.69 | F54: 125.69 | J54: FALSE
J55: FALSE
A56: 2.2.1.2 | B56: Поставка и выполнение узких порогов между проемами 1-го этажа из бетонных элементов со шпатлевкой, согласно детали PORM10, приподнятых на 1 см с резиновыми опорами по усмотрению исполнителя, включая резку, отделку и все подготовительные работы и аксессуары, необходимые для идеального завершения. | J56: FALSE
J57: FALSE
A58: 2.2.1.2.1 | B58: Порог A - Размер 400x70 мм. | C58: un | D58: 1 | E58: 14.6 | F58: 14.6 | J58: FALSE
J59: FALSE
A60: 2.2.1.2.2 | B60: Порог B - Размер 3960x70 мм. | C60: un | D60: 1 | E60: 144.54 | F60: 144.54 | J60: FALSE
J61: FALSE
A62: 2.2.1.2.3 | B62: Порог C - Размер 5300x70 мм. | C62: un | D62: 1 | E62: 193.45 | F62: 193.45 | J62: FALSE
J63: FALSE
A64: 2.2.1.2.4 | B64: Порог D - Размер 1390x70 мм. | C64: un | D64: 1 | E64: 507.36 | F64: 507.36 | J64: FALSE
J65: FALSE
A66: 2.2.1.2.5 | B66: Порог E - Размер 1040x70 мм. | C66: un | D66: 1 | E66: 37.96 | F66: 37.96 | J66: FALSE
J67: FALSE
A68: 2.3 | B68: ГИДРОИЗОЛЯЦИЯ И ТЕПЛОИЗОЛЯЦИЯ | C68: =SUM(F72:F112) -> 23753.39 | E68: 55065 | J68: FALSE
J69: FALSE
A70: 2.3.1 | B70: НА КРОВЛЕ #2 и #3 | J70: FALSE
J71: FALSE
A72: 2.3.1.1 | B72: Поставка и выполнение гидроизоляции плоских кровель (#2 и #3) 1-го этажа (недоступные), включая все подготовительные работы и аксессуары, необходимые для идеального завершения, согласно следующим работам: | J72: FALSE
J73: FALSE
A74: 2.3.1.1.1 | B74: Теплоизоляция плитами экструдированного полистирола "IFOAM COBERTURAS" толщиной 8 см, включая резку, отделку. | C74: m2 | D74: 37.14 | E74: 11.9 | F74: 441.97 | J74: FALSE
J75: FALSE
A76: 2.3.1.1.2 | B76: Формирующий слой из легкого бетона для выравнивания и создания желобов и уклонов необходимой толщины, с затертой поверхностью для укладки мембран. | C76: m2 | D76: 37.14 | E76: 23.36 | F76: 867.59 | J76: FALSE
J77: FALSE
A78: 2.3.1.1.3 | B78: Система гидроизоляции типа "Imperalum" с покраской Imperkote L, система гидроизоляции с двумя перекрещенными мембранами POLYPLAS 30 + POLYXIS R40 (мембраны поднимаются на парапеты, делая перекрытие и крепятся к ним соответствующими уголками или другими), разделительная мембрана из каландрированной полиэфирной ткани типа "IMPERSEP 200", включая резку, отделку, крепления, все готово для получения финишного покрытия. | C78: m2 | D78: 37.14 | E78: 31.78 | F78: 1180.31 | J78: FALSE
J79: FALSE
A80: 2.3.2 | B80: НА БАЛКОНЕ | J80: FALSE
J81: FALSE
A82: 2.3.2.1 | B82: Поставка и выполнение гидроизоляции балкона 1-го этажа (доступные), включая все подготовительные работы и аксессуары, необходимые для идеального завершения, согласно следующим работам: | J82: FALSE
J83: FALSE
A84: 2.3.2.1.1 | B84: Теплоизоляция плитами экструдированного полистирола "IFOAM COBERTURAS" толщиной 8 см, включая резку, отделку. | C84: m2 | D84: 53 | E84: 11.9 | F84: 630.7 | J84: FALSE
J85: FALSE
A86: 2.3.2.1.2 | B86: Стяжка с затертой поверхностью для укладки мембран и создания уклонов. | C86: m2 | D86: 53 | E86: 23.36 | F86: 1238.08 | J86: FALSE
J87: FALSE
A88: 2.3.2.1.3 | B88: Система гидроизоляции типа "Imperalum" с покраской Imperkote L, система гидроизоляции с двумя перекрещенными мембранами POLYPLAS 30 + POLYXIS R40, (мембраны поднимаются на парапеты, делая перекрытие и крепятся к ним соответствующими уголками или другими), разделительная мембрана из каландрированной полиэфирной ткани типа "IMPERSEP 200", включая резку, отделку, крепления, все готово для получения финишного покрытия. | C88: m2 | D88: 53 | E88: 31.78 | F88: 1684.34 | J88: FALSE
J89: FALSE
A90: 2.3.3 | B90: НА КРОВЛЕ ТЕХНИЧЕСКОЙ ЗОНЫ БАССЕЙНА #1 И ТЕХНИЧЕСКОЙ ЗОНЫ #2 | J90: FALSE
J91: FALSE
A92: 2.3.3.1 | B92: Поставка и выполнение гидроизоляции плоской кровли технической зоны #1 и компенсационного бака, технической зоны #2, включая все подготовительные работы и аксессуары, необходимые для идеального завершения, согласно следующим работам: | J92: FALSE
J93: FALSE
A94: 2.3.3.1.1 | B94: Стяжка с затертой поверхностью для укладки мембран и создания уклонов. | C94: m2 | D94: 32.4 | E94: 23.36 | F94: 756.86 | J94: FALSE
J95: FALSE
A96: 2.3.3.1.2 | B96: Система гидроизоляции типа "Imperalum" с покраской Imperkote L, система гидроизоляции с двумя перекрещенными мембранами POLYPLAS 30 + POLYXIS R40, (мембраны поднимаются на парапеты, делая перекрытие и крепятся к ним соответствующими уголками или другими), разделительная мембрана из каландрированной полиэфирной ткани типа "IMPERSEP 200", включая резку, отделку, крепления, все готово для получения финишного покрытия. | C96: m2 | D96: 32.4 | E96: 31.78 | F96: 1029.67 | J96: FALSE
J97: FALSE
A98: 2.3.4 | B98: НА ЗАГЛУБЛЕННЫХ ПОВЕРХНОСТЯХ | J98: FALSE
J99: FALSE
A100: 2.3.4.1 | B100: Поставка и выполнение системы дренажа заглубленных стен путем применения дренажной мембраны с выступами типа "Aguadrain" или эквивалентной, закрепленной к железобетонным поверхностям, включая геодренажную трубу в дне траншеи, обернутую щебнем, подключение к дренажной сети, колодцы, систему крепления, резку, отделку и все подготовительные работы и аксессуары. | C100: m2 | D100: 303.47 | E100: 22.54 | F100: 6840.21 | J100: FALSE
...

Sheet Example Orcamento PT Viora Buil
A1: № M | B1: № V | C1: DESCRIÇÃO DOS TRABALHOS | D1: UN. MED. | E1: QUANT. | F1: PREÇO UNITÁRIO | G1: VALOR TOTAL | H1: Comentário
B4: 1 | C4: CANTEIRO DE OBRAS E TRABALHOS COMPLEMENTARES | D4: =G8 | G4: =SUM(G10:G46) -> 108116 | H4: =G4-('Orcamento RU'!C4+'Orcamento RU'!C2206) -> -70094.4
C6: CANTEIRO DE OBRAS
A8: 1.1.1 (1) | B8: 1.1 | C8: Montagem, construção, manutenção, desmontagem e demolição do canteiro de obras, incluindo as respectivas instalações, redes provisórias de água, esgoto, eletricidade e meios de telecomunicações, vias internas de circulação e tudo mais necessário de acordo com o Decreto-Lei nº 18/08 de 29 de janeiro, atendendo às prescrições de segurança, higiene e saúde no trabalho, de acordo com o Decreto-Lei nº 273/2003 de 29 de outubro e demais legislação em vigor, elaboração e implementação do plano de prevenção e gestão de resíduos de construção e demolição (nos termos do D.L. nº 46/2008 de 12 de março).
A10: 1.1.1 (1) | B10: 1.1.1 | C10: Fornecimento e instalação, manutenção e desmontagem de vedação em torno do terreno com painéis opacos de chapa de aço galvanizado perfilada com espessura de 0,6 mm, com nervuras de altura entre 40 e 50 mm, colocadas a uma distância entre 250 e 270 mm, e perfis em S de chapa de aço galvanizado dobrada de dimensão 102x33x1,5 mm, com acabamento sendzimir, comprimento 2,8 m, fixados no solo por meio de cubos de concreto C20/25 XC0 Cl0.40 Dmax 25mm S2 de dimensão 102x33x1,5 cm, a cada 2,0 m, incluindo todos os trabalhos e materiais relacionados. | D10: ml | E10: 260 | F10: 100 | G10: =F10*E10 -> 26000 | H10: Pode construir a cerca de imediato, economizando 268000
A12: 1.1.1 (1) | B12: 1.1.2 | C12: Fornecimento e montagem, manutenção e desmontagem de portão deslizante para acesso de veículos em aço galvanizado de duas folhas com dimensões aproximadas de 4,0x2,0m com trava para cadeado e ferragens para fixação ao piso, instalado na vedação temporária do terreno, fixado por meio de postes do mesmo material, ancorados no solo por meio de cubos de concreto C20/25 XC0 Cl0.40 Dmáx 25mm S2, incluindo todos os trabalhos e materiais relacionados. | D12: vg | E12: 1 | F12: 800 | G12: =F12*E12 -> 800
A14: 1.1.1 (1) | B14: 1.1.3 | C14: Fornecimento e instalação de placa informativa, divulgando a construção, incluindo todos os trabalhos e materiais relacionados. | D14: vg | E14: 1 | F14: 120 | G14: =F14*E14 -> 120
A16: 1.1.1 (1) | B16: 1.1.4 | C16: Fornecimento e execução de redes primárias de eletricidade, água e esgoto, incluindo o consumo mensal durante todo o período de execução da obra até a recepção provisória, incluindo trabalhos e materiais relacionados. | D16: meses | E16: 18 | F16: 200 | G16: =F16*E16 -> 3600 | H16: Este ponto será resolvido de acordo com a situação
A18: 1.1.1 (1) | B18: 1.1.5 | C18: Fornecimento e montagem de módulo de escritório de dimensão 6,0x3,0 m para reuniões de obra, instalado sobre base nivelada de brita, com banheiro e ar condicionado, incluindo aterramento e todos os trabalhos e materiais relacionados. | D18: vg | E18: 1 | F18: 0 | G18: =F18*E18 -> 0 | H18: A pedido do cliente, para sua conveniência. Preço 12,000 euros
A20: 1.1.1 (1) | B20: 1.1.6 | C20: Fornecimento e montagem de módulo de ferramentaria geral de dimensão 3,0x2,40 m tipo contêiner marítimo, instalado sobre base nivelada de brita, incluindo todos os trabalhos e materiais relacionados. | D20: vg | E20: 1 | F20: 5200 | G20: =F20*E20 -> 5200
A22: 1.1.1 (1) | B22: 1.1.7 | C22: Fornecimento e instalação de bloco sanitário portátil em polietileno de dimensão 1,20x1,20x2,35m de cor cinza ou outra, sem ligações, com sanitário químico anaeróbico com sistema de descarga por pedal, espelho, porta com fechadura e teto translúcido para passagem de luz externa, incluindo limpeza semanal e todos os trabalhos e materiais relacionados. | D22: meses | E22: 18 | F22: 147 | G22: =F22*E22 -> 2646
A24: 1.1.1 (1) | B24: 1.8 | C24: Fornecimento e execução de implantação topográfica através de técnico especializado dos níveis de implantação da construção, incluindo piscina e limites, bem como todos os trabalhos e materiais relacionados. | D24: vg | E24: 1 | F24: 1530 | G24: =F24*E24 -> 1530
A26: 1.1.1 (1) | B26: 1.9 | C26: Fornecimento e montagem de andaimes de tubos padrão, tipo multidirecional, até 9 m de altura, constituídos por estrutura tubular de aço laminado a quente galvanizado de diâmetro 48,3 mm e espessura 3,2 mm, sem duplicação de elementos verticais, compostos por plataformas de trabalho de 60 cm de largura, colocadas a cada 2 m de altura, escada interior com alçapão, guarda-costas com dois corrimãos e rodapé, e guarda-frente com um corrimão, para execução de fachada(s) com elementos estruturais (terraços cobertos e descobertos, cornijas e outros, etc.) dispostos em mais de 50% do seu perímetro e que se projetam mais de 30 cm do plano da fachada. Nota (1): os andaimes devem estar em total conformidade com a legislação em vigor, nomeadamente EN 12811 e EN 12810. | D26: meses | E26: 18 | F26: 500 | G26: =F26*E26 -> 9000 | H26: Aluguel de andaimes
A28: 1.1.1 (1) | B28: 1.10 | C28: Fornecimento, execução e implementação/adaptação do plano de segurança e saúde (PSS) na fase de construção, incluindo todos os trabalhos e materiais relacionados. | D28: meses | E28: 18 | F28: 390 | G28: =F28*E28 -> 7020 | H28: O seguro do objeto pode variar entre 300-500 euros. Foi fornecida a informação mais recente
A30: 1.1.1 (1) | B30: 1.11 | C30: Fornecimento, execução e implementação/adaptação do plano de gestão de resíduos (PGR), sua classificação (LER), triagem e separação nas suas componentes recicláveis e respectiva eliminação ou transporte para zonas de reciclagem e para operadores autorizados e licenciados, de acordo com a legislação em vigor. | D30: meses | E30: 18 | F30: 300 | G30: =F30*E30 -> 5400 | H30: Este ponto será resolvido de acordo com a situação
A32: 1.1.1 (1) | B32: 1.12 | C32: Elaboração e entrega ao dono da obra da compilação técnica da obra, que inclui elementos úteis a ter em conta na sua utilização futura, bem como na realização de trabalhos posteriores à sua conclusão para preservar a segurança e saúde dos que os executam, de acordo com o disposto no artigo 16º do Decreto-Lei nº 273/2003 de 29 de outubro, considerando os desenhos finais de todas as especialidades em papel e suporte digital, todos os estudos, projetos, documentação anexa e relacionada. | D32: vg | E32: 1 | F32: 0 | G32: =F32*E32 -> 0 | H32: Incluído no custo do próprio projeto
A34: 1.1.1 (1) | B34: 1.13 | C34: Fornecimento e coordenação de recursos humanos e materiais necessários para a limpeza e manutenção do canteiro de obras, incluindo a instalação de todos os equipamentos de segurança, como guarda-corpos e linhas de vida, etc., tudo de acordo com a legislação em vigor. | D34: meses | E34: 18 | F34: 150 | G34: =F34*E34 -> 2700
A36: 1.1.1 (1) | B36: 1.14 | C36: Fornecimento de pessoal especializado, nomeadamente diretor de projeto (engenheiro civil), encarregado geral, preparador de obra. | D36: meses | E36: 18 | F36: 450 | G36: =F36*E36 -> 8100
A38: 1.1.1 (1) | B38: 1.15 | C38: Fornecimento e instalação de equipamentos e materiais de segurança, colocados em locais visíveis, incluindo todos os trabalhos e materiais relacionados. | D38: vg | E38: 1 | F38: 1500 | G38: =F38*E38 -> 1500
C40: GUINDASTE
B42: 1.16 | C42: Fornecimento e execução de escavação em qualquer tipo de solo para a base do guindaste, incluindo depósito de terra em armazenamento para aterros, compactação e nivelamento da base da plataforma de trabalho, bem como todos os trabalhos e materiais relacionados. | D42: vg | E42: 1 | F42: 0 | G42: =F42*E42 -> 0 | H42: Incluído no custo dos trabalhos de terraplenagem
B44: 1.17 | C44: Fornecimento e execução de elementos estruturais de concreto tipo C25/30 XC2(P) Dmáx 20mm S3, fabricados, transportados e colocados em obra de acordo com NP EN 206-1 e NP ENV 13670-1 para a base de instalação do guindaste, incluindo execução de fôrmas e armaduras em aço tipo A500NR SD e todos os trabalhos necessários para um acabamento de qualidade, tudo de acordo com o projeto de estabilidade, incluindo todos os trabalhos e materiais relacionados. Nota (1): deve-se considerar a desmontagem da fundação do guindaste. | D44: vg | E44: 1 | F44: 8000 | G44: =F44*E44 -> 8000
B46: 1.18 | C46: Fornecimento e operação de guindaste de torre com lança extensível de 50 m com características adequadas à obra, incluindo controle por rádio e por cabo, balde-trenó de 300 litros e palete para 2000 kg. | D46: vg | E46: 1 | F46: =SUM(G48:G52) -> 26500 | G46: =F46*E46 -> 26500
B48: 1.18.1 | C48: Montagem do guindaste. | D48: vg | E48: 1 | F48: 1700 | G48: =F48*E48 -> 1700
B49: 1.18.2 | C49: Operação do guindaste. | D49: meses | E49: 14 | F49: 1500 | G49: =F49*E49 -> 21000
B50: 1.18.3 | C50: Desmontagem do guindaste. | D50: vg | E50: 1 | F50: 1700 | G50: =F50*E50 -> 1700
B51: 1.18.4 | C51: Entrega do guindaste. | D51: peças | E51: 1 | F51: 1050 | G51: =F51*E51 -> 1050
B52: 1.18.5 | C52: Retirada do guindaste. | D52: peças | E52: 1 | F52: 1050 | G52: =F52*E52 -> 1050
B55: 2 | C55: MOVIMENTO DE TERRAS | G55: =SUM(G59:G71) -> 34482.88 | H55: =G55-('Orcamento RU'!C749+'Orcamento RU'!C2217) -> -39311.59
C57: MOVIMENTO DE TERRAS
A59: 1,1 (2) | B59: 2.1 | C59: Limpeza geral do terreno, incluindo todos os tipos de trabalhos de limpeza, remoção, desmatamento e corte de espécies arbóreas, existentes e necessárias para a execução geral dos projetos. | D59: un | E59: 1 | F59: 4000 | G59: =F59*E59 -> 4000
A61: 1,2 (2) | B61: 2.2 | C61: Execução de escavação geral para implantação da estrutura da habitação, piscina e muros em solo de qualquer tipo (incluindo rocha), para atingir as cotas iniciais de fundação, bem como execução de trabalhos de escoramento, escoras, drenagem, incluindo todos os trabalhos relacionados. | D61: m³ | E61: 2234.27 | F61: 4 | G61: =F61*E61 -> 8937.08
A63: 1,3 (2) | B63: 2.3 | C63: Execução de aterros na zona da habitação, piscina e terraços exteriores com materiais provenientes da escavação, incluindo espalhamento e compactação adequada, executada por meios mecânicos, em camadas de espessura máxima de 0,30 m, com utilização de água na quantidade necessária para a correta compactação, para atingir os níveis de projeto, incluindo todos os trabalhos relacionados. | D63: m³ | E63: 482.44 | F63: 5 | G63: =F63*E63 -> 2412.2
A65: 1.4.1 (2) | B65: 2.4 | C65: Transporte, carga e descarga de excedentes de solo da zona da habitação para vazadouro, incluindo 20% de empolamento, bem como todos os trabalhos relacionados. | D65: m³ | E65: 2102.2 | F65: 8 | G65: =F65*E65 -> 16817.6
A67: 1.2.1.1 (3) | B67: 2.5 | C67: Escavação de solo de qualquer natureza até as cotas de projeto, incluindo transporte para zonas de aterro, os restantes devem ser transportados para depósito autorizado, incluindo transporte, compensações, bem como todos os meios, trabalhos, materiais necessários. | D67: m3 | E67: 68 | F67: 3 | G67: =F67*E67 -> 204
A69: 1.2.2.1 (3) | B69: 2.6 | C69: Aterro em camadas até as cotas de projeto com solo selecionado proveniente das escavações ou de zonas de empréstimo fora da área de intervenção, incluindo transporte, todos os meios, trabalhos, materiais necessários. | D69: m3 | E69: 386 | F69: 3 | G69: =F69*E69 -> 1158
A71: 1.2.3.1 (3) | B71: 2.7 | C71: Fornecimento, carga, transporte, descarga, espalhamento de solo de empréstimo, bem como todos os meios, trabalhos, materiais necessários. | D71: m3 | E71: 318 | F71: 3 | G71: =F71*E71 -> 954
B73: 3 | C73: ESTRUTURA DE CONCRETO ARMADO | G73: =SUM(G79:G269) -> 567388.82 | H73: =G73-'Orcamento RU'!C761 -> 8996.574
C75: Concreto
A77: 2.1.1 (2) | B77: 3.1 | C77: Fornecimento e colocação de concreto magro C12/15, com classe de exposição X0, Cl 1.0, Dmax 25mm, S3, com espessura de 5 cm sob elementos de fundação, incluindo nivelamento prévio e compactação do fundo das escavações, colocado na forma geométrica dos seguintes elementos:
A79: 2.1.1.1 (2) | B79: 3.1.1 | C79: Em fundações, fundações de paredes, muros de contenção, vigas de fundação e lajes de fundação | D79: m2 | E79: 329.7 | F79: 12 | G79: =F79*E79 -> 3956.4
A81: 2.1.2 (2) | B81: 3.2 | C81: Fornecimento e colocação de concreto C30/37, com classe de exposição XC2, Cl 0.4, Dmax 20mm, S3, incluindo vibração e todos os trabalhos relacionados, necessários para perfeito acabamento nos seguintes elementos:
A83: 2.1.2.1 (2) | B83: 3.2.1 | C83: Em vigas de fundação | D83: m³ | E83: 29.25 | F83: 140 | G83: =F83*E83 -> 4095
A84: 2.1.2.2 (2) | B84: 3.2.2 | C84: Em fundações | D84: m³ | E84: 8.94 | F84: 140 | G84: =F84*E84 -> 1251.6
A85: 2.1.2.3(2) | B85: 3.2.3 | C85: Em fundações de paredes e divisórias | D85: m³ | E85: 106.22 | F85: 140 | G85: =F85*E85 -> 14870.8
A86: 2.1.2.4 (2) | B86: 3.2.4 | C86: Em laje de fundação | D86: m³ | E86: 3.02 | F86: 140 | G86: =F86*E86 -> 422.8
A88: 2.1.3(2) | B88: 3.3 | C88: Fornecimento e colocação de concreto C30/37, com classe de exposição XC2, Cl 0.4, Dmax 20mm, S4, incluindo vibração e todos os trabalhos relacionados, necessários para perfeito acabamento nos seguintes elementos:
A90: 2.1.3.1 (2) | B90: 3.3.1 | C90: Pilares de paredes do subsolo | D90: m³ | E90: 2.51 | F90: 140 | G90: =F90*E90 -> 351.4
A91: 2.1.3.2 (2) | B91: 3.3.2 | C91: Paredes do subsolo/contenção/divisórias | D91: m³ | E91: 88.26 | F91: 140 | G91: =F91*E91 -> 12356.4
A92: 2.1.3.2(2) | B92: 3.3.3 | C92: Escada exterior | D92: m³ | E92: 1.32 | F92: 140 | G92: =F92*E92 -> 184.8
A94: 2.1.4 (2) | B94: 3.4 | C94: Fornecimento e colocação de concreto C40/50, com classe de exposição XS1, Cl 0.2, Dmax 20mm, S4, incluindo vibração e todos os trabalhos relacionados, necessários para perfeito acabamento nos seguintes elementos:
A96: 2.1.4.1 (2) | B96: 3.4.1 | C96: Em pilares | D96: m³ | E96: 7.28 | F96: 160 | G96: =F96*E96 -> 1164.8
A97: 2.1.4.2 (2) | B97: 3.4.2 | C97: Em paredes | D97: m³ | E97: 27.46 | F97: 160 | G97: =F97*E97 -> 4393.6
A99: 2.1.4 (2) | B99: 3.5 | C99: Fornecimento e colocação de concreto C40/50, com classe de exposição XS1, Cl 0.2, Dmax 16mm, S4, incluindo vibração e todos os trabalhos relacionados, necessários para perfeito acabamento nos seguintes elementos:
A101: 2.1.4.3 (2) | B101: 3.5.1 | C101: Em vigas | D101: m³ | E101: 52.37 | F101: 160 | G101: =F101*E101 -> 8379.2
A102: 2.1.4.4 (2) | B102: 3.5.2 | C102: Em lajes maciças | D102: m³ | E102: 60.12 | F102: 160 | G102: =F102*E102 -> 9619.2
A103: 2.1.4.5 (2) | B103: 3.5.3 | C103: Em lajes maciças aligeiradas (Cobiax) | D103: m³ | E103: 50.41 | F103: 160 | G103: =F103*E103 -> 8065.6
A104: 2.1.4.6 (2) | B104: 3.5.4 | C104: Em escadas Escada E1 | D104: m³ | E104: 1.91 | F104: 160 | G104: =F104*E104 -> 305.6
A106: 2.1.5 (2) | B106: 3.6 | C106: Fornecimento e colocação de concreto C40/50, com classe de exposição XD2, Cl 0.2, Dmax 20mm, S4, em elementos da piscina, tanque de compensação e espelho d'água, incluindo vibração e todos os trabalhos relacionados, necessários para perfeito acabamento nos seguintes elementos:
A108: 2.1.5.1 (2) | B108: 3.6.1 | C108: Em paredes | D108: m³ | E108: 30.26 | F108: 160 | G108: =F108*E108 -> 4841.6
A109: 2.1.5.2 (2) | B109: 3.6.2 | C109: Em lajes | D109: m³ | E109: 21.41 | F109: 160 | G109: =F109*E109 -> 3425.6
A110: 2.1.5.3 (2) | B110: 3.6.3 | C110: Em vigas/reforços | D110: m³ | E110: 3.06 | F110: 160 | G110: =F110*E110 -> 489.6
A111: 2.1.5.4 (2) | B111: 3.6.4 | C111: Em escadas (Escada E3) | D111: m³ | E111: 1.18 | F111: 160 | G111: =F111*E111 -> 188.8
C113: Aço/Armadura
A115: 2.2.1 (2) | B115: 3.7 | C115: Fornecimento, fabricação e instalação de aço A500NR SD em armaduras de elementos estruturais, incluindo desperdícios, emendas, arame recozido, meios e equipamentos e todos os trabalhos relacionados, necessários para perfeito acabamento nos seguintes elementos:
A117: 2.2.1.1 | B117: 3.7.1 | C117: Fundações
B118: 3.7.1.1 | C118: Ø10 | D118: kg | E118: 421.74 | F118: 1.9 | G118: =F118*E118 -> 801.306
A120: 2.2.1.2 | B120: 3.7.2 | C120: Fundações de paredes/divisórias
B121: 3.7.2.1 | C121: Ø8 | D121: kg | E121: 1572.83 | F121: 1.9 | G121: =F121*E121 -> 2988.377
B122: 3.7.2.2 | C122: Ø10 | D122: kg | E122: 3799.07 | F122: 1.9 | G122: =F122*E122 -> 7218.233
A124: 2.2.1.3 | B124: 3.7.3 | C124: Laje de fundação
B125: 3.7.3.1 | C125: Ø10 | D125: kg | E125: 289.81 | F125: 1.9 | G125: =F125*E125 -> 550.639
B126: 3.7.3.2 | C126: Ø12 | D126: kg | E126: 412.85 | F126: 1.9 | G126: =F126*E126 -> 784.415
A128: 2.2.1.4 | B128: 3.7.4 | C128: Vigas de fundação
B129: 3.7.4.1 | C129: Ø8 | D129: kg | E129: 651.95 | F129: 1.9 | G129: =F129*E129 -> 1238.705
B130: 3.7.4.2 | C130: Ø10 | D130: kg | E130: 132.8 | F130: 1.9 | G130: =F130*E130 -> 252.32
B131: 3.7.4.3 | C131: Ø12 | D131: kg | E131: 477.82 | F131: 1.9 | G131: =F131*E131 -> 907.858
B132: 3.7.4.4 | C132: Ø16 | D132: kg | E132: 1878.6 | F132: 1.9 | G132: =F132*E132 -> 3569.34
A134: 2.2.1.5 | B134: 3.7.5 | C134: Paredes do subsolo/contenção e divisórias
B135: 3.7.5.1 | C135: Ø8 | D135: kg | E135: 861.38 | F135: 1.9 | G135: =F135*E135 -> 1636.622
B136: 3.7.5.2 | C136: Ø10 | D136: kg | E136: 4610.89 | F136: 1.9 | G136: =F136*E136 -> 8760.691
B137: 3.7.5.3 | C137: Ø12 | D137: kg | E137: 12447.9 | F137: 1.9 | G137: =F137*E137 -> 23651.01
A139: 2.2.1.6 | B139: 3.7.6 | C139: Pilares
B140: 3.7.6.1 | C140: Ø8 | D140: kg | E140: 873.77 | F140: 1.9 | G140: =F140*E140 -> 1660.163
B141: 3.7.6.2 | C141: Ø12 | D141: kg | E141: 1173.14 | F141: 1.9 | G141: =F141*E141 -> 2228.966
B142: 3.7.6.3 | C142: Ø16 | D142: kg | E142: 851.86 | F142: 1.9 | G142: =F142*E142 -> 1618.534
A144: 2.2.1.7 | B144: 3.7.7 | C144: Vigas e reforços
B145: 3.7.7.1 | C145: Ø8 | D145: kg | E145: 2505.02 | F145: 1.9 | G145: =F145*E145 -> 4759.538
B146: 3.7.7.2 | C146: Ø10 | D146: kg | E146: 113.14 | F146: 1.9 | G146: =F146*E146 -> 214.966
B147: 3.7.7.3 | C147: Ø12 | D147: kg | E147: 145.88 | F147: 1.9 | G147: =F147*E147 -> 277.172
B148: 3.7.7.4 | C148: Ø16 | D148: kg | E148: 6059.68 | F148: 1.9 | G148: =F148*E148 -> 11513.392
A150: 2.2.1.8 | B150: 3.7.8 | C150: Lajes
B151: 3.7.8.1 | C151: Ø10 | D151: kg | E151: 3007.17 | F151: 1.9 | G151: =F151*E151 -> 5713.623
B152: 3.7.8.2 | C152: Ø12 | D152: kg | E152: 14406.06 | F152: 1.9 | G152: =F152*E152 -> 27371.514
A154: 2.2.1.9 | B154: 3.7.9 | C154: Escadas
B155: 3.7.9.1 | C155: Ø10 | D155: kg | E155: 601.06 | F155: 1.9 | G155: =F155*E155 -> 1142.014
A157: 2.2.1.10 | B157: 3.7.10 | C157: Piscina (lajes, paredes e tanque de compensação)
B158: 3.7.10.1 | C158: Ø8 | D158: kg | E158: 977.88 | F158: 1.9 | G158: =F158*E158 -> 1857.972
B159: 3.7.10.2 | C159: Ø10 | D159: kg | E159: 2445.29 | F159: 1.9 | G159: =F159*E159 -> 4646.051
B160: 3.7.10.3 | C160: Ø12 | D160: kg | E160: 4767.93 | F160: 1.9 | G160: =F160*E160 -> 9059.067
...

Sheet Orcamento PT
A4: Item | B4: Descrição | D4: UN | E4: Quantidade | F4: PREÇO
F5: Unitário | G5: T O T A L
D8: Units | E8: Quantity | F8: Unit Price | G8: Total | H8: My Unit Price | I8: My total Price | J8: My Savings
B10: EXECUÇÃO DE MORADIA - URB. DAS GAIVOTAS MATA PORCAS, PRAIA DA LUZ
A12: 1 | B12: ESTALEIRO
A14: 1.1 | B14: ESTALEIRO E TRABALHOS COMPLEMENTARES
A16: 1.1.1 | B16: Montagem, construção, manutenção, desmontagem e demolição de estaleiro, incluindo as correspondentes instalações, redes provisórias de água, esgoto, electricidade e meios de telecomunicações, vias internas de circulação e tudo o mais necessário de acordo com o Dec-Lei n.º 18/08, de 29 de Janeiro, satisfazendo as prescrições relativas à Segurança, Higiene e Saúde no trabalho, em conformidade com o Dec-Lei n.º 273/2003 de 29 de Outubro e demais legislação em vigor, Desenvolvimento e Implementação do Plano de Prevenção e Gestão de Resíduos de Construção e Demolição (na acepção do D.L. Nº46/2008 de 12 de Março). | D16: vg | E16: 1 | F16: 173610.4 | G16: 173610.4
A18: 1.1 | B18: ESTALEIRO E TRABALHOS COMPLEMENTARES | G18: 173610.4
A20: 1 | B20: ESTALEIRO | G20: 173610.4 | H20: =G20 -> 173610.4
A23: 2 | B23: ARQUITECTURA
A25: 2.1 | B25: ALVENARIAS E PARAMENTOS LEVES
A27: 2.1.1 | B27: ALVENARIAS EXTERIORES
A29: 2.1.1.1 | B29: Fornecimento e execução de parede exterior com 1 pano de tijolo térmico Preceram com 25cm de espessura, incluindo argamassa de assentamento ao traço 1:4, vergas de betão armado sobre vãos, gatos de travamento em aço inox entre alvenarias e estrutura de betão e todos os trabalhos preparatórios e acessórios necessários a um perfeito acabamento. (PE-A) (PE-B) (PE-C) (PE-D) (PE-E) (PE-P) (PE-F) | D29: m2 | E29: 155.42 | F29: 50.66 | G29: 7873.58
A31: 2.1.1.2 | B31: Fornecimento e execução de parede exterior com 1 pano em alvenaria de tijolo cerâmico com 30x20x15cm, incluindo argamassa de assentamento ao traço 1:4, vergas de betão armado sobre vãos e todos os trabalhos preparatórios e acessórios necessários a um perfeito acabamento. (PE-M) (PE-N) | D31: m2 | E31: 32.57 | F31: 32 | G31: 1042.24
A33: 2.1.1.3 | B33: Fornecimento e execução de parede exterior com 1 pano em alvenaria de tijolo cerâmico com 30x20x11cm, incluindo argamassa de assentamento ao traço 1:4, vergas de betão armado sobre vãos, nos intervalos de caixas de ar prever canaleta em betonilha com pendente para escoamento de águas de condensação para ralo com saída, e todos os trabalhos preparatórios e acessórios necessários a um perfeito acabamento. (PE-H) (PE-K) (PE-L) | D33: m2 | E33: 144.31 | F33: 28.06
A35: 2.1.2 | B35: ALVENARIAS INTERIORES
A37: 2.1.2.1 | B37: Fornecimento e execução de paredes interiores com 1 pano em alvenaria de tijolo cerâmico com 30x20x15cm, incluindo argamassa de assentamento ao traço 1:4, vergas de betão armado sobre vãos e todos os trabalhos preparatórios e acessórios necessários a um perfeito acabamento. (PI-A) (PI-B) | D37: m2 | E37: 152.25 | F37: 32 | G37: 4872
A39: 2.1.2.2 | B39: Fornecimento e execução de paredes interiores com 1 pano em alvenaria de tijolo cerâmico com 30x20x7cm, incluindo argamassa de assentamento ao traço 1:4, vergas de betão armado sobre vãos e todos os trabalhos preparatórios e acessórios necessários a um perfeito acabamento. (PI-C) | D39: m2 | E39: 14.64 | F39: 25.22 | G39: 369.22
A41: 2.1.2.3 | B41: Fornecimento e execução de paredes interiores com 2 panos em alvenaria de tijolo cerâmico com 30x20x11cm + caixa de ar 3cm + 30x20x11cm, incluindo argamassa de assentamento ao traço 1:4, vergas de betão armado sobre vãos e todos os trabalhos preparatórios e acessórios necessários a um perfeito acabamento. (PI-D) (PI-E) | D41: m2 | E41: 48.01 | F41: 56.13 | G41: 2694.8
A43: 2.1.3 | B43: PARAMENTOS LEVES INTERIORES
A45: 2.1.3.1 | B45: Fornecimento e execução de revestimento em placas de gesso cartonado de 12mm, em faces interiores das paredes exteriores, sistema de dupla placagem, preenchimento interior com lã de rocha com 9cm de espessura, incluindo estrutura perfilada para suporte das placas com montantes de 90mm, sistema de fixação, tratamento de juntas, barramento e preparação final para receber pintura ou revestimento final e todos os trabalhos preparatórios e acessórios necessários a um perfeito acabamento. (PE-P) | D45: m2 | E45: 19.35 | F45: 54.18 | G45: 1048.38
A47: 2.1.3.2 | B47: Fornecimento e execução de revestimento em placas de gesso cartonado standard de 12mm, em faces interiores das paredes exteriores, sistema de dupla placagem, preenchimento interior com lã de rocha com 5cm de espessura, incluindo estrutura perfilada para suporte das placas com montantes de 48mm, sistema de fixação, tratamento de juntas, barramento e preparação final para receber pintura ou revestimento final e todos os trabalhos preparatórios e acessórios necessários a um perfeito acabamento. (PE-C) (PE-D) (PI-G) | D47: m2 | E47: 37.64 | F47: 52.76 | G47: 1985.89
A49: 2.1.3.3 | B49: Fornecimento e execução de revestimento em placas de gesso cartonado hidrófugo de 12mm, em faces interiores das paredes exteriores, sistema de dupla placagem, preenchimento interior com lã de rocha com 5cm de espessura, incluindo estrutura perfilada para suporte das placas com montantes de 48mm, sistema de fixação, tratamento de juntas, barramento e preparação final para receber pintura ou revestimento final e todos os trabalhos preparatórios e acessórios necessários a um perfeito acabamento. (PE-I) (PI-H) | D49: m2 | E49: 20.27 | F49: 62.72 | G49: 1271.33
A51: 2.1.3.4 | B51: Fornecimento e execução de revestimento em placas de gesso cartonado hidrófugo de 12mm, em faces interiores das paredes exteriores, sistema de dupla placagem, preenchimento interior com lã de rocha com 3cm de espessura, incluindo estrutura perfilada para suporte das placas com montantes de 30mm, sistema de fixação, tratamento de juntas, barramento e preparação final para receber pintura ou revestimento final e todos os trabalhos preparatórios e acessórios necessários a um perfeito acabamento. (PE-J) | D51: m2 | E51: 10.99 | F51: 60.65 | G51: 666.54
A53: 2.1.3.5 | B53: Fornecimento e montagem de paramentos leves em dupla placagem de gesso cartonado hidrófugo de 12mm por face, revestidas interiormente com isolamento acustico de lã de rocha de 5cm, incluindo estrutura perfilada para suporte das placas com montantes de 48mm, sistema de fixação, tratamento de juntas, barramento e preparação final para receber pintura e todos os trabalhos preparatórios e acessórios necessários a um perfeito acabamento. (PI-F) | D53: m2 | E53: 17.94 | F53: 52.76 | G53: 946.51
A55: 2.1.3.6 | B55: Fornecimento e montagem de paramentos leves em placagem simples de MDF hidrófugo 19mm lacado por face, com acabamento mate à cor RAL 9003, revestidas interiormente com isolamento acustico de lã de rocha de 4cm, incluindo estrutura em tubo FACAR de 4cm para suporte das placas, sistema de fixação e todos os trabalhos preparatórios e acessórios necessários a um perfeito acabamento. (PI-I) (PR06) | D55: m2 | E55: 12.91 | F55: 71.12 | G55: 918.16
A57: 2.1 | B57: ALVENARIAS E PARAMENTOS LEVES | G57: 27737.99 | H57: =G57 -> 27737.99
A60: 2.2 | B60: SOLEIRAS EM BETÃO
A62: 2.2.1 | B62: SOLEIRAS EM BETÃO
A64: 2.2.1.1 | B64: Fornecimento e execução de soleiras em betão com barramento, conforme detalhe PORM10, sobre-elevada 1cm com apoios de borracha ao critério do executante, incluindo cortes, remates e todos os trabalhos preparatórios e acessórios necessários a um perfeito acabamento.
A66: 2.2.1.1.1 | B66: Soleira VE 01.1 - Dimensão de 1.10m. | D66: un | E66: 1 | F66: 45.48 | G66: 45.48
A68: 2.2.1.1.2 | B68: Soleira VE 01.2 - Dimensão de 4.68m. | D68: un | E68: 1 | F68: 193.49 | G68: 193.49
A70: 2.2.1.1.3 | B70: Soleira VE 01.3 - Dimensão de 4.61m. | D70: un | E70: 1 | F70: 190.6 | G70: 190.6
A72: 2.2.1.1.4 | B72: Soleira VE 01.4 - Dimensão de 3.04m. | D72: un | E72: 1 | F72: 125.69 | G72: 125.69
A74: 2.2.1.2 | B74: Fornecimento e execução de soleiras estreitas entre vãos do piso 1, em peças de betão com barramento, conforme detalhe PORM10, sobre-elevada 1cm com apoios de borracha ao critério do executante, incluindo cortes, remates e todos os trabalhos preparatórios e acessórios necessários a um perfeito acabamento.
A76: 2.2.1.2.1 | B76: Soleira A - Dimensão de 400x70mm. | D76: un | E76: 1 | F76: 14.6 | G76: 14.6
A78: 2.2.1.2.2 | B78: Soleira B - Dimensão de 3960x70mm. | D78: un | E78: 1 | F78: 144.54 | G78: 144.54
A80: 2.2.1.2.3 | B80: Soleira C - Dimensão de 5300x70mm. | D80: un | E80: 1 | F80: 193.45 | G80: 193.45
A82: 2.2.1.2.4 | B82: Soleira D - Dimensão de 1390x70mm. | D82: un | E82: 1 | F82: 507.36 | G82: 507.36
A84: 2.2.1.2.5 | B84: Soleira E - Dimensão de 1040x70mm. | D84: un | E84: 1 | F84: 37.96 | G84: 37.96
A86: 2.2 | B86: SOLEIRAS EM BETÃO | G86: 1453.17
A89: 2.3 | B89: IMPERMEABILIZAÇÕES E ISOLAMENTOS
A91: 2.3.1 | B91: EM COBERTURA #2 e #3
A93: 2.3.1.1 | B93: Fornecimento e execução de impermeabilização de Coberturas Planas (#2 e #3) do Piso 1 (não acessivel), incluindo todos os trabalhos preparatórios e acessórios necessários a um perfeito acabamento, de acordo com os seguintes trabalhos:
A95: 2.3.1.1.1 | B95: Isolamento térmico em placas de poliestireno extrudido "IFOAM COBERTURAS" com 8cm de espessura, incluindo cortes, remates. | D95: m2 | E95: 37.14 | F95: 11.9 | G95: 441.97
A97: 2.3.1.1.2 | B97: Camada de forma em betão leve para regularização e criação de caleiras e pendentes na espessura necessária, com acabamento afagado para o assentamento de telas. | D97: m2 | E97: 37.14 | F97: 23.36 | G97: 867.59
A99: 2.3.1.1.3 | B99: Sistema de impermeabilização tipo "Imperalum" com pintura a Imperkote L, sistema de impermeabilização com duas telas cruzadas tela POLYPLAS 30 + POLYXIS R40 (as telas sobem nos muretes, fazendo capeamento sendo fixas a estes com cantoneiras apropriadas ou outros), tela separador em tecido de poliester calandrado tipo "IMPERSEP 200" incluindo cortes, remates, fixações, tudo pronto para receber revestimento final. | D99: m2 | E99: 37.14 | F99: 31.78 | G99: 1180.31
A101: 2.3.2 | B101: EM VARANDA
A103: 2.3.2.1 | B103: Fornecimento e execução de impermeabilização de Varanda do Piso 1 (acessiveis), incluindo todos os trabalhos preparatórios e acessórios necessários a um perfeito acabamento, de acordo com os seguintes trabalhos:
A105: 2.3.2.1.1 | B105: Isolamento térmico em placas de poliestireno extrudido "IFOAM COBERTURAS" com 8cm de espessura, incluindo cortes, remates. | D105: m2 | E105: 53 | F105: 11.9 | G105: 630.7
A107: 2.3.2.1.2 | B107: Betonilha com acabamento afagado para o assentamento de telas e criação de pendentes. | D107: m2 | E107: 53 | F107: 23.36 | G107: 1238.08
A109: 2.3.2.1.3 | B109: Sistema de impermeabilização tipo "Imperalum" com pintura a Imperkote L, sistema de impermeabilização com duas telas cruzadas POLYPLAS 30 + POLYXIS R40, (as telas sobem nos muretes, fazendo capeamento sendo fixas a estes com cantoneiras apropriadas ou outros), tela separador em tecido de poliester calandrado tipo "IMPERSEP 200", incluindo cortes, remates, fixações, tudo pronto para receber revestimento final. | D109: m2 | E109: 53 | F109: 31.78 | G109: 1684.34
A111: 2.3.3 | B111: EM COBERTURA DA ÁREA TÉCNICA DA PISCINA #1 E ÁREA TÉCNICA #2
A113: 2.3.3.1 | B113: Fornecimento e execução de impermeabilização de Cobertura Plana da Área Técnica #1 e Tanque de Compensação, Área Técnica #2, incluindo todos os trabalhos preparatórios e acessórios necessários a um perfeito acabamento, de acordo com os seguintes trabalhos:
A115: 2.3.3.1.1 | B115: Betonilha com acabamento afagado para o assentamento de telas e criação de pendentes. | D115: m2 | E115: 32.4 | F115: 23.36 | G115: 756.86
A117: 2.3.3.1.2 | B117: Sistema de impermeabilização tipo "Imperalum" com pintura a Imperkote L, sistema de impermeabilização com duas telas cruzadas POLYPLAS 30 + POLYXIS R40, (as telas sobem nos muretes, fazendo capeamento sendo fixas a estes com cantoneiras apropriadas ou outros), tela separador em tecido de poliester calandrado tipo "IMPERSEP 200", incluindo cortes, remates, fixações, tudo pronto para receber revestimento final. | D117: m2 | E117: 32.4 | F117: 31.78 | G117: 1029.67
A119: 2.3.4 | B119: EM PARAMENTOS ENTERRADOS
A121: 2.3.4.1 | B121: Fornecimento e execução de sistema de drenagem das paredes enterradas através da aplicação de tela drenante pitonada tipo "Aguadrain" ou equivalente, fixa aos paramentos de betão armado, incluindo tubo geodreno no fundo da vala envolto em brita, ligação à rede de drenagem, caixas, sistema de fixação, cortes, remates e todos os trabalhos preparatórios e acessórios. | D121: m2 | E121: 303.47 | F121: 22.54 | G121: 6840.21
A123: 2.3.5 | B123: EM LAJES INTERIORES
A125: 2.3.5.1 | B125: Fornecimento e execução de Isolamento térmico de lajes interiores (#2 e #3) com placas de poliestireno extrudido "XPS" com 8cm de espessura assente sobre manta acústica Impactodam de 10mm, de acordo com desenho de pormenor, incluindo cortes, remates e todos os trabalhos preparatórios e acessórios. | D125: m2 | E125: 320.7 | F125: 11.9 | G125: 3816.33
A127: 2.3.6 | B127: EM BASES DE DUCHE
A129: 2.3.6.1 | B129: Fornecimento e execução de impermeabilização de bases de duche no pavimento com argamassa cimentícia bicomponente elástica tipo "Mapelastic Smart" ou equivalente, armado com rede de fibra de vidro com tratamento anti-alcalino, com subida até 30cm nas paredes, incluindo todos os trabalhos preparatórios e acessórios necessários a um perfeito acabamento. | D129: un | E129: 22.19 | F129: 29.09 | G129: 645.51
A131: 2.3.7 | B131: SISTEMA DE IMPERMEABILIZAÇÃO DA PISCINA E ESPELHOS DE ÁGUA
A133: 2.3.7.1 | B133: Fornecimento e execução de sistema da "IMPERALUM" para impermeabilização da piscina e espelhos de água, constituido por aplicação pintura a Imperkote F, sistema de duas telas cruzadas POLYPLAS 30 + POLYXIS R40T + POLYBANCA 33, separador em tecido de poliester calandrado, IMPERSEP 150 (no fundo e nos cantos), sistema de 1 tela POLYXIS R50 nos paramentos verticais, pronto para receber acabamento final, tudo de acordo com desenhos de pormenor, incluindo cortes e remates e todos os trabalhos preparatórios e acessórios a um perfeito acabamento. | D133: m2 | E133: 200.6 | F133: 23.04 | G133: 4621.82
A135: 2.3 | B135: IMPERMEABILIZAÇÕES E ISOLAMENTOS | G135: 23753.39 | H135: =G135 -> 23753.39
A138: 2.4 | B138: COBERTURA
A140: 2.4.1 | B140: Fornecimento e montagem de revestimento de cobertura #1 com chapas de zinco lacadas a branco RAL 9003, com junta agrafada tipo "Double Lock", assente sobre camada de ventilação tipo "AGUADRAIN GEO" e Membrana de impermeabilização tipo "RHENOFOL CV", isolamento térmico XPS de 8cm pelo interior e camada de lã de rocha com 17cm entre OSB, conforme desenho de pormenor, incluindo execução de caleira e capeamentos em zinco, cortes, remates, elementos de fixação e todos os trabalhos preparatórios e acessórios necessários a um perfeito acabamento. (PV15) | D140: m2 | E140: 181.91 | F140: 290.82 | G140: 52903.07
A142: 2.4.2 | B142: Fornecimento e aplicação de revestimento a seixo rolado miudo cinza, numa espessura de 10cm, em cobertura plana #2 e #3 (não acessivel), incluindo carga, transporte, espanhamento e todos os trabalhos preparatórios e acessórios necessários a um perfeito acabamento. (PV12) | D142: m2 | E142: 37.14 | F142: 29.31 | G142: 1088.57
A144: 2.4.3 | B144: Fornecimento e execução de capeamentos de muretes da cobertura #2 e #3 (não acessivel) em chapa de metálica zincada, incluindo cortes, remates, elementos de fixação, criação de pendentes, conforme elementos do projecto, e todos os trabalhos preparatórios e acessórios necessários a um perfeito acabamento. | D144: m2 | E144: 15.09 | F144: 323.28 | G144: 4878.3
A146: 2.4.4 | B146: Fornecimento e execução de chaminé metálica da lareira de acordo com o desenho de pormenor, incluindo tubo metálico de exaustão, isolamentos de estanquicidade, cortes, remates, ligações e todos os trabalhos preparatórios e acessórios necessários a um perfeito acabamento. | D146: un | E146: 2 | F146: 581.9 | G146: 1163.8
A148: 2.4 | B148: COBERTURA | G148: 60033.74 | H148: =G148 -> 60033.74
A151: 2.5 | B151: REVESTIMENTO DE TECTOS
A153: 2.5.1 | B153: TECTOS EXTERIORES
A155: 2.5.1.1 | B155: Fornecimento e execução de revestimento de tectos de betão aparente com acabamento hidrofugante, da "SIKAGARD 680-S PT", incolor mate, incluindo preparação da base com corte de rebarbas de betão, preenchimento de chochos com materiais apropriados, preparação geral das superficies, aplicação de primário e todos os trabalhos preparatórios e acessórios necessários a um perfeito acabamento. (TE04) | D155: m2 | E155: 42.56 | F155: 12.93 | G155: 550.3
A157: 2.5.2 | B157: TECTOS INTERIORES
A159: 2.5.2.1 | B159: Fornecimento e execução de revestimento de tectos de betão aparente com acabamento hidrofugante, da "SIKAGARD 680-S PT", incolor mate, incluindo preparação da base com corte de rebarbas de betão, preenchimento de chochos com materiais apropriados, preparação geral das superficies, aplicação de primário e todos os trabalhos preparatórios e acessórios necessários a um perfeito acabamento. (TE01) | D159: m2 | E159: 331.34 | F159: 12.93 | G159: 4284.23
A161: 2.5.2.2 | B161: Fornecimento e montagem de tectos falsos continuos com placas de gesso cartonado de 12mm, "KNAUF KS STANDARD", incluindo alheta com 10mmx10mm com perfil do sistema, estrutura de suporte, sistema de fixação, execução de aberturas para colocação de equipamentos diversos, recaídas, tratamento de juntas, barramento e preparação final para receber pintura e todos os trabalhos preparatórios e acessórios necessários a um perfeito acabamento. (TE02) | D161: m2 | E161: 170.41 | F161: 32.2 | G161: 5487.2
A163: 2.5.2.3 | B163: Fornecimento e montagem de tectos falsos continuos com placas de gesso cartonado hidrofugo de 12mm, "KNAUF HIDROFUGA H1", incluindo alheta com 10mmx10mm com perfil do sistema, estrutura de suporte, sistema de fixação, execução de aberturas para colocação de equipamentos diversos, recaídas, tratamento de juntas, barramento e preparação final para receber pintura e todos os trabalhos preparatórios e acessórios necessários a um perfeito acabamento. (TE03) | D163: m2 | E163: 59.45 | F163: 38.66 | G163: 2298.34
A165: 2.5.2.4 | B165: Fornecimento e execução de sanca em tectos falsos de gesso cartonado, conforme desenho de pormenor, com barramento e preparação final para receber pintura, incluindo todos os trabalhos preparatórios e acessórios necessários a um perfeito acabamento. | D165: ml | E165: 11.9 | F165: 38.66 | G165: 460.05
A167: 2.5.2.5 | B167: Fornecimento e execução de pintura a tinta aquosa, "CIN - VINYLMATE - Ref.ª 10-250", acabamento extra mate, na cor branco RAL 9003, em 2 a 3 demãos, incluindo limpeza prévia de superfícies, aplicação de 1 demão de primário "EP/GC 300 - Ref.ª 10-600" e todos os trabalhos preparatórios e acessórios necessários a um perfeito acabamento. (PR02) | D167: m2 | E167: 229.86 | F167: 10.34 | G167: 2376.75
A169: 2.5 | B169: REVESTIMENTO DE TECTOS | G169: 15456.87 | H169: =G169 -> 15456.87
A172: 2.6 | B172: REVESTIMENTO DE PAREDES
A174: 2.6.1 | B174: PAREDES EXTERIORES
A176: 2.6.1.1 | B176: Fornecimento e execução de revestimento de paredes de betão aparente com acabamento hidrofugante, da "SIKAGARD 680-S PT", incolor mate, incluindo preparação da base com corte de rebarbas de betão, preenchimento de chochos com materiais apropriados, preparação geral das superficies, aplicação de primário e todos os trabalhos preparatórios e acessórios necessários a um perfeito acabamento. (PR08) | D176: m2 | E176: 110.6 | F176: 12.93 | G176: 1430.06
A178: 2.6.1.2 | B178: Fornecimento e execução de barramento "WEBER REV PASTA CINZA RAL 7035 da marca SAINT-GOBAIN", incluindo todos os trabalhos preparatórios e acessórios necessários a um perfeito acabamento. (PR09) | D178: m2 | E178: 319.19 | F178: 35.96 | G178: 11478.07
A180: 2.6.1.3 | B180: Fornecimento e execução de revestimento de fachadas com sistema completo "ETICS - WEBER REV PASTA CINZA RAL 7035 da marca SAINT-GOBAIN", constituido por argamassa de colagem, isolamento térmico com placas de poliestireno expandido moldado de 7cm de espessura, duas camadas de argamassa de revestimento separadas entre elas por rede de reforço, rede normal, primário de regularização, regulador e acabamento final, incluindo buchas e acessórios de fixação, perfis e cantoneiras de remate e todos os trabalhos preparatórios e acessórios necessários a um perfeito acabamento. (PR10) | D180: m2 | E180: 131.48 | F180: 75 | G180: 9861
A182: 2.6.1.4 | B182: Fornecimento e montagem de sistema de fachada acabada a chapa de aluminio 5mm lacada a cor branca RAL 9003 com sistema colado da marca "CORTIZO" e sub-estrutura perfil T e isolamento XPS 7cm, incluindo cortes, remates e todos os trabalhos preparatórios e acessórios necessários a um perfeito acabamento. (PR11) | D182: m2 | E182: 106.79 | F182: 234.7 | G182: 25063.61
A184: 2.6.1.5 | B184: Fornecimento e execução de reboco areado fino ao traço 1:4, em fachadas e pérgola, tudo pronto para receber pintura ou barramento final, incluindo salpico, emboço e todos os trabalhos preparatórios e acessórios necessários a um perfeito acabamento. (PR09) (PR14) | D184: m2 | E184: 353.75 | F184: 31.79 | G184: 11245.71
A186: 2.6.1.6 | B186: Fornecimento e execução de pintura a tinta 100% acrilíca, "CIN - NOVATEX - Ref.ª 12-230", na cor Cinza RAL 7035, em 2 a 3 demãos, sobre reboco, incluindo limpeza prévia de superfícies, aplicação de 1 demão de primário "EP/GC 300 - Ref.ª 10-600" e todos os trabalhos preparatórios e acessórios necessários a um perfeito acabamento. (PR14) | D186: m2 | E186: 34.56 | F186: 12.93 | G186: 446.86
A188: 2.6.2 | B188: PAREDES INTERIORES
A190: 2.6.2.1 | B190: Fornecimento e execução de revestimento de paredes de betão aparente com acabamento hidrofugante, da "SIKAGARD 680-S PT", incolor mate, incluindo preparação da base com corte de rebarbas de betão, preenchimento de chochos com materiais apropriados, preparação geral das superficies, aplicação de primário e todos os trabalhos preparatórios e acessórios necessários a um perfeito acabamento. (PR01) | D190: m2 | E190: 52 | F190: 12.93 | G190: 672.36
A192: 2.6.2.2 | B192: Fornecimento e execução de estuque projectado, incluindo barramento em massa fina, reforço com rede de fibra de vidro 5x5cm (75g/m2) na transição betão/alvenaria e perfis cobre-cantos em pvc reforçado com rede de fibra, tudo pronto para receber pintura e todos os trabalhos preparatórios e acessórios necessários a um perfeito acabamento. (PR02) (PR03) | D192: m2 | E192: 466.94 | F192: 19.4 | G192: 9058.64
A194: 2.6.2.3 | B194: Fornecimento e assentamento de revestimento em pastilha "CLASSIC BRANCO 30x30cm da marca "RUBICER" e com juntas em betume cinza claro RAL 7035, incluindo reboco base sarrafado em paramentos de alvenaria, argamassa de assentamento ou cola, cortes, remates, betumagem de juntas e todos os trabalhos preparatórios e acessórios necessários a um perfeito acabamento. (PR5.1) | D194: m2 | E194: 81.43 | F194: 103.64 | G194: 8439.41
A196: 2.6.2.4 | B196: Fornecimento e assentamento de revestimento em pastilha "GREY 30x30cm da marca "RUBICER" e com juntas em betume branco RAL 9003, incluindo reboco base sarrafado em paramentos de alvenaria, argamassa de assentamento ou cola, cortes, remates, betumagem de juntas e todos os trabalhos preparatórios e acessórios necessários a um perfeito acabamento. (PR5.2) | D196: m2 | E196: 46.05 | F196: 118.58 | G196: 5460.61
A198: 2.6.2.5 | B198: Fornecimento e execução de reboco estanhado, incluindo salpico, emboço e todos os trabalhos preparatórios e acessórios necessários a um perfeito acabamento. (PR07) | D198: m2 | E198: 50.7 | F198: 32.46 | G198: 1645.72
A200: 2.6.2.6 | B200: Fornecimento e execução de pintura a tinta aquosa, "CIN - VINYLCLEAN MATE - Ref.ª 10-245", na cor branco RAL 9003, em 2 a 3 demãos, aplicada em paredes estucadas e/ou gesso cartonado, incluindo limpeza prévia de superfícies, aplicação de 1 demão de primário "EP/GC 300 - Ref.ª 10-600" e todos os trabalhos preparatórios e acessórios necessários a um perfeito acabamento. (PR02) (PR04) | D200: m2 | E200: 551.51 | F200: 10.34 | G200: 5702.61
A202: 2.6.2.7 | B202: Fornecimento e execução de pintura a tinta de esmalte aquoso acrílico, "CIN - CINACRYL MATE - Ref.ª 10-230", na cor branco RAL 9003, em 2 a 3 demãos, aplicada em paredes estucadas e/ou gesso cartonado, incluindo limpeza prévia de superfícies, aplicação de 1 demão de primário "EP/GC 300 - Ref.ª 10-600" e todos os trabalhos preparatórios e acessórios necessários a um perfeito acabamento. (PR03) (PR04) | D202: m2 | E202: 21.34 | F202: 10.34 | G202: 220.66
A204: 2.6 | B204: REVESTIMENTO DE PAREDES | G204: 90725.32 | H204: =G204 -> 90725.32
A207: 2.7 | B207: REVESTIMENTO DE PAVIMENTOS E RODAPÉS
A209: 2.7.1 | B209: PAVIMENTOS EXTERIORES
...

Sheet Orcamento ENG
A4: Item | B4: Description | D4: UN | E4: Quantidade | F4: PREÇO
F5: Unitário | G5: T O T A L
D8: Units | E8: Quantity | F8: Unit Price | G8: Total | H8: My Unit Price | I8: My total Price | J8: My Savings
B10: HOUSING EXECUTION - URB. DAS GAIVOTAS MATA PORCAS, PRAIA DA LUZ
A12: 1 | B12: Site Setup
A14: 1.1 | B14: Site set up AND COMPLEMENTARY WORKS
A16: 1.1.1 | B16: Assembly, construction, maintenance, disassembly and demolition of a construction site, including the corresponding installations, temporary water, sewage, electricity and telecommunications networks, internal circulation routes and everything else necessary in accordance with Decree-Law no. October 29th and other legislation in force, Development and Implementation of the Construction and Demolition Waste Prevention and Management Plan (within the meaning of D.L. No. 46/2008 of March 12th). | D16: vg | E16: 1 | F16: 173610.4 | G16: 173610.4
A18: 1.1 | B18: Site Setup AND COMPLEMENTARY WORKS | G18: 173610.4
A20: 1 | B20: Site Setup | G20: 173610.4 | H20: =G20 -> 173610.4
A23: 2 | B23: ARCHITECTURE
A25: 2.1 | B25: MASONRY AND LIGHTWEIGHT PAMENTS
A27: 2.1.1 | B27: EXTERIOR MASONRY
A29: 2.1.1.1 | B29: Supply and execution of an external wall with 1 sheet of Preceram thermal brick 25cm thick, including laying mortar in a 1:4 ratio, reinforced concrete lintels over gaps, stainless steel locking cats between masonry and concrete structure and all preparatory work and accessories necessary for a perfect finish. (PE-A) (PE-B) (PE-C) (PE-D) (PE-E) (PE-P) (PE-F) | D29: m2 | E29: 155.42 | F29: 50.66 | G29: 7873.58
A31: 2.1.1.2 | B31: Supply and execution of an exterior wall with 1 panel in ceramic brick masonry measuring 30x20x15cm, including laying mortar at 1:4, reinforced concrete lintels over gaps and all preparatory work and accessories necessary for a perfect finish. (PE-M) (PE-N) | D31: m2 | E31: 32.57 | F31: 32 | G31: 1042.24
A33: 2.1.1.3 | B33: Supply and execution of an external wall with 1 panel in ceramic brick masonry measuring 30x20x11cm, including laying mortar in a 1:4 line, reinforced concrete lintels over gaps, in the intervals between air boxes provide a channel in the subfloor with a slope for the drainage of condensation water to a drain with an exit, and all the preparatory work and accessories necessary for a perfect finish. (PE-H) (PE-K) (PE-L) | D33: m2 | E33: 144.31 | F33: 28.06 | G33: 4049.34
A35: 2.1.2 | B35: INTERIOR MASONRY
A37: 2.1.2.1 | B37: Supply and execution of interior walls with 1 panel in ceramic brick masonry measuring 30x20x15cm, including laying mortar at 1:4, reinforced concrete lintels over gaps and all preparatory work and accessories necessary for a perfect finish. (PI-A) (PI-B) | D37: m2 | E37: 152.25 | F37: 32 | G37: 4872
A39: 2.1.2.2 | B39: Supply and execution of interior walls with 1 panel in ceramic brick masonry measuring 30x20x7cm, including laying mortar at 1:4, reinforced concrete lintels over gaps and all preparatory work and accessories necessary for a perfect finish. (PI-C) | D39: m2 | E39: 14.64 | F39: 25.22 | G39: 369.22
A41: 2.1.2.3 | B41: Supply and execution of interior walls with 2 panels in ceramic brick masonry measuring 30x20x11cm + air box 3cm + 30x20x11cm, including laying mortar at 1:4, reinforced concrete lintels over gaps and all preparatory work and accessories necessary for a perfect finish. (PI-D) (PI-E) | D41: m2 | E41: 48.01 | F41: 56.13 | G41: 2694.8
A43: 2.1.3 | B43: LIGHT INTERIOR APPLIANCES
A45: 2.1.3.1 | B45: Supply and execution of cladding in 12mm plasterboard sheets, on the interior sides of the exterior walls, double plating system, interior filling with 9cm thick rock wool, including profiled structure to support the boards with 90mm uprights, fixing system, joint treatment, smoothing and final preparation to receive painting or final coating and all preparatory work and accessories necessary for a perfect finish. (PE-P) | D45: m2 | E45: 19.35 | F45: 54.18 | G45: 1048.38
A47: 2.1.3.2 | B47: Supply and execution of cladding in standard 12mm plasterboard sheets, on the interior sides of exterior walls, double plating system, interior filling with 5cm thick rock wool, including profiled structure to support the boards with 48mm uprights, fixing system, joint treatment, smoothing and final preparation to receive painting or final coating and all preparatory work and accessories necessary for a perfect finish. (PE-C) (PE-D) (PI-G) | D47: m2 | E47: 37.64 | F47: 52.76 | G47: 1985.89
A49: 2.1.3.3 | B49: Supply and execution of cladding in 12mm water-repellent plasterboard sheets, on the interior sides of exterior walls, double plating system, interior filling with 5cm thick rock wool, including profiled structure to support the boards with 48mm uprights, fixing system, joint treatment, smoothing and final preparation to receive painting or final coating and all preparatory work and accessories necessary for a perfect finish. (PE-I) (PI-H) | D49: m2 | E49: 20.27 | F49: 62.72 | G49: 1271.33
A51: 2.1.3.4 | B51: Supply and execution of cladding in 12mm water-repellent plasterboard sheets, on the interior sides of exterior walls, double plating system, interior filling with 3cm thick rock wool, including profiled structure to support the boards with 30mm uprights, fixing system, joint treatment, smoothing and final preparation to receive painting or final coating and all preparatory work and accessories necessary for a perfect finish. (PE-J) | D51: m2 | E51: 10.99 | F51: 60.65 | G51: 666.54
A53: 2.1.3.5 | B53: Supply and assembly of lightweight walls in double 12mm water-repellent plasterboard panels per side, internally coated with 5cm rock wool acoustic insulation, including profiled structure to support the plates with 48mm uprights, fixing system, joint treatment, sealing and final preparation to receive painting and all preparatory work and accessories necessary for a perfect finish. (PI-F) | D53: m2 | E53: 17.94 | F53: 52.76 | G53: 946.51
A55: 2.1.3.6 | B55: Supply and assembly of lightweight walls in simple 19mm water-repellent MDF board, lacquered on each side, with a matte finish in the color RAL 9003, covered internally with 4cm rock wool acoustic insulation, including a 4cm FACAR tube structure to support the plates, fixing system and all preparatory work and accessories necessary for a perfect finish. (PI-I) (PR06) | D55: m2 | E55: 12.91 | F55: 71.12 | G55: 918.16
A57: 2.1 | B57: MASONRY AND LIGHTWEIGHT PAMENTS | G57: 27737.99 | H57: =G57 -> 27737.99
A60: 2.2 | B60: CONCRETE SILLS
A62: 2.2.1 | B62: CONCRETE SILLS
A64: 2.2.1.1 | B64: Supply and execution of concrete sills with bars, according to detail PORM10, raised 1cm with rubber supports at the discretion of the executor, including cuts, finishes and all preparatory work and accessories necessary for a perfect finish.
A66: 2.2.1.1.1 | B66: Threshold VE 01.1 - Dimension 1.10m. | D66: un | E66: 1 | F66: 45.48 | G66: 45.48
A68: 2.2.1.1.2 | B68: Threshold VE 01.2 - Dimension 4.68m. | D68: un | E68: 1 | F68: 193.49 | G68: 193.49
A70: 2.2.1.1.3 | B70: Threshold VE 01.3 - Dimension 4.61m. | D70: un | E70: 1 | F70: 190.6 | G70: 190.6
A72: 2.2.1.1.4 | B72: Threshold VE 01.4 - Dimension 3.04m. | D72: un | E72: 1 | F72: 125.69 | G72: 125.69
A74: 2.2.1.2 | B74: Supply and execution of narrow sills between gaps on the 1st floor, in concrete parts with bars, according to detail PORM10, raised 1cm with rubber supports at the discretion of the contractor, including cuts, finishes and all preparatory work and accessories necessary for a perfect finish.
A76: 2.2.1.2.1 | B76: Threshold A - Dimensions 400x70mm. | D76: un | E76: 1 | F76: 14.6 | G76: 14.6
A78: 2.2.1.2.2 | B78: Threshold B - Dimensions 3960x70mm. | D78: un | E78: 1 | F78: 144.54 | G78: 144.54
A80: 2.2.1.2.3 | B80: Threshold C - Dimensions 5300x70mm. | D80: un | E80: 1 | F80: 193.45 | G80: 193.45
A82: 2.2.1.2.4 | B82: Threshold D - Dimensions 1390x70mm. | D82: un | E82: 1 | F82: 507.36 | G82: 507.36
A84: 2.2.1.2.5 | B84: Threshold E - Dimensions 1040x70mm. | D84: un | E84: 1 | F84: 37.96 | G84: 37.96
A86: 2.2 | B86: CONCRETE SILLS | G86: 1453.17
A89: 2.3 | B89: WATERPROOFING AND INSULATION
A91: 2.3.1 | B91: IN COVERAGE #2 and #3
A93: 2.3.1.1 | B93: Supply and execution of waterproofing of Flat Roofs (#2 and #3) on Floor 1 (non-accessible), including all preparatory work and accessories necessary for a perfect finish, in accordance with the following works:
A95: 2.3.1.1.1 | B95: Thermal insulation in extruded polystyrene plates "IFOAM COBERTURAS" 8cm thick, including cuts, finishes. | D95: m2 | E95: 37.14 | F95: 11.9 | G95: 441.97
A97: 2.3.1.1.2 | B97: Formwork layer in light concrete for regularizing and creating gutters and slopes of the required thickness, with a smooth finish for laying screens. | D97: m2 | E97: 37.14 | F97: 23.36 | G97: 867.59
A99: 2.3.1.1.3 | B99: "Imperalum" type waterproofing system with Imperkote L painting, waterproofing system with two crossed screens POLYPLAS 30 + POLYXIS R40 screen (the screens go up on the walls, creating caps and fixed to them with appropriate angles or others), separator screen in calendered polyester fabric type "IMPERSEP 200" including cuts, finishes, fixings, all ready to receive final coating. | D99: m2 | E99: 37.14 | F99: 31.78 | G99: 1180.31
A101: 2.3.2 | B101: ON BALCONY
A103: 2.3.2.1 | B103: Supply and execution of waterproofing of the 1st Floor Balcony (accessible), including all preparatory work and accessories necessary for a perfect finish, in accordance with the following works:
A105: 2.3.2.1.1 | B105: Thermal insulation in extruded polystyrene plates "IFOAM COBERTURAS" 8cm thick, including cuts, finishes. | D105: m2 | E105: 53 | F105: 11.9 | G105: 630.7
A107: 2.3.2.1.2 | B107: Screed with a smooth finish for laying screens and creating pendants. | D107: m2 | E107: 53 | F107: 23.36 | G107: 1238.08
A109: 2.3.2.1.3 | B109: "Imperalum" type waterproofing system with Imperkote L painting, waterproofing system with two crossed screens POLYPLAS 30 + POLYXIS R40, (the screens go up on the walls, creating caps and fixed to them with appropriate angles or others), separator screen in calendered polyester fabric type "IMPERSEP 200", including cuts, finishes, fixings, all ready to receive final coating. | D109: m2 | E109: 53 | F109: 31.78 | G109: 1684.34
A111: 2.3.3 | B111: COVERING THE TECHNICAL AREA OF POOL #1 AND TECHNICAL AREA #2
A113: 2.3.3.1 | B113: Supply and execution of waterproofing of the Flat Roof of Technical Area #1 and Compensation Tank, Technical Area #2, including all preparatory work and accessories necessary for a perfect finish, in accordance with the following works:
A115: 2.3.3.1.1 | B115: Screed with a smooth finish for laying screens and creating pendants. | D115: m2 | E115: 32.4 | F115: 23.36 | G115: 756.86
A117: 2.3.3.1.2 | B117: "Imperalum" type waterproofing system with Imperkote L painting, waterproofing system with two crossed screens POLYPLAS 30 + POLYXIS R40, (the screens go up on the walls, creating caps and fixed to them with appropriate angles or others), separator screen in calendered polyester fabric type "IMPERSEP 200", including cuts, finishes, fixings, all ready to receive final coating. | D117: m2 | E117: 32.4 | F117: 31.78 | G117: 1029.67
A119: 2.3.4 | B119: IN BURIED GARMENTS
A121: 2.3.4.1 | B121: Supply and execution of a drainage system for buried walls through the application of a pitted drainage screen type "Aguadrain" or equivalent, fixed to the reinforced concrete walls, including a geodrain tube at the bottom of the trench wrapped in crushed stone, connection to the drainage network, boxes, fixing system, cuts, finishes and all preparatory work and accessories. | D121: m2 | E121: 303.47 | F121: 22.54 | G121: 6840.21
A123: 2.3.5 | B123: ON INTERIOR SLABS
A125: 2.3.5.1 | B125: Supply and execution of thermal insulation of interior slabs (#2 and #3) with 8cm thick "XPS" extruded polystyrene plates based on a 10mm Impactodam acoustic blanket, according to the detailed drawing, including cuts, finishes and all preparatory work and accessories. | D125: m2 | E125: 320.7 | F125: 11.9 | G125: 3816.33
A127: 2.3.6 | B127: IN SHOWER BASES
A129: 2.3.6.1 | B129: Supply and execution of waterproofing of shower trays on the floor with elastic two-component cement mortar type "Mapelastic Smart" or equivalent, reinforced with fiberglass mesh with anti-alkaline treatment, with a rise of up to 30cm on the walls, including all preparatory work and accessories necessary for a perfect finish. | D129: un | E129: 22.19 | F129: 29.09 | G129: 645.51
A131: 2.3.7 | B131: POOL WATERPROOFING SYSTEM AND WATER MIRRORS
A133: 2.3.7.1 | B133: Supply and execution of the "IMPERALUM" system for waterproofing the pool and water features, consisting of Imperkote F paint application, system of two crossed screens POLYPLAS 30 + POLYXIS R40T + POLYBANCA 33, separator in calendered polyester fabric, IMPERSEP 150 (at the bottom and in the corners), system of 1 screen POLYXIS R50 on the vertical walls, ready to receive a final finish, everything in accordance with detailed drawings, including cuts and finishes and all preparatory work and accessories for a perfect finish. | D133: m2 | E133: 200.6 | F133: 23.04 | G133: 4621.82
A135: 2.3 | B135: WATERPROOFING AND INSULATION | G135: 23753.39 | H135: =G135 -> 23753.39
A138: 2.4 | B138: COVERAGE
A140: 2.4.1 | B140: Supply and assembly of roof covering #1 with zinc sheets lacquered in white RAL 9003, with "Double Lock" type stapled joint, based on a "AGUADRAIN GEO" type ventilation layer and "RHENOFOL CV" type waterproofing membrane, 8cm XPS thermal insulation on the inside and a 17cm layer of rock wool between OSB, according to the detail drawing, including execution of gutter and zinc capping, cuts, finishes, fastening elements and all preparatory work and accessories necessary for a perfect finish. (PV15) | D140: m2 | E140: 181.91 | F140: 290.82 | G140: 52903.07
A142: 2.4.2 | B142: Supply and application of fine gray pebble covering, in a thickness of 10cm, on flat roofs #2 and #3 (not accessible), including loading, transport, dusting and all preparatory work and accessories necessary for a perfect finish. (PV12) | D142: m2 | E142: 37.14 | F142: 29.31 | G142: 1088.57
A144: 2.4.3 | B144: Supply and execution of wall coverings for roof #2 and #3 (not accessible) in galvanized metal sheet, including cuts, finishes, fixing elements, creation of pendants, according to project elements, and all preparatory work and accessories necessary for a perfect finish. | D144: m2 | E144: 15.09 | F144: 323.28 | G144: 4878.3
A146: 2.4.4 | B146: Supply and execution of a metal fireplace chimney in accordance with the detailed drawing, including metal exhaust pipe, watertight insulation, cuts, finishes, connections and all preparatory work and accessories necessary for a perfect finish. | D146: un | E146: 2 | F146: 581.9 | G146: 1163.8
A148: 2.4 | B148: COVERAGE | G148: 60033.74 | H148: =G148 -> 60033.74
A151: 2.5 | B151: CEILING COATING
A153: 2.5.1 | B153: EXTERIOR CEILINGS
A155: 2.5.1.1 | B155: Supply and execution of covering exposed concrete ceilings with water-repellent finish, "SIKAGARD 680-S PT", colorless matt, including preparation of the base by cutting out concrete burrs, filling of gaps with appropriate materials, general surface preparation, application of primer and all preparatory work and accessories necessary for a perfect finish. (TE04) | D155: m2 | E155: 42.56 | F155: 12.93 | G155: 550.3
A157: 2.5.2 | B157: INTERIOR CEILINGS
A159: 2.5.2.1 | B159: Supply and execution of covering exposed concrete ceilings with water-repellent finish, "SIKAGARD 680-S PT", colorless matt, including preparation of the base by cutting out concrete burrs, filling of gaps with appropriate materials, general surface preparation, application of primer and all preparatory work and accessories necessary for a perfect finish. (TE01) | D159: m2 | E159: 331.34 | F159: 12.93 | G159: 4284.23
A161: 2.5.2.2 | B161: Supply and assembly of continuous false ceilings with 12mm plasterboard sheets, "KNAUF KS STANDARD", including 10mmx10mm fin with system profile, support structure, fixing system, execution of openings for placing various equipment, recesses, joint treatment, skimming and final preparation to receive painting and all preparatory work and accessories necessary for a perfect finish. (TE02) | D161: m2 | E161: 170.41 | F161: 32.2 | G161: 5487.2
A163: 2.5.2.3 | B163: Supply and assembly of continuous false ceilings with 12mm water-repellent plasterboard sheets, "KNAUF HIDROFUGA H1", including 10mmx10mm fin with system profile, support structure, fixing system, execution of openings for placing various equipment, recesses, joint treatment, damming and final preparation to receive painting and all preparatory work and accessories necessary for a perfect finish. (TE03) | D163: m2 | E163: 59.45 | F163: 38.66 | G163: 2298.34
A165: 2.5.2.4 | B165: Supply and execution of molding in false plasterboard ceilings, according to the detailed drawing, with finishing and final preparation to receive painting, including all preparatory work and accessories necessary for a perfect finish. | D165: ml | E165: 11.9 | F165: 38.66 | G165: 460.05
A167: 2.5.2.5 | B167: Supply and execution of water paint painting, "CIN - VINYLMATE - Ref.ª 10-250", extra matt finish, in white RAL 9003, in 2 to 3 coats, including prior cleaning of surfaces, application of 1 coat of primer "EP/GC 300 - Ref.ª 10-600" and all preparatory work and accessories necessary for a perfect finish. (PR02) | D167: m2 | E167: 229.86 | F167: 10.34 | G167: 2376.75
A169: 2.5 | B169: CEILING COATING | G169: 15456.87 | H169: =G169 -> 15456.87
A172: 2.6 | B172: WALL COATING
A174: 2.6.1 | B174: EXTERIOR WALLS
A176: 2.6.1.1 | B176: Supply and execution of exposed concrete wall cladding with a water-repellent finish, "SIKAGARD 680-S PT", colorless matt, including preparation of the base by cutting out concrete burrs, filling gaps with appropriate materials, general surface preparation, application of primer and all preparatory work and accessories necessary for a perfect finish. (PR08) | D176: m2 | E176: 110.6 | F176: 12.93 | G176: 1430.06
A178: 2.6.1.2 | B178: Supply and execution of "WEBER REV PASTE GRAY RAL 7035 from the SAINT-GOBAIN brand", including all preparatory work and accessories necessary for a perfect finish. (PR09) | D178: m2 | E178: 319.19 | F178: 35.96 | G178: 11478.07
A180: 2.6.1.3 | B180: Supply and execution of facade cladding with the complete system "ETICS - WEBER REV PASTE GRAY RAL 7035 from the brand SAINT-GOBAIN", consisting of bonding mortar, thermal insulation with 7cm thick molded expanded polystyrene plates, two layers of coating mortar separated between them by reinforcing mesh, normal mesh, leveling primer, regulator and final finish, including anchors and fixing accessories, profiles and finishing angles and all preparatory work and accessories necessary for a perfect finish. (PR10) | D180: m2 | E180: 131.48 | F180: 75 | G180: 9861
A182: 2.6.1.4 | B182: Supply and assembly of a finished facade system made from 5mm aluminum sheet lacquered in white RAL 9003 with a glued system from the brand "CORTIZO" and a T profile sub-structure and 7cm XPS insulation, including cuts, finishes and all preparatory work and accessories necessary for a perfect finish. (PR11) | D182: m2 | E182: 106.79 | F182: 234.7 | G182: 25063.61
A184: 2.6.1.5 | B184: Supply and execution of fine sanded plaster at 1:4, on facades and pergolas, all ready to receive painting or final finishing, including splashing, plastering and all preparatory work and accessories necessary for a perfect finish. (PR09) (PR14) | D184: m2 | E184: 353.75 | F184: 31.79 | G184: 11245.71
A186: 2.6.1.6 | B186: Supply and execution of painting with 100% acrylic paint, "CIN - NOVATEX - Ref.ª 12-230", in the color Gray RAL 7035, in 2 to 3 coats, on plaster, including prior cleaning of surfaces, application of 1 coat of primer "EP/GC 300 - Ref.ª 10-600" and all preparatory work and accessories necessary for a perfect finish. (PR14) | D186: m2 | E186: 34.56 | F186: 12.93 | G186: 446.86
A188: 2.6.2 | B188: INTERIOR WALLS
A190: 2.6.2.1 | B190: Supply and execution of exposed concrete wall cladding with a water-repellent finish, "SIKAGARD 680-S PT", colorless matt, including preparation of the base by cutting out concrete burrs, filling gaps with appropriate materials, general surface preparation, application of primer and all preparatory work and accessories necessary for a perfect finish. (PR01) | D190: m2 | E190: 52 | F190: 12.93 | G190: 672.36
A192: 2.6.2.2 | B192: Supply and execution of projected plaster, including thin mass skimming, reinforcement with 5x5cm (75g/m2) fiberglass mesh in the concrete/masonry transition and PVC corner profiles reinforced with fiber mesh, all ready to receive painting and all the preparatory work and accessories necessary for a perfect finish. (PR02) (PR03) | D192: m2 | E192: 466.94 | F192: 19.4 | G192: 9058.64
A194: 2.6.2.3 | B194: Supply and installation of "CLASSIC WHITE 30x30cm" tablet coating from the "RUBICER" brand and with joints in light gray bitumen RAL 7035, including base plaster on masonry faces, laying mortar or glue, cuts, finishing, grouting of joints and all preparatory work and accessories necessary for a perfect finish. (PR5.1) | D194: m2 | E194: 81.43 | F194: 103.64 | G194: 8439.41
A196: 2.6.2.4 | B196: Supply and installation of coating in "GRAY 30x30cm" tablet from the "RUBICER" brand and with joints in white bitumen RAL 9003, including base plaster lathed on masonry faces, laying mortar or glue, cuts, finishes, grouting of joints and all preparatory work and accessories necessary for a perfect finish. (PR5.2) | D196: m2 | E196: 46.05 | F196: 118.58 | G196: 5460.61
A198: 2.6.2.5 | B198: Supply and execution of tin plaster, including splashing, plastering and all preparatory work and accessories necessary for a perfect finish. (PR07) | D198: m2 | E198: 50.7 | F198: 32.46 | G198: 1645.72
A200: 2.6.2.6 | B200: Supply and execution of water paint painting, "CIN - VINYLCLEAN MATE - Ref.ª 10-245", in white RAL 9003, in 2 to 3 coats, applied to plastered walls and/or plasterboard, including prior cleaning of surfaces, application of 1 coat of primer "EP/GC 300 - Ref.ª 10-600" and all preparatory work and accessories necessary for a perfect finishing. (PR02) (PR04) | D200: m2 | E200: 551.51 | F200: 10.34 | G200: 5702.61
A202: 2.6.2.7 | B202: Supply and execution of painting with acrylic water enamel paint, "CIN - CINACRYL MATE - Ref.ª 10-230", in white RAL 9003, in 2 to 3 coats, applied to plastered walls and/or plasterboard, including prior cleaning of surfaces, application of 1 coat of primer "EP/GC 300 - Ref.ª 10-600" and all necessary preparatory work and accessories to a perfect finish. (PR03) (PR04) | D202: m2 | E202: 21.34 | F202: 10.34 | G202: 220.66
A204: 2.6 | B204: WALL COATING | G204: 90725.32 | H204: =G204 -> 90725.32
A207: 2.7 | B207: COATING OF FLOORS AND Skirting
A209: 2.7.1 | B209: EXTERIOR FLOORING
...

Sheet Resumo Viora Build
A1: 25-
B9: Клиент | F9: Matthew Renier
B11: Местоположение | F11: Das Gaivotas, Mata Porcas, Praia da Luz
B13: Описание работ
B15: Общая площадь застройки (м²) | F15: 392.8
B17: Прочее (цоколь, бассейн, пристройки, стены): | F17: 782.27
B19: Бассейн (м²) | F19: 100
B21: Дата | F21: 45812
B23: АРТ º | D23: ОПИСАНИЕ РАБОТ | J23: ИТОГО ПО РАЗДЕЛУ | L23: СТОИМОСТЬ (м2)
B25: ='Orcamento RU Viora Build'!C4 -> 1 | D25: ='Orcamento RU Viora Build'!D4 -> СТРОИТЕЛЬНАЯ ПЛОЩАДКА И ДОПОЛНИТЕЛЬНЫЕ РАБОТЫ | J25: ='Orcamento RU Viora Build'!H4 -> 2015 | L25: =+J25/$F$15 -> 5.1298371
B26: ='Orcamento RU Viora Build'!C56 -> 2 | D26: ='Orcamento RU Viora Build'!D56 -> ЗЕМЛЯНЫЕ РАБОТЫ | J26: ='Orcamento RU Viora Build'!H56 -> 69140.305 | L26: =+J26/$F$15 -> 176.01911
B27: ='Orcamento RU Viora Build'!C74 -> 3 | D27: ='Orcamento RU Viora Build'!D74 -> ЖЕЛЕЗОБЕТОННАЯ КОНСТРУКЦИЯ | J27: ='Orcamento RU Viora Build'!H74 -> 468347.35 | L27: =+J27/$F$15 -> 1192.3303
B28: ='Orcamento RU Viora Build'!C389 -> 4 | D28: ='Orcamento RU Viora Build'!D389 -> ГИДРОИЗОЛЯЦИЯ И ТЕПЛОИЗОЛЯЦИЯ | J28: ='Orcamento RU Viora Build'!H389 -> 52593.507 | L28: =+J28/$F$15 -> 133.89386
B29: ='Orcamento RU Viora Build'!C511 -> 5 | D29: ='Orcamento RU Viora Build'!D511 -> КАМЕННАЯ КЛАДКА И ОГРАЖДАЮЩИЕ КОНСТРУКЦИИ | J29: ='Orcamento RU Viora Build'!H511 -> 27664.108 | L29: =+J29/$F$15 -> 70.427973
B30: ='Orcamento RU Viora Build'!C669 -> 6 | D30: ='Orcamento RU Viora Build'!D669 -> КРОВЛЯ | J30: ='Orcamento RU Viora Build'!H669 -> 56228.093 | L30: =+J30/$F$15 -> 143.14688
B31: ='Orcamento RU Viora Build'!C701 -> 7 | D31: ='Orcamento RU Viora Build'!D701 -> ОТДЕЛКА ПОТОЛКОВ | J31: ='Orcamento RU Viora Build'!H701 -> 14727.368 | L31: =+J31/$F$15 -> 37.4933
B32: ='Orcamento RU Viora Build'!C769 -> 8 | D32: ='Orcamento RU Viora Build'!D769 -> ОТДЕЛКА СТЕН | J32: ='Orcamento RU Viora Build'!H769 -> 127239.06 | L32: =+J32/$F$15 -> 323.92835
B33: ='Orcamento RU Viora Build'!C857 -> 9 | D33: ='Orcamento RU Viora Build'!D857 -> ОТДЕЛКА ПОЛОВ И ПЛИНТУСОВ | J33: ='Orcamento RU Viora Build'!H857 -> 101274.85 | L33: =+J33/$F$15 -> 257.82803
B34: ='Orcamento RU Viora Build'!C1007 -> 10 | D34: ='Orcamento RU Viora Build'!D1007 -> МЕТАЛЛОКОНСТРУКЦИИ И ОКОННЫЕ РАМЫ | J34: ='Orcamento RU Viora Build'!H1007 -> 268546.38 | L34: =+J34/$F$15 -> 683.67206
B35: ='Orcamento RU Viora Build'!C1394 -> 11 | D35: ='Orcamento RU Viora Build'!D1394 -> СТОЛЯРНЫЕ РАБОТЫ | J35: ='Orcamento RU Viora Build'!H1394 -> 60186.757 | L35: =+J35/$F$15 -> 153.22494
B36: ='Orcamento RU Viora Build'!C1554 -> 12 | D36: ='Orcamento RU Viora Build'!D1554 -> САНТЕХНИЧЕСКОЕ ОБОРУДОВАНИЕ | J36: ='Orcamento RU Viora Build'!H1554 -> 25273.269 | L36: =+J36/$F$15 -> 64.341316
B37: ='Orcamento RU Viora Build'!C1690 -> 13 | D37: ='Orcamento RU Viora Build'!D1690 -> ОБОРУДОВАНИЕ КУХНИ И ПРАЧЕЧНОЙ | J37: ='Orcamento RU Viora Build'!H1690 -> 4262.8398 | L37: =+J37/$F$15 -> 10.852443
B38: ='Orcamento RU Viora Build'!C1743 -> 14 | D38: ='Orcamento RU Viora Build'!D1743 -> ВНУТРЕННЯЯ СЕТЬ ВОДОСНАБЖЕНИЯ, БАССЕЙН | J38: ='Orcamento RU Viora Build'!H1743 -> 34663.27 | L38: =+J38/$F$15 -> 88.246613
B39: ='Orcamento RU Viora Build'!C1901 -> 15 | D39: ='Orcamento RU Viora Build'!D1901 -> ГАЗОВАЯ СЕТЬ | J39: ='Orcamento RU Viora Build'!H1901 -> 3640.6719 | L39: =+J39/$F$15 -> 9.268513
B40: ='Orcamento RU Viora Build'!C1934 -> 16 | D40: ='Orcamento RU Viora Build'!D1934 -> ПОСТАВКА И МОНТАЖ ОБОРУДОВАНИЯ И СИСТЕМ КОНДИЦИОНИРОВАНИЯ И ПРОИЗВОДСТВА ГОРЯЧЕЙ САНИТАРНОЙ ВОДЫ | J40: ='Orcamento RU Viora Build'!H1934 -> 131227.36 | L40: =+J40/$F$15 -> 334.08188
B41: ='Orcamento RU Viora Build'!C2221 -> 17 | D41: ='Orcamento RU Viora Build'!D2221 -> ЭЛЕКТРИЧЕСКАЯ СЕТЬ | J41: ='Orcamento RU Viora Build'!H2221 -> 121063.37 | L41: =+J41/$F$15 -> 308.20614
B42: ='Orcamento RU Viora Build'!C2682 -> 18 | D42: ='Orcamento RU Viora Build'!D2682 -> ТЕЛЕКОММУНИКАЦИОННЫЕ УСТАНОВКИ ITED | J42: ='Orcamento RU Viora Build'!H2682 -> 9916.335 | L42: =+J42/$F$15 -> 25.245252
B43: ='Orcamento RU Viora Build'!C2750 -> 19 | D43: ='Orcamento RU Viora Build'!D2750 -> ПОЛЫ, ПОКРЫТИЯ И СТРОИТЕЛЬНЫЕ ЭЛЕМЕНТЫ | J43: ='Orcamento RU Viora Build'!H2750 -> 25064.97 | L43: =+J43/$F$15 -> 63.811024
B44: ='Orcamento RU Viora Build'!C2819 -> 20 | D44: ='Orcamento RU Viora Build'!D2819 -> ОСВЕЩЕНИЕ - СВЕТОВЫЕ ТОЧКИ | J44: ='Orcamento RU Viora Build'!H2819 -> 0 | L44: =+J44/$F$15 -> 0
B45: ='Orcamento RU Viora Build'!C2840 -> 21 | D45: ='Orcamento RU Viora Build'!D2840 -> ОБОРУДОВАНИЕ | J45: ='Orcamento RU Viora Build'!H2840 -> 1396.226 | L45: =+J45/$F$15 -> 3.5545468
B46: ='Orcamento RU Viora Build'!C2852 -> 22 | D46: ='Orcamento RU Viora Build'!D2852 -> ПОСАДКИ И ПОСЕВЫ (ИСКЛЮЧЕН) | J46: ='Orcamento RU Viora Build'!H2852 -> 0 | L46: =+J46/$F$15 -> 0
B47: ='Orcamento RU Viora Build'!C2943 -> 23 | D47: ='Orcamento RU Viora Build'!D2943 -> ПОЛИВ (ИСКЛЮЧЕН) | J47: ='Orcamento RU Viora Build'!H2943 -> 0 | L47: =+J47/$F$15 -> 0
B48: ='Orcamento RU Viora Build'!C3014 -> 24 | D48: ='Orcamento RU Viora Build'!D3014 -> ОБСЛУЖИВАНИЕ ЗЕЛЕНЫХ ЗОН (ИСКЛЮЧЕН) | J48: ='Orcamento RU Viora Build'!H3014 -> 0 | L48: =+J48/$F$15 -> 0
B49: ='Orcamento RU Viora Build'!C3018 -> 25 | D49: ='Orcamento RU Viora Build'!D3018 -> БЛАГОУСТРОЙСТВО УЧАСТКА | J49: ='Orcamento RU Viora Build'!H3018 -> 44572.631 | L49: =+J49/$F$15 -> 113.47411
B50: ='Orcamento RU Viora Build'!C3123 -> 26 | D50: ='Orcamento RU Viora Build'!D3123 -> ПРОЧЕЕ | J50: ='Orcamento RU Viora Build'!H3123 -> 12030.2 | L50: =+J50/$F$15 -> 30.626782
B51: ='Orcamento RU Viora Build'!C3167 -> 27 | D51: ='Orcamento RU Viora Build'!D3167 -> ВНУТРЕННЯЯ СЕТЬ БЫТОВЫХ И ДОЖДЕВЫХ СТОЧНЫХ ВОД | J51: ='Orcamento RU Viora Build'!H3167 -> 47244.964 | L51: =+J51/$F$15 -> 120.2774
B53: ИТОГО ЗА ЖИЛЬЕ | J53: =SUM(J25:J51) -> 1708318.9 | L53: =+J53/$F$15 -> 4349.0807
B54: IVA (23%) | J54: =+J53*0.23 -> 392913.35
B55: ИТОГО С IVA | J55: =+J54+J53 -> 2101232.2
B57: ИТОГО ЗА БАССЕЙН | L57: =+J57/$F$19 -> 0
B58: IVA (23%) | J58: =+J57*0.23 -> 0
B59: ИТОГО С IVA | J59: =+J58+J57 -> 0
B61: ОБЩИЙ ИТОГ | J61: =J53+J57 -> 1708318.9
B62: IVA (23%) | J62: =+J61*0.23 -> 392913.35
B63: ИТОГО С IVA | J63: =+J62+J61 -> 2101232.2

Sheet Orcamento RU Viora Build
A1: ID | B1: № M | C1: № V | D1: ОПИСАНИЕ РАБОТ | E1: ЕД. ИЗМ. | F1: КОЛ-ВО | G1: ЦЕНА ЗА ЕДИНИЦУ | H1: ОБЩАЯ СТОИМОСТЬ | I1: Коментарий
I2: Matthew ENG
C4: 1 | D4: СТРОИТЕЛЬНАЯ ПЛОЩАДКА И ДОПОЛНИТЕЛЬНЫЕ РАБОТЫ | E4: =H8 | H4: =SUM(H10:H52) -> 2015 | I4: =H4-('Orcamento RU'!C4+'Orcamento RU'!C2206) -> -176195.4
D6: СТРОИТЕЛЬНАЯ ПЛОЩАДКА | G6: =SUM(H10:H38) -> 2015
B8: 1.1.1 (1) | C8: 1.1 | D8: Монтаж, строительство, обслуживание, демонтаж и снос строительной площадки, включая соответствующие установки, временные сети водоснабжения, канализации, электричества и средства телекоммуникаций, внутренние пути движения и все остальное необходимое в соответствии с Декретом-Законом № 18/08 от 29 января, удовлетворяющее предписаниям по безопасности, гигиене и охране труда, в соответствии с Декретом-Законом № 273/2003 от 29 октября и прочим действующим законодательством, разработка и внедрение плана предотвращения и управления отходами строительства и сноса (в понимании Д.З. № 46/2008 от 12 марта).
A10: ='Master List'!A463 -> W-PRE-001 | B10: 1.1.1 (1) | C10: 1.1.1 | D10: =VLOOKUP(A10,'Master List'!$A$1:$C$1192,2,FALSE) -> Поставка и установка, обслуживание и демонтаж ограждения вокруг участка с непрозрачными панелями из профилированного оцинкованного стального листа толщиной 0,6 мм, с ребрами высотой от 40 до 50 мм, расположенными на расстоянии от 250 до 270 мм, и профилями в S из согнутого оцинкованного стального листа размером 102x33x1,5 мм, с отделкой сендзимир, длиной 2,8 м, закрепленными в земле с помощью кубов бетона C20/25 XC0 Cl0.40 Dmax 25mm S2 размером 102x33x1,5 см, каждые 2,0 м, включая все работы и материалы, которые к ним относятся. | E10: =VLOOKUP(A10,'Master List'!$A$1:$C$1192,3,FALSE) -> м | F10: 0 | G10: =VLOOKUP(A10,'Master List'!$A$4:$F2715,5,FALSE) -> 106750.8 | H10: =G10*F10 -> 0 | I10: Matthew сообщил, что, по словам архитектора, временный забор по периметру дома не требуется. Он понадобится только в зоне въезда. Ранее у нас было заложено 260 погонных метров по цене 100 евро за метр. Мы согласовали, что при необходимости можно будет сразу строить постоянный забор вместо временного — это позволит сэкономить 26 000 евро. Если же всё-таки будет принято решение установить временный забор во фронтальной части, его стоимость составит 100 евро за погонный метр.
A12: ='Master List'!A464 -> W-PRE-002 | B12: 1.1.1 (1) | C12: 1.1.2 | D12: =VLOOKUP(A12,'Master List'!$A$1:$C$1192,2,FALSE) -> Поставка и монтаж, обслуживание и разборка раздвижных ворот для доступа транспортных средств из оцинкованной стали из двух створок с приблизительными размерами 4,0x2,0м с защелкой для замка и фурнитурой для крепления к полу, установленные в временном ограждении территории, закрепленные с помощью столбов из того же материала, анкерованных в грунте с помощью бетонных кубов C20/25 XC0 Cl0.40 Dmáx 25mm S2, включая все работы и материалы, связанные с этим. | E12: =VLOOKUP(A12,'Master List'!$A$1:$C$1192,3,FALSE) -> шт | F12: 1 | G12: =VLOOKUP(A12,'Master List'!$A$4:$F2717,5,FALSE) -> 1560 | H12: =G12*F12 -> 1560
A14: ='Master List'!A465 -> W-PRE-003 | B14: 1.1.1 (1) | C14: 1.1.3 | D14: =VLOOKUP(A14,'Master List'!$A$1:$C$1192,2,FALSE) -> Поставка и установка информационного щита, рекламирующего строительство, включая все работы и материалы, относящиеся к этому. | E14: =VLOOKUP(A14,'Master List'!$A$1:$C$1192,3,FALSE) -> шт | F14: 1 | G14: =VLOOKUP(A14,'Master List'!$A$4:$F2719,5,FALSE) -> 455 | H14: =G14*F14 -> 455
A16: ='Master List'!A466 -> W-PRE-004 | B16: 1.1.1 (1) | C16: 1.1.4 | D16: =VLOOKUP(A16,'Master List'!$A$1:$C$1192,2,FALSE) -> Поставка и выполнение первичных сетей электричества, воды и канализации, включая ежемесячное потребление в течение всего срока выполнения работ до предварительного приемки, включая связанные работы и материалы. | E16: =VLOOKUP(A16,'Master List'!$A$1:$C$1192,3,FALSE) -> міс | F16: 18 | G16: =VLOOKUP(A16,'Master List'!$A$4:$F2721,5,FALSE) -> 0 | H16: =G16*F16 -> 0 | I16: Этот пункт будет урегулироваться по факту
A18: ='Master List'!A467 -> W-PRE-005 | B18: 1.1.1 (1) | C18: 1.1.5 | D18: =VLOOKUP(A18,'Master List'!$A$1:$C$1192,2,FALSE) -> Поставка и монтаж офисного модуля размером 6,0x3,0 м для строительных совещаний, установленного на выровненной основе из щебня, с туалетом и кондиционером, включая заземление и все сопутствующие работы и материалы. | E18: =VLOOKUP(A18,'Master List'!$A$1:$C$1192,3,FALSE) -> шт | F18: 1 | G18: =VLOOKUP(A18,'Master List'!$A$4:$F2723,5,FALSE) -> 0 | H18: =G18*F18 -> 0 | I18: По желанию клиента для его удобства. Цена 12 000 Евро
A20: ='Master List'!A468 -> W-PRE-006 | B20: 1.1.1 (1) | C20: 1.1.6 | D20: =VLOOKUP(A20,'Master List'!$A$1:$C$1192,2,FALSE) -> Поставка и монтаж модуля общего инструмента размером 3,0x2,40 м типа морского контейнера, установленного на выровненной основе из щебня, включая все работы и материалы, связанные с этим. | E20: =VLOOKUP(A20,'Master List'!$A$1:$C$1192,3,FALSE) -> шт | F20: 1 | G20: =VLOOKUP(A20,'Master List'!$A$4:$F2725,5,FALSE) -> 0 | H20: =G20*F20 -> 0
A22: ='Master List'!A469 -> W-PRE-007 | B22: 1.1.1 (1) | C22: 1.1.7 | D22: =VLOOKUP(A22,'Master List'!$A$1:$C$1192,2,FALSE) -> Поставка и установка портативного санитарного блока из полиэтилена размером 1,20x1,20x2,35м серого цвета или другого, без подключений, с анаэробным химическим туалетом с системой сброса на ножном приводе, зеркалом, дверью с замком и полупрозрачным потолком для пропуска внешнего света, включая еженедельную уборку и все сопутствующие работы и материалы. | E22: =VLOOKUP(A22,'Master List'!$A$1:$C$1192,3,FALSE) -> міс | F22: 18 | G22: =VLOOKUP(A22,'Master List'!$A$4:$F2727,5,FALSE) -> 0 | H22: =G22*F22 -> 0
A24: ='Master List'!A470 -> W-PRE-008 | B24: 1.1.1 (1) | C24: 1.8 | D24: =VLOOKUP(A24,'Master List'!$A$1:$C$1192,2,FALSE) -> Поставка и выполнение топографической разбивки через специализированного техника уровней установки строительства, включая бассейн и границы, а также все работы и материалы, связанные с этим. | E24: =VLOOKUP(A24,'Master List'!$A$1:$C$1192,3,FALSE) -> шт | F24: 1 | G24: =VLOOKUP(A24,'Master List'!$A$4:$F2729,5,FALSE) -> 0 | H24: =G24*F24 -> 0
A26: ='Master List'!A471 -> W-PRE-009 | B26: 1.1.1 (1) | C26: 1.9 | D26: =VLOOKUP(A26,'Master List'!$A$1:$C$1192,2,FALSE) -> Поставка и монтаж строительных лесов из стандартных труб, многофункционального типа, высотой до 9 м, состоящих из стальной трубной конструкции из горячекатаной оцинкованной стали диаметром 48,3 мм и толщиной 3,2 мм, без дублирования вертикальных элементов, состоящих из рабочих платформ шириной 60 см, размещенных каждые 2 м по высоте, внутренней лестницы с люком, задних ограждений с двумя перекладинами и нижней планкой, и передних ограждений с одной перекладиной, для выполнения фасада(ов) с конструктивными элементами (крытые и открытые террасы, карнизы и другие и т. д.), размещенными на более чем 50% их периметра и выступающими более чем на 30 см от плоскости фасада. Примечание (1): строительные леса должны полностью соответствовать действующему законодательству, в частности, EN 12811 и EN 12810. | E26: =VLOOKUP(A26,'Master List'!$A$1:$C$1192,3,FALSE) -> міс | F26: 18 | G26: =VLOOKUP(A26,'Master List'!$A$4:$F2731,5,FALSE) -> 0 | H26: =G26*F26 -> 0 | I26: Аренда строительных лесов
A28: ='Master List'!A472 -> W-PRE-010 | B28: 1.1.1 (1) | C28: 1.10 | D28: =VLOOKUP(A28,'Master List'!$A$1:$C$1192,2,FALSE) -> Поставка, выполнение и внедрение/адаптация плана безопасности и здоровья (ПБЗ) на этапе строительства, включая все работы и материалы, связанные с этим. | E28: =VLOOKUP(A28,'Master List'!$A$1:$C$1192,3,FALSE) -> міс | F28: 18 | G28: =VLOOKUP(A28,'Master List'!$A$4:$F2733,5,FALSE) -> 0 | H28: =G28*F28 -> 0 | I28: Страховка обьекта может отличаться от 300-500 евро. Написали последнюю информацию
A30: ='Master List'!A473 -> W-PRE-011 | B30: 1.1.1 (1) | C30: 1.11 | D30: =VLOOKUP(A30,'Master List'!$A$1:$C$1192,2,FALSE) -> Поставка, выполнение и внедрение/адаптация плана управления отходами (ПГО), его классификация (ЛЕР), сортировка и разделение на его перерабатываемые компоненты и соответствующая утилизация или транспортировка в зоны переработки и к уполномоченным и лицензированным операторам, в соответствии с действующим законодательством. | E30: =VLOOKUP(A30,'Master List'!$A$1:$C$1192,3,FALSE) -> міс | F30: 18 | G30: =VLOOKUP(A30,'Master List'!$A$4:$F2735,5,FALSE) -> 0 | H30: =G30*F30 -> 0 | I30: Этот пункт будет урегулироваться по факту
A32: ='Master List'!A474 -> W-PRE-012 | B32: 1.1.1 (1) | C32: 1.12 | D32: =VLOOKUP(A32,'Master List'!$A$1:$C$1192,2,FALSE) -> Подготовка и передача владельцу строительного проекта технической компиляции работ, которая включает полезные элементы, которые следует учитывать при их будущем использовании, а также работы, выполняемые после их завершения для сохранения безопасности и здоровья тех, кто их выполняет, в соответствии с положениями статьи 16 Декрета-Закона № 273/2003 от 29 октября, с учетом итоговых чертежей всех специальностей на бумажном и цифровом носителе, всех исследований, проектов, сопутствующей и связанной документации. | E32: =VLOOKUP(A32,'Master List'!$A$1:$C$1192,3,FALSE) -> шт | F32: 1 | G32: =VLOOKUP(A32,'Master List'!$A$4:$F2737,5,FALSE) -> 0 | H32: =G32*F32 -> 0 | I32: Входить в стоимость самого проекта
A34: ='Master List'!A475 -> W-PRE-013 | B34: 1.1.1 (1) | C34: 1.13 | D34: =VLOOKUP(A34,'Master List'!$A$1:$C$1192,2,FALSE) -> Обеспечение и координация человеческих и материальных ресурсов, необходимых для уборки и обслуживания строительной площадки, включая установку всего оборудования безопасности, такого как ограждения и линии жизни и т.д., все в соответствии с действующим законодательством. | E34: =VLOOKUP(A34,'Master List'!$A$1:$C$1192,3,FALSE) -> міс | F34: 18 | G34: =VLOOKUP(A34,'Master List'!$A$4:$F2739,5,FALSE) -> 0 | H34: =G34*F34 -> 0
A36: ='Master List'!A476 -> W-PRE-014 | B36: 1.1.1 (1) | C36: 1.14 | D36: =VLOOKUP(A36,'Master List'!$A$1:$C$1192,2,FALSE) -> Поставка специализированного персонала, а именно директора проекта (гражданский инженер), главного прораба, подготовителя проекта. | E36: =VLOOKUP(A36,'Master List'!$A$1:$C$1192,3,FALSE) -> міс | F36: 18 | G36: =VLOOKUP(A36,'Master List'!$A$4:$F2741,5,FALSE) -> 0 | H36: =G36*F36 -> 0
A38: ='Master List'!A477 -> W-PRE-015 | B38: 1.1.1 (1) | C38: 1.15 | D38: =VLOOKUP(A38,'Master List'!$A$1:$C$1192,2,FALSE) -> Поставка и установка оборудования и материалов безопасности, расположенных в видимых местах, включая все работы и материалы, связанные с этим. | E38: =VLOOKUP(A38,'Master List'!$A$1:$C$1192,3,FALSE) -> шт | F38: 1 | G38: =VLOOKUP(A38,'Master List'!$A$4:$F2743,5,FALSE) -> 0 | H38: =G38*F38 -> 0
D40: КРАН | G40: =SUM(H42:H52) -> 0
A42: ='Master List'!A478 -> W-PRE-016 | C42: 1.16 | D42: =VLOOKUP(A42,'Master List'!$A$1:$C$1192,2,FALSE) -> Поставка и выполнение земляных работ на любом типе грунта для основания крана, включая укладку земли в хранилище для насыпей, уплотнение и выравнивание основания рабочей платформы, а также все работы и материалы, связанные с этим. | E42: =VLOOKUP(A42,'Master List'!$A$1:$C$1192,3,FALSE) -> шт | F42: 1 | G42: =VLOOKUP(A42,'Master List'!$A$4:$F2747,5,FALSE) -> 0 | H42: =G42*F42 -> 0 | I42: Включено в стоимость земелных работ
A44: ='Master List'!A479 -> W-PRE-017 | C44: 1.17 | D44: =VLOOKUP(A44,'Master List'!$A$1:$C$1192,2,FALSE) -> Поставка и выполнение элементов бетонной конструкции типа C25/30 XC2(P) Dmáx 20mm S3, изготовленных, транспортированных и уложенных на объекте в соответствии с NP EN 206-1 и NP ENV 13670-1 для основания установки крана, включая выполнение опалубки и арматур из стали типа A500NR SD и все работы, необходимые для качественной отделки, всё в соответствии с проектом устойчивости, включая все работы и материалы, связанные с этим. Примечание (1): необходимо учитывать демонтаж фундамента крана. | E44: =VLOOKUP(A44,'Master List'!$A$1:$C$1192,3,FALSE) -> шт | F44: 1 | G44: =VLOOKUP(A44,'Master List'!$A$4:$F2749,5,FALSE) -> 0 | H44: =G44*F44 -> 0
C46: 1.18 | D46: Поставка и эксплуатация башенного крана с выдвижной стрелой длиной 50 м с характеристиками, соответствующими объекту, включая радиоуправление и управление по кабелю, ковш-санки на 300 литров и поддон для 2000 кг. | E46: vg | F46: 1
A48: ='Master List'!A480 -> W-PRE-018 | C48: 1.18.1 | D48: =VLOOKUP(A48,'Master List'!$A$1:$C$1192,2,FALSE) -> Монтаж крана | E48: =VLOOKUP(A48,'Master List'!$A$1:$C$1192,3,FALSE) -> шт | F48: 1 | G48: =VLOOKUP(A48,'Master List'!$A$4:$F2753,5,FALSE) -> 0 | H48: =G48*F48 -> 0
A49: ='Master List'!A481 -> W-PRE-019 | C49: 1.18.2 | D49: =VLOOKUP(A49,'Master List'!$A$1:$C$1192,2,FALSE) -> Эксплуатация крана | E49: =VLOOKUP(A49,'Master List'!$A$1:$C$1192,3,FALSE) -> міс | F49: 14 | G49: =VLOOKUP(A49,'Master List'!$A$4:$F2754,5,FALSE) -> 0 | H49: =G49*F49 -> 0
A50: ='Master List'!A482 -> W-PRE-020 | C50: 1.18.3 | D50: =VLOOKUP(A50,'Master List'!$A$1:$C$1192,2,FALSE) -> Демонтаж крана | E50: =VLOOKUP(A50,'Master List'!$A$1:$C$1192,3,FALSE) -> шт | F50: 1 | G50: =VLOOKUP(A50,'Master List'!$A$4:$F2755,5,FALSE) -> 0 | H50: =G50*F50 -> 0
A51: ='Master List'!A483 -> W-PRE-021 | C51: 1.18.4 | D51: =VLOOKUP(A51,'Master List'!$A$1:$C$1192,2,FALSE) -> Доставка крана | E51: =VLOOKUP(A51,'Master List'!$A$1:$C$1192,3,FALSE) -> шт | F51: 1 | G51: =VLOOKUP(A51,'Master List'!$A$4:$F2756,5,FALSE) -> 0 | H51: =G51*F51 -> 0
A52: ='Master List'!A484 -> W-PRE-022 | C52: 1.18.5 | D52: =VLOOKUP(A52,'Master List'!$A$1:$C$1192,2,FALSE) -> Вывоз крана | E52: =VLOOKUP(A52,'Master List'!$A$1:$C$1192,3,FALSE) -> шт | F52: 1 | G52: =VLOOKUP(A52,'Master List'!$A$4:$F2757,5,FALSE) -> 0 | H52: =G52*F52 -> 0
C56: 2 | D56: ЗЕМЛЯНЫЕ РАБОТЫ | H56: =SUM(H60:H72) -> 69140.305 | I56: =H56-('Orcamento RU'!C749+'Orcamento RU'!C2217) -> -4654.165
D58: ЗЕМЛЯНЫЕ РАБОТЫ | G58: =SUM(H60:H72) -> 69140.305
A60: ='Master List'!A486 -> W-LND-001 | B60: 1,1 (2) | C60: 2.1 | D60: =VLOOKUP(A60,'Master List'!$A$1:$C$1192,2,FALSE) -> Общая очистка участка, включающая все виды работ по очистке, удалению, расчистке и вырубке древесных пород, существующих и необходимых для общего выполнения проектов. | E60: =VLOOKUP(A60,'Master List'!$A$1:$C$1192,3,FALSE) -> шт | F60: 1 | G60: =VLOOKUP(A60,'Master List'!$A$4:$F2765,5,FALSE) -> 1560 | H60: =G60*F60 -> 1560
A62: ='Master List'!A487 -> W-LND-002 | B62: 1,2 (2) | C62: 2.2 | D62: =VLOOKUP(A62,'Master List'!$A$1:$C$1192,2,FALSE) -> Выполнение общих земляных работ для размещения конструкции жилого дома, бассейна и стен на грунте любого типа (включая скальный), чтобы достичь начальных отметок фундамента, а также выполнение работ по креплению, подпоркам, канализации, включая все сопутствующие работы. | E62: =VLOOKUP(A62,'Master List'!$A$1:$C$1192,3,FALSE) -> м3 | F62: 2234.27 | G62: =VLOOKUP(A62,'Master List'!$A$4:$F2767,5,FALSE) -> 6.5 | H62: =G62*F62 -> 14522.755
A64: ='Master List'!A488 -> W-LND-003 | B64: 1,3 (2) | C64: 2.3 | D64: =VLOOKUP(A64,'Master List'!$A$1:$C$1192,2,FALSE) -> Выполнение насыпей в зоне жилого дома, бассейна и внешних террас с использованием материалов из выемки, включая распределение и надлежащее уплотнение, выполняемое механическими средствами, слоями максимальной толщиной 0,30 м, с использованием воды в количестве, необходимом для правильного уплотнения, для достижения проектных уровней, включая все сопутствующие работы. | E64: =VLOOKUP(A64,'Master List'!$A$1:$C$1192,3,FALSE) -> м3 | F64: 482.44 | G64: =VLOOKUP(A64,'Master List'!$A$4:$F2769,5,FALSE) -> 32.5 | H64: =G64*F64 -> 15679.3
A66: ='Master List'!A489 -> W-LND-004 | B66: 1.4.1 (2) | C66: 2.4 | D66: =VLOOKUP(A66,'Master List'!$A$1:$C$1192,2,FALSE) -> Транспортировка, погрузка и разгрузка излишков грунта из зоны жилого дома на свалку, включая 20% разрыхление, а также все сопутствующие работы. | E66: =VLOOKUP(A66,'Master List'!$A$1:$C$1192,3,FALSE) -> м3 | F66: 2102.2 | G66: =VLOOKUP(A66,'Master List'!$A$4:$F2771,5,FALSE) -> 11.05 | H66: =G66*F66 -> 23229.31
A68: ='Master List'!A490 -> W-LND-005 | B68: 1.2.1.1 (3) | C68: 2.5 | D68: =VLOOKUP(A68,'Master List'!$A$1:$C$1192,2,FALSE) -> Выемка грунта любого характера до проектных отметок, включая транспортировку в зоны насыпи, остальные должны транспортироваться на авторизованный склад, включая транспортировку, компенсации, а также все средства, работы, материалы, необходимые. | E68: =VLOOKUP(A68,'Master List'!$A$1:$C$1192,3,FALSE) -> м3 | F68: 68 | G68: =VLOOKUP(A68,'Master List'!$A$4:$F2773,5,FALSE) -> 4.03 | H68: =G68*F68 -> 274.04
A70: ='Master List'!A491 -> W-LND-006 | B70: 1.2.2.1 (3) | C70: 2.6 | D70: =VLOOKUP(A70,'Master List'!$A$1:$C$1192,2,FALSE) -> Насыпь слоями до проектных отметок отборным грунтом из выемок или из зон заимствования вне зоны вмешательства, включая транспортировку, все средства, работы, материалы, необходимые. | E70: =VLOOKUP(A70,'Master List'!$A$1:$C$1192,3,FALSE) -> м3 | F70: 386 | G70: =VLOOKUP(A70,'Master List'!$A$4:$F2775,5,FALSE) -> 24.7 | H70: =G70*F70 -> 9534.2
A72: ='Master List'!A492 -> W-LND-007 | B72: 1.2.3.1 (3) | C72: 2.7 | D72: =VLOOKUP(A72,'Master List'!$A$1:$C$1192,2,FALSE) -> Поставка, погрузка, транспортировка, разгрузка, распределение заимствованного грунта, а также все средства, работы, материалы, необходимые. | E72: =VLOOKUP(A72,'Master List'!$A$1:$C$1192,3,FALSE) -> м3 | F72: 318 | G72: =VLOOKUP(A72,'Master List'!$A$4:$F2777,5,FALSE) -> 13.65 | H72: =G72*F72 -> 4340.7
C74: 3 | D74: ЖЕЛЕЗОБЕТОННАЯ КОНСТРУКЦИЯ | H74: =SUM(H80:H386) -> 468347.35 | I74: =H74-'Orcamento RU'!C761 -> -90044.899
D76: Бетон | G76: =SUM(H80:H119) -> 78664.515
B78: 2.1.1 (2) | C78: 3.1 | D78: Поставка и укладка подбетонки из бетона C12/15, с классом воздействия X0, Cl 1.0, Dmax 25мм, S3, толщиной 5 см под элементы фундамента, включая предварительное выравнивание и уплотнение дна котлованов, уложенной в геометрической форме следующих элементов:
B80: 2.1.1.1 (2) | C80: 3.1.1 | D80: В фундаментах, фундаментах стен, ограничительных стенах, фундаментных балках и фундаментных плитах | E80: m2 | F80: 329.7
A81: ='Master List'!A496 -> W-CON-002 | D81: =VLOOKUP(A81,'Master List'!$A$1:$C$1192,2,FALSE) -> Устройство чернового слоя бетона | E81: =VLOOKUP(A81,'Master List'!$A$1:$C$1192,3,FALSE) -> м3 | F81: =330*0.05 -> 16.5 | G81: =VLOOKUP(A81,'Master List'!$A$4:$F2787,5,FALSE) -> 17.55 | H81: =G81*F81 -> 289.575
A82: ='Master List'!A4 -> M-CON-001 | D82: =VLOOKUP(A82,'Master List'!$A$1:$C$1192,2,FALSE) -> Бетон C12/15 XC0(P) Cl1.00 Dmáx 22 мм S4 | E82: =VLOOKUP(A82,'Master List'!$A$1:$C$1192,3,FALSE) -> м3 | F82: =F81*1.02 -> 16.83 | G82: =VLOOKUP(A82,'Master List'!$A$4:$F2788,5,FALSE) -> 107.64 | H82: =G82*F82 -> 1811.5812
B85: 2.1.2 (2) | C85: 3.2 | D85: Поставка и укладка бетона C30/37, с классом воздействия XC2, Cl 0.4, Dmax 20мм, S3, включая вибрирование и все сопутствующие работы, необходимые для идеального завершения в следующих элементах:
B87: 2.1.2.1 (2) | C87: 3.2.1 | D87: В фундаментных балках | E87: m³ | F87: 29.25
B88: 2.1.2.2 (2) | C88: 3.2.2 | D88: В фундаментах | E88: m³ | F88: 8.94
B89: 2.1.2.3(2) | C89: 3.2.3 | D89: В фундаментах стен и перегородок | E89: m³ | F89: 106.22
B90: 2.1.2.4 (2) | C90: 3.2.4 | D90: В фундаментной плите | E90: m³ | F90: 3.02
B92: 2.1.3(2) | C92: 3.3 | D92: Поставка и укладка бетона C30/37, с классом воздействия XC2, Cl 0.4, Dmax 20мм, S4, включая вибрирование и все сопутствующие работы, необходимые для идеального завершения в следующих элементах:
B94: 2.1.3.1 (2) | C94: 3.3.1 | D94: Столбы стен подвала | E94: m³ | F94: 2.51
B95: 2.1.3.2 (2) | C95: 3.3.2 | D95: Стены подвала/опорные/перегородки | E95: m³ | F95: 88.26
B96: 2.1.3.2(2) | C96: 3.3.3 | D96: Наружная лестница | E96: m³ | F96: 1.32
B98: 2.1.4 (2) | C98: 3.4 | D98: Поставка и укладка бетона C40/50, с классом воздействия XS1, Cl 0.2, Dmax 20мм, S4, включая вибрирование и все сопутствующие работы, необходимые для идеального завершения в следующих элементах:
B100: 2.1.4.1 (2) | C100: 3.4.1 | D100: В столбах | E100: m³ | F100: 7.28
B101: 2.1.4.2 (2) | C101: 3.4.2 | D101: В стенах | E101: m³ | F101: 27.46
B103: 2.1.4 (2) | C103: 3.5 | D103: Поставка и укладка бетона C40/50, с классом воздействия XS1, Cl 0.2, Dmax 16мм, S4, включая вибрирование и все сопутствующие работы, необходимые для идеального завершения в следующих элементах:
B105: 2.1.4.3 (2) | C105: 3.5.1 | D105: В балках | E105: m³ | F105: 52.37
B106: 2.1.4.4 (2) | C106: 3.5.2 | D106: В монолитных плитах | E106: m³ | F106: 60.12
B107: 2.1.4.5 (2) | C107: 3.5.3 | D107: В облегченных монолитных плитах (Cobiax) | E107: m³ | F107: 50.41
B108: 2.1.4.6 (2) | C108: 3.5.4 | D108: В лестницах Лестница E1 | E108: m³ | F108: 1.91
B110: 2.1.5 (2) | C110: 3.6 | D110: Поставка и укладка бетона C40/50, с классом воздействия XD2, Cl 0.2, Dmax 20мм, S4, в элементах бассейна, компенсационного бака и водного зеркала, включая вибрирование и все сопутствующие работы, необходимые для идеального завершения в следующих элементах:
B112: 2.1.5.1 (2) | C112: 3.6.1 | D112: В стенах | E112: m³ | F112: 30.26
B113: 2.1.5.2 (2) | C113: 3.6.2 | D113: В плитах | E113: m³ | F113: 21.41
B114: 2.1.5.3 (2) | C114: 3.6.3 | D114: В балках/усилениях | E114: m³ | F114: 3.06
B115: 2.1.5.4 (2) | C115: 3.6.4 | D115: В лестницах (Лестница E3) | E115: m³ | F115: 1.18
A117: ='Master List'!A499 -> W-CON-005 | D117: =VLOOKUP(A117,'Master List'!$A$1:$C$1192,2,FALSE) -> Укладка чистового бетона в опалубку | E117: =VLOOKUP(A117,'Master List'!$A$1:$C$1192,3,FALSE) -> м3 | F117: =SUM(F87:F115) -> 494.98 | G117: =VLOOKUP(A117,'Master List'!$A$4:$F2823,5,FALSE) -> 16.25 | H117: =G117*F117 -> 8043.425
A118: ='Master List'!A6 -> M-CON-004 | D118: =VLOOKUP(A118,'Master List'!$A$1:$C$1192,2,FALSE) -> Бетон C30/37 XC2(P) Cl0.40 Dmáx 22мм S4 | E118: =VLOOKUP(A118,'Master List'!$A$1:$C$1192,3,FALSE) -> м3 | F118: =SUM(F87:F96)*1.02 -> 244.3104 | G118: =VLOOKUP(A118,'Master List'!$A$4:$F2824,5,FALSE) -> 127.946 | H118: =G118*F118 -> 31258.538
A119: ='Master List'!A7 -> M-CON-005 | D119: =VLOOKUP(A119,'Master List'!$A$1:$C$1192,2,FALSE) -> Бетон C40/50 XS1(P) Cl0.20 Dmáx 16мм S4 | E119: =VLOOKUP(A119,'Master List'!$A$1:$C$1192,3,FALSE) -> м3 | F119: =SUM(F100:F115)*1.02 -> 260.5692 | G119: =VLOOKUP(A119,'Master List'!$A$4:$F2825,5,FALSE) -> 143 | H119: =G119*F119 -> 37261.396
D123: Сталь/Арматура | G123: =SUM(H176:H182) -> 107195.57
B125: 2.2.1 (2) | C125: 3.7 | D125: Поставка, изготовление и установка стали A500NR SD в арматуре конструктивных элементов, включая отходы, стыки, отожженную проволоку, средства и оборудование и все сопутствующие работы, необходимые для идеального завершения в следующих элементах:
B127: 2.2.1.1 | C127: 3.7.1 | D127: Фундаменты
C128: 3.7.1.1 | D128: Ø10 | E128: kg | F128: 421.74
B130: 2.2.1.2 | C130: 3.7.2 | D130: Фундаменты стен/перегородок
C131: 3.7.2.1 | D131: Ø8 | E131: kg | F131: 1572.83
C132: 3.7.2.2 | D132: Ø10 | E132: kg | F132: 3799.07
B134: 2.2.1.3 | C134: 3.7.3 | D134: Фундаментная плита
C135: 3.7.3.1 | D135: Ø10 | E135: kg | F135: 289.81
C136: 3.7.3.2 | D136: Ø12 | E136: kg | F136: 412.85
B138: 2.2.1.4 | C138: 3.7.4 | D138: Фундаментные балки
C139: 3.7.4.1 | D139: Ø8 | E139: kg | F139: 651.95
C140: 3.7.4.2 | D140: Ø10 | E140: kg | F140: 132.8
C141: 3.7.4.3 | D141: Ø12 | E141: kg | F141: 477.82
C142: 3.7.4.4 | D142: Ø16 | E142: kg | F142: 1878.6
B144: 2.2.1.5 | C144: 3.7.5 | D144: Стены подвала/опорные и перегородки
C145: 3.7.5.1 | D145: Ø8 | E145: kg | F145: 861.38
C146: 3.7.5.2 | D146: Ø10 | E146: kg | F146: 4610.89
C147: 3.7.5.3 | D147: Ø12 | E147: kg | F147: 12447.9
B149: 2.2.1.6 | C149: 3.7.6 | D149: Столбы
C150: 3.7.6.1 | D150: Ø8 | E150: kg | F150: 873.77
C151: 3.7.6.2 | D151: Ø12 | E151: kg | F151: 1173.14
C152: 3.7.6.3 | D152: Ø16 | E152: kg | F152: 851.86
B154: 2.2.1.7 | C154: 3.7.7 | D154: Балки и усиления
C155: 3.7.7.1 | D155: Ø8 | E155: kg | F155: 2505.02
C156: 3.7.7.2 | D156: Ø10 | E156: kg | F156: 113.14
C157: 3.7.7.3 | D157: Ø12 | E157: kg | F157: 145.88
C158: 3.7.7.4 | D158: Ø16 | E158: kg | F158: 6059.68
B160: 2.2.1.8 | C160: 3.7.8 | D160: Плиты
C161: 3.7.8.1 | D161: Ø10 | E161: kg | F161: 3007.17
C162: 3.7.8.2 | D162: Ø12 | E162: kg | F162: 14406.06
...

Sheet Master List
A1: ID | B1: Матеріали | C1: Од. виміру | D1: Кількість | E1: Ціна за Шт | F1: РАЗОМ | G1: Наша Скидка Работа | H1: Наша Скидка Материалы | I1: Цена без скидки | J1: Скидка Магазина или подрядчика | K1: Цена нам штука со скидкой | L1: Итого себестоимость | M1: Заработок | N1: Наценка | O1: Маржа | P1: Поставщик | Q1: Комментарий | S1: МАТЕРИАЛ И РАБОТА РАЗБИВКА
A2: МАТЕРІАЛИ І РОБОТИ | F2: =SUM(F4:F842) -> 1708318.9 | M2: =SUM(M4:M1199) -> 394227.44 | N2: 0.3 | S2: МАТЕРИАЛ | T2: РАБОТА
A3: Залізобетонні конструкції
A4: M-CON-001 | B4: Бетон C12/15 XC0(P) Cl1.00 Dmáx 22 мм S4 | C4: м3 | D4: =SUMIF('Orcamento RU Viora Build'!$A:$A,A4,'Orcamento RU Viora Build'!$F:$F) -> 16.83 | E4: =K4+(K4*N4) -> 107.64 | F4: =D4*E4 -> 1811.5812 | I4: 82.8 | J4: 0 | K4: =I4-I4*J4 -> 82.8 | L4: =K4*D4 -> 1393.524 | M4: =F4-L4 -> 418.0572 | N4: =N2 -> 0.3 | O4: =M4/F4 -> 0.23076923 | P4: Secil betão | Q4: Цена из прошлых смет
A5: M-CON-002 | B5: Бетон C16/20 X0(P) Cl0.40 Dmáx 15mm S2 | C5: м3 | D5: =SUMIF('Orcamento RU Viora Build'!$A:$A,A5,'Orcamento RU Viora Build'!$F:$F) -> 60.62166 | E5: =K5+(K5*N5) -> 114.218 | F5: =D5*E5 -> 6924.0848 | I5: 87.86 | J5: 0 | K5: =I5-I5*J5 -> 87.86 | L5: =K5*D5 -> 5326.219 | M5: =F5-L5 -> 1597.8657 | N5: =$N$2 -> 0.3 | O5: =M5/F5 -> 0.23076923 | P5: Secil betão | Q5: Цена из прошлых смет
A6: M-CON-004 | B6: Бетон C30/37 XC2(P) Cl0.40 Dmáx 22мм S4 | C6: м3 | D6: =SUMIF('Orcamento RU Viora Build'!$A:$A,A6,'Orcamento RU Viora Build'!$F:$F) -> 302.97672 | E6: =K6+(K6*N6) -> 127.946 | F6: =D6*E6 -> 38764.659 | I6: 98.42 | J6: 0 | K6: =I6-I6*J6 -> 98.42 | L6: =K6*D6 -> 29818.969 | M6: =F6-L6 -> 8945.6906 | N6: =$N$2 -> 0.3 | O6: =M6/F6 -> 0.23076923 | P6: Secil betão | Q6: Цена из прошлых смет
A7: M-CON-005 | B7: Бетон C40/50 XS1(P) Cl0.20 Dmáx 16мм S4 | C7: м3 | D7: =SUMIF('Orcamento RU Viora Build'!$A:$A,A7,'Orcamento RU Viora Build'!$F:$F) -> 260.5692 | E7: =K7+(K7*N7) -> 143 | F7: =D7*E7 -> 37261.396 | I7: 110 | J7: 0 | K7: =I7-I7*J7 -> 110 | L7: =K7*D7 -> 28662.612 | M7: =F7-L7 -> 8598.7836 | N7: =$N$2 -> 0.3 | O7: =M7/F7 -> 0.23076923 | P7: Secil betão | Q7: Цена из прошлых смет
A8: M-CON-006 | B8: Бетон циклопічний C20/25 XC2 Cl0.40 S3 | C8: м3 | D8: =SUMIF('Orcamento RU Viora Build'!$A:$A,A8,'Orcamento RU Viora Build'!$F:$F) -> 42.075 | E8: =K8+(K8*N8) -> 143 | F8: =D8*E8 -> 6016.725 | I8: 110 | J8: 0 | K8: =I8-I8*J8 -> 110 | L8: =K8*D8 -> 4628.25 | M8: =F8-L8 -> 1388.475 | N8: =$N$2 -> 0.3 | O8: =M8/F8 -> 0.23076923 | P8: Secil betão | Q8: Цена из прошлых смет
A9: M-CON-007 | B9: Бетон декоративний SECIL Argamassas Unidecor natural | C9: м3 | D9: =SUMIF('Orcamento RU Viora Build'!$A:$A,A9,'Orcamento RU Viora Build'!$F:$F) -> 17.136 | E9: =K9+(K9*N9) -> 116.493 | F9: =D9*E9 -> 1996.224 | I9: 89.61 | J9: 0 | K9: =I9-I9*J9 -> 89.61 | L9: =K9*D9 -> 1535.557 | M9: =F9-L9 -> 460.66709 | N9: =$N$2 -> 0.3 | O9: =M9/F9 -> 0.23076923 | P9: Ссылка
A10: M-CON-008 | B10: Поліпропіленовий шнур для швів | C10: м | D10: =SUMIF('Orcamento RU Viora Build'!$A:$A,A10,'Orcamento RU Viora Build'!$F:$F) -> 79.2 | E10: =K10+(K10*N10) -> 0.51545 | F10: =D10*E10 -> 40.82364 | I10: 0.61 | J10: 0.35 | K10: =I10-I10*J10 -> 0.3965 | L10: =K10*D10 -> 31.4028 | M10: =F10-L10 -> 9.42084 | N10: =$N$2 -> 0.3 | O10: =M10/F10 -> 0.23076923 | P10: Recom
A11: M-CON-012 | B11: Арматура диаметром 12 мм A500NR SD | C11: кг | D11: =SUMIF('Orcamento RU Viora Build'!$A:$A,A11,'Orcamento RU Viora Build'!$F:$F) -> 35799.937 | E11: =K11+(K11*N11) -> 0.5746 | F11: =D11*E11 -> 20570.644 | I11: 0.68 | J11: 0.35 | K11: =I11-I11*J11 -> 0.442 | L11: =K11*D11 -> 15823.572 | M11: =F11-L11 -> 4747.0716 | N11: =$N$2 -> 0.3 | O11: =M11/F11 -> 0.23076923 | P11: Metalofarense | Q11: Цена из прошлых смет
A12: M-CON-013 | B12: Арматура диаметром 10 мм A500NR SD | C12: кг | D12: =SUMIF('Orcamento RU Viora Build'!$A:$A,A12,'Orcamento RU Viora Build'!$F:$F) -> 17878.319 | E12: =K12+(K12*N12) -> 0.58305 | F12: =D12*E12 -> 10423.954 | I12: 0.69 | J12: 0.35 | K12: =I12-I12*J12 -> 0.4485 | L12: =K12*D12 -> 8018.4258 | M12: =F12-L12 -> 2405.5278 | N12: =$N$2 -> 0.3 | O12: =M12/F12 -> 0.23076923 | P12: Metalofarense | Q12: Цена из прошлых смет
A13: M-CON-015 | B13: Арматура диаметром 16 мм A500NR SD | C13: кг | D13: =SUMIF('Orcamento RU Viora Build'!$A:$A,A13,'Orcamento RU Viora Build'!$F:$F) -> 9229.647 | E13: =K13+(K13*N13) -> 0.61685 | F13: =D13*E13 -> 5693.3078 | I13: 0.73 | J13: 0.35 | K13: =I13-I13*J13 -> 0.4745 | L13: =K13*D13 -> 4379.4675 | M13: =F13-L13 -> 1313.8402 | N13: =$N$2 -> 0.3 | O13: =M13/F13 -> 0.23076923 | P13: Metalofarense | Q13: Цена из прошлых смет
A14: M-CON-014 | B14: Арматура диаметром 8 мм A500NR SD | C14: кг | D14: =SUMIF('Orcamento RU Viora Build'!$A:$A,A14,'Orcamento RU Viora Build'!$F:$F) -> 14861.271 | E14: =K14+(K14*N14) -> 0.61685 | F14: =D14*E14 -> 9167.175 | I14: 0.73 | J14: 0.35 | K14: =I14-I14*J14 -> 0.4745 | L14: =K14*D14 -> 7051.6731 | M14: =F14-L14 -> 2115.5019 | N14: =$N$2 -> 0.3 | O14: =M14/F14 -> 0.23076923 | P14: Metalofarense | Q14: Цена из прошлых смет
A15: M-CON-020 | B15: Вязальная проволока | C15: кг | D15: =SUMIF('Orcamento RU Viora Build'!$A:$A,A15,'Orcamento RU Viora Build'!$F:$F) -> 1107.9489 | E15: =K15+(K15*N15) -> 2.054 | F15: =D15*E15 -> 2275.727 | I15: 1.58 | J15: 0 | K15: =I15-I15*J15 -> 1.58 | L15: =K15*D15 -> 1750.5593 | M15: =F15-L15 -> 525.16778 | N15: =$N$2 -> 0.3 | O15: =M15/F15 -> 0.23076923 | P15: Metalofarense | Q15: Цена из прошлых смет
A16: M-CON-022 | B16: Круги отрезные по металлу диаметром 230мм | C16: шт | D16: =SUMIF('Orcamento RU Viora Build'!$A:$A,A16,'Orcamento RU Viora Build'!$F:$F) -> 222.37978 | E16: =K16+(K16*N16) -> 0 | F16: =D16*E16 -> 0 | I16: 1.44 | J16: 1 | K16: =I16-I16*J16 -> 0 | L16: =K16*D16 -> 0 | M16: =F16-L16 -> 0 | N16: =$N$2 -> 0.3 | O16: =M16/F16 -> #DIV/0! | P16: тут | Q16: Цена из прошлых смет
A17: M-CON-023 | B17: Круги отрезные по дереву диаметром 180мм | C17: шт | D17: =SUMIF('Orcamento RU Viora Build'!$A:$A,A17,'Orcamento RU Viora Build'!$F:$F) -> 9.9971 | E17: =K17+(K17*N17) -> 0 | F17: =D17*E17 -> 0 | I17: 1.2 | J17: 1 | K17: =I17-I17*J17 -> 0 | L17: =K17*D17 -> 0 | M17: =F17-L17 -> 0 | N17: =$N$2 -> 0.3 | O17: =M17/F17 -> #DIV/0! | P17: тут | Q17: Цена из прошлых смет
A18: M-CON-030 | B18: Деревянные щиты опалубки | C18: м2 | D18: =SUMIF('Orcamento RU Viora Build'!$A:$A,A18,'Orcamento RU Viora Build'!$F:$F) -> 3158.13 | E18: =K18+(K18*N18) -> 0 | F18: =D18*E18 -> 0 | I18: 15 | J18: 1 | K18: =I18-I18*J18 -> 0 | L18: =K18*D18 -> 0 | M18: =F18-L18 -> 0 | N18: =$N$2 -> 0.3 | O18: =M18/F18 -> #DIV/0! | Q18: Цена из прошлых смет
A19: M-CON-031 | B19: Метизи | C19: кг | D19: =SUMIF('Orcamento RU Viora Build'!$A:$A,A19,'Orcamento RU Viora Build'!$F:$F) -> 261.22612 | E19: =K19+(K19*N19) -> 0 | F19: =D19*E19 -> 0 | I19: 3 | J19: 1 | K19: =I19-I19*J19 -> 0 | L19: =K19*D19 -> 0 | M19: =F19-L19 -> 0 | N19: =$N$2 -> 0.3 | O19: =M19/F19 -> #DIV/0! | Q19: Цена из прошлых смет
A20: M-CON-035 | B20: Канати попереднього напруження | C20: м | D20: =SUMIF('Orcamento RU Viora Build'!$A:$A,A20,'Orcamento RU Viora Build'!$F:$F) -> 1279.404 | E20: =K20+(K20*N20) -> 7.8 | F20: =D20*E20 -> 9979.3512 | I20: 6 | J20: 0 | K20: =I20-I20*J20 -> 6 | L20: =K20*D20 -> 7676.424 | M20: =F20-L20 -> 2302.9272 | N20: =$N$2 -> 0.3 | O20: =M20/F20 -> 0.23076923 | Q20: найдена только цена на алиэкспрессе
A21: M-CON-036 | B21: Активні анкери | C21: шт | D21: =SUMIF('Orcamento RU Viora Build'!$A:$A,A21,'Orcamento RU Viora Build'!$F:$F) -> 58 | E21: =K21+(K21*N21) -> 7.15 | F21: =D21*E21 -> 414.7 | I21: 5.5 | J21: 0 | K21: =I21-I21*J21 -> 5.5 | L21: =K21*D21 -> 319 | M21: =F21-L21 -> 95.7 | N21: =$N$2 -> 0.3 | O21: =M21/F21 -> 0.23076923 | P21: Jorge Material de Construção
A22: M-CON-037 | B22: Пасивні анкери | C22: шт | D22: =SUMIF('Orcamento RU Viora Build'!$A:$A,A22,'Orcamento RU Viora Build'!$F:$F) -> 58 | E22: =K22+(K22*N22) -> 6.37 | F22: =D22*E22 -> 369.46 | I22: 4.9 | J22: 0 | K22: =I22-I22*J22 -> 4.9 | L22: =K22*D22 -> 284.2 | M22: =F22-L22 -> 85.26 | N22: =$N$2 -> 0.3 | O22: =M22/F22 -> 0.23076923 | P22: Brico Depôt Faro
A23: M-CON-038 | B23: Система Cobiax для залізобетонних перекриттів | C23: шт | D23: =SUMIF('Orcamento RU Viora Build'!$A:$A,A23,'Orcamento RU Viora Build'!$F:$F) -> 638 | E23: =K23+(K23*N23) -> 3.25 | F23: =D23*E23 -> 2073.5 | I23: 2.5 | J23: 0 | K23: =I23-I23*J23 -> 2.5 | L23: =K23*D23 -> 1595 | M23: =F23-L23 -> 478.5 | N23: =$N$2 -> 0.3 | O23: =M23/F23 -> 0.23076923 | Q23: Невозможно найти + возможно неправильно указана ед. измерения
A24: M-CON-039 | B24: Бентонітовий шнур Waterstop | C24: м | D24: =SUMIF('Orcamento RU Viora Build'!$A:$A,A24,'Orcamento RU Viora Build'!$F:$F) -> 48.09 | E24: =K24+(K24*N24) -> 14.3728 | F24: =D24*E24 -> 691.18795 | I24: 11.056 | J24: 0 | K24: =I24-I24*J24 -> 11.056 | L24: =K24*D24 -> 531.68304 | M24: =F24-L24 -> 159.50491 | N24: =$N$2 -> 0.3 | O24: =M24/F24 -> 0.23076923 | P24: Brico Depôt Faro
A25: M-CON-040 | B25: Матеріали для влаштування деформаційного шва | C25: м | D25: =SUMIF('Orcamento RU Viora Build'!$A:$A,A25,'Orcamento RU Viora Build'!$F:$F) -> 10.941 | E25: =K25+(K25*N25) -> 25.48 | F25: =D25*E25 -> 278.77668 | I25: 19.6 | J25: 0 | K25: =I25-I25*J25 -> 19.6 | L25: =K25*D25 -> 214.4436 | M25: =F25-L25 -> 64.33308 | N25: =$N$2 -> 0.3 | O25: =M25/F25 -> 0.23076923 | P25: bricobutikk
A26: M-CON-041 | B26: Залізобетонні опори під плити | C26: шт | D26: =SUMIF('Orcamento RU Viora Build'!$A:$A,A26,'Orcamento RU Viora Build'!$F:$F) -> 18 | E26: =K26+(K26*N26) -> 163.67 | F26: =D26*E26 -> 2946.06 | I26: 125.9 | J26: 0 | K26: =I26-I26*J26 -> 125.9 | L26: =K26*D26 -> 2266.2 | M26: =F26-L26 -> 679.86 | N26: =$N$2 -> 0.3 | O26: =M26/F26 -> 0.23076923 | P26: geradordeprecos
A27: M-CON-050 | B27: Металоконструкції колон | C27: кг | D27: =SUMIF('Orcamento RU Viora Build'!$A:$A,A27,'Orcamento RU Viora Build'!$F:$F) -> 5975.56 | E27: =K27+(K27*N27) -> 3.042 | F27: =D27*E27 -> 18177.654 | I27: 2.6 | J27: 0.1 | K27: =I27-I27*J27 -> 2.34 | L27: =K27*D27 -> 13982.81 | M27: =F27-L27 -> 4194.8431 | N27: =$N$2 -> 0.3 | O27: =M27/F27 -> 0.23076923 | P27: geradordeprecos
A28: M-CON-051 | B28: Металоконструкції балок | C28: кг | D28: =SUMIF('Orcamento RU Viora Build'!$A:$A,A28,'Orcamento RU Viora Build'!$F:$F) -> 3972.81 | E28: =K28+(K28*N28) -> 2.808 | F28: =D28*E28 -> 11155.65 | I28: 2.4 | J28: 0.1 | K28: =I28-I28*J28 -> 2.16 | L28: =K28*D28 -> 8581.2696 | M28: =F28-L28 -> 2574.3809 | N28: =$N$2 -> 0.3 | O28: =M28/F28 -> 0.23076923 | P28: majodir
A29: M-CON-052 | B29: Профіль металевий | C29: кг | D29: =SUMIF('Orcamento RU Viora Build'!$A:$A,A29,'Orcamento RU Viora Build'!$F:$F) -> 2891.1435 | E29: =K29+(K29*N29) -> 2.574 | F29: =D29*E29 -> 7441.8034 | I29: 2.2 | J29: 0.1 | K29: =I29-I29*J29 -> 1.98 | L29: =K29*D29 -> 5724.4641 | M29: =F29-L29 -> 1717.3392 | N29: =$N$2 -> 0.3 | O29: =M29/F29 -> 0.23076923 | P29: masterferro
A30: Цегляна кладка
A31: M-BRK-001 | B31: Кирпич размером 30х20х25см | C31: шт | D31: =SUMIF('Orcamento RU Viora Build'!$A:$A,A31,'Orcamento RU Viora Build'!$F:$F) -> 2487 | E31: =K31+(K31*N31) -> 1.105 | F31: =D31*E31 -> 2748.135 | I31: 0.85 | J31: 0 | K31: =I31-I31*J31 -> 0.85 | L31: =K31*D31 -> 2113.95 | M31: =F31-L31 -> 634.185 | N31: =$N$2 -> 0.3 | O31: =M31/F31 -> 0.23076923 | P31: Recom | Q31: Цена из прошлых смет
A32: M-BRK-002 | B32: Кирпич размером 30х20х15см | C32: шт | D32: =SUMIF('Orcamento RU Viora Build'!$A:$A,A32,'Orcamento RU Viora Build'!$F:$F) -> 3454 | E32: =K32+(K32*N32) -> 0.728 | F32: =D32*E32 -> 2514.512 | I32: 0.56 | J32: 0 | K32: =I32-I32*J32 -> 0.56 | L32: =K32*D32 -> 1934.24 | M32: =F32-L32 -> 580.272 | N32: =$N$2 -> 0.3 | O32: =M32/F32 -> 0.23076923 | P32: Recom | Q32: Цена из прошлых смет
A33: M-BRK-003 | B33: Кирпич размером 30х20х11см | C33: шт | D33: =SUMIF('Orcamento RU Viora Build'!$A:$A,A33,'Orcamento RU Viora Build'!$F:$F) -> 3846 | E33: =K33+(K33*N33) -> 0.559 | F33: =D33*E33 -> 2149.914 | I33: 0.43 | J33: 0 | K33: =I33-I33*J33 -> 0.43 | L33: =K33*D33 -> 1653.78 | M33: =F33-L33 -> 496.134 | N33: =$N$2 -> 0.3 | O33: =M33/F33 -> 0.23076923 | P33: Recom | Q33: Цена из прошлых смет
A34: M-BRK-008 | B34: Кирпич размером 30х20х7см | C34: шт | D34: =SUMIF('Orcamento RU Viora Build'!$A:$A,A34,'Orcamento RU Viora Build'!$F:$F) -> 235 | E34: =K34+(K34*N34) -> 0.351 | F34: =D34*E34 -> 82.485 | I34: 0.27 | J34: 0 | K34: =I34-I34*J34 -> 0.27 | L34: =K34*D34 -> 63.45 | M34: =F34-L34 -> 19.035 | N34: =$N$2 -> 0.3 | O34: =M34/F34 -> 0.23076923 | P34: Abel de Oliveira Carrasquinho | Q34: Цена из прошлых смет
A35: M-BRK-009 | B35: Блоки бетонні розміром 50x20x25см | C35: шт | D35: =SUMIF('Orcamento RU Viora Build'!$A:$A,A35,'Orcamento RU Viora Build'!$F:$F) -> 772 | E35: =K35+(K35*N35) -> 1.989 | F35: =D35*E35 -> 1535.508 | I35: 1.53 | J35: 0 | K35: =I35-I35*J35 -> 1.53 | L35: =K35*D35 -> 1181.16 | M35: =F35-L35 -> 354.348 | N35: =$N$2 -> 0.3 | O35: =M35/F35 -> 0.23076923 | P35: База
A36: M-BRK-004 | B36: Блоки бетонні розміром 50x20x20см | C36: шт | D36: =SUMIF('Orcamento RU Viora Build'!$A:$A,A36,'Orcamento RU Viora Build'!$F:$F) -> 940 | E36: =K36+(K36*N36) -> 1.781 | F36: =D36*E36 -> 1674.14 | I36: 1.37 | J36: 0 | K36: =I36-I36*J36 -> 1.37 | L36: =K36*D36 -> 1287.8 | M36: =F36-L36 -> 386.34 | N36: =$N$2 -> 0.3 | O36: =M36/F36 -> 0.23076923 | P36: База | Q36: Цена из прошлых смет
A37: M-BRK-005 | B37: Блоки бетонні розміром 50x20x15см | C37: шт | D37: =SUMIF('Orcamento RU Viora Build'!$A:$A,A37,'Orcamento RU Viora Build'!$F:$F) -> 200 | E37: =K37+(K37*N37) -> 0.91 | F37: =D37*E37 -> 182 | I37: 0.7 | J37: 0 | K37: =I37-I37*J37 -> 0.7 | L37: =K37*D37 -> 140 | M37: =F37-L37 -> 42 | N37: =$N$2 -> 0.3 | O37: =M37/F37 -> 0.23076923 | P37: База | Q37: Цена из прошлых смет
A38: M-BRK-025 | B38: Цемент | C38: т | D38: =SUMIF('Orcamento RU Viora Build'!$A:$A,A38,'Orcamento RU Viora Build'!$F:$F) -> 28.7554 | E38: =K38+(K38*N38) -> 189.1032 | F38: =D38*E38 -> 5437.7382 | I38: 167.2 | J38: 0.13 | K38: =I38-I38*J38 -> 145.464 | L38: =K38*D38 -> 4182.8755 | M38: =F38-L38 -> 1254.8627 | N38: =$N$2 -> 0.3 | O38: =M38/F38 -> 0.23076923 | P38: Abel de Oliveira Carrasquinho | Q38: Цена из прошлых смет
A39: M-BRK-026 | B39: Песок | C39: м3 | D39: =SUMIF('Orcamento RU Viora Build'!$A:$A,A39,'Orcamento RU Viora Build'!$F:$F) -> 107.81015 | E39: =K39+(K39*N39) -> 56.875 | F39: =D39*E39 -> 6131.7023 | I39: 43.75 | J39: 0 | K39: =I39-I39*J39 -> 43.75 | L39: =K39*D39 -> 4716.6941 | M39: =F39-L39 -> 1415.0082 | N39: =$N$2 -> 0.3 | O39: =M39/F39 -> 0.23076923 | P39: База Данных | Q39: Цена из прошлых смет
A40: Покрівля
A41: M-ROF-004 | B41: Руберойд POLYPLAS 30 | C41: м2 | D41: =SUMIF('Orcamento RU Viora Build'!$A:$A,A41,'Orcamento RU Viora Build'!$F:$F) -> 367.708 | E41: =K41+(K41*N41) -> 4.225 | F41: =D41*E41 -> 1553.5663 | I41: 3.25 | J41: 0 | K41: =I41-I41*J41 -> 3.25 | L41: =K41*D41 -> 1195.051 | M41: =F41-L41 -> 358.5153 | N41: =$N$2 -> 0.3 | O41: =M41/F41 -> 0.23076923 | P41: Leroy Marlin
A42: M-ROF-008 | B42: Руберойд POLYXIS R40 | C42: м2 | D42: =SUMIF('Orcamento RU Viora Build'!$A:$A,A42,'Orcamento RU Viora Build'!$F:$F) -> 367.708 | E42: =K42+(K42*N42) -> 8.97 | F42: =D42*E42 -> 3298.3408 | I42: 6.9 | J42: 0 | K42: =I42-I42*J42 -> 6.9 | L42: =K42*D42 -> 2537.1852 | M42: =F42-L42 -> 761.15556 | N42: =$N$2 -> 0.3 | O42: =M42/F42 -> 0.23076923 | P42: Tyt
A43: M-ROF-015 | B43: Гідроізоляційна мембрана RHENOFOL CV | C43: м2 | D43: =SUMIF('Orcamento RU Viora Build'!$A:$A,A43,'Orcamento RU Viora Build'!$F:$F) -> 200.101 | E43: =K43+(K43*N43) -> 12.597 | F43: =D43*E43 -> 2520.6723 | I43: 9.69 | J43: 0 | K43: =I43-I43*J43 -> 9.69 | L43: =K43*D43 -> 1938.9787 | M43: =F43-L43 -> 581.69361 | N43: =$N$2 -> 0.3 | O43: =M43/F43 -> 0.23076923 | P43: Ссылка | Q43: Такой гидроизоляции нету в Португалии
A44: M-ROF-017 | B44: Плити OSB товщиною 22мм | C44: м2 | D44: =SUMIF('Orcamento RU Viora Build'!$A:$A,A44,'Orcamento RU Viora Build'!$F:$F) -> 382.011 | E44: =K44+(K44*N44) -> 26.767 | F44: =D44*E44 -> 10225.288 | I44: 20.59 | J44: 0 | K44: =I44-I44*J44 -> 20.59 | L44: =K44*D44 -> 7865.6065 | M44: =F44-L44 -> 2359.6819 | N44: =$N$2 -> 0.3 | O44: =M44/F44 -> 0.23076923 | P44: Recom
A45: M-ROF-016 | B45: Оцинковані листи для покрівлі | C45: м2 | D45: =SUMIF('Orcamento RU Viora Build'!$A:$A,A45,'Orcamento RU Viora Build'!$F:$F) -> 216.7 | E45: =K45+(K45*N45) -> 67.6 | F45: =D45*E45 -> 14648.92 | I45: 52 | J45: 0 | K45: =I45-I45*J45 -> 52 | L45: =K45*D45 -> 11268.4 | M45: =F45-L45 -> 3380.52 | N45: =$N$2 -> 0.3 | O45: =M45/F45 -> 0.23076923 | P45: majodir | Q45: Не указан размер листа
A46: M-ROF-018 | B46: Кріплення для оцинкованих листів | C46: шт | D46: =SUMIF('Orcamento RU Viora Build'!$A:$A,A46,'Orcamento RU Viora Build'!$F:$F) -> 1213 | E46: =K46+(K46*N46) -> 0.507 | F46: =D46*E46 -> 614.991 | I46: 0.39 | J46: 0 | K46: =I46-I46*J46 -> 0.39 | L46: =K46*D46 -> 473.07 | M46: =F46-L46 -> 141.921 | N46: =$N$2 -> 0.3 | O46: =M46/F46 -> 0.23076923 | P46: armazensreis
A47: M-ROF-005 | B47: Геотекстиль IMPERSEP 200 | C47: м2 | D47: =SUMIF('Orcamento RU Viora Build'!$A:$A,A47,'Orcamento RU Viora Build'!$F:$F) -> 693.048 | E47: =K47+(K47*N47) -> 1.066 | F47: =D47*E47 -> 738.78917 | I47: 0.82 | J47: 0 | K47: =I47-I47*J47 -> 0.82 | L47: =K47*D47 -> 568.29936 | M47: =F47-L47 -> 170.48981 | N47: =$N$2 -> 0.3 | O47: =M47/F47 -> 0.23076923 | P47: База
A48: M-ROF-0010 | B48: Геотекстиль IMPERSEP 150 | C48: м2 | D48: =SUMIF('Orcamento RU Viora Build'!$A:$A,A48,'Orcamento RU Viora Build'!$F:$F) -> 988.394 | E48: =K48+(K48*N48) -> 0.91 | F48: =D48*E48 -> 899.43854 | I48: 0.7 | J48: 0 | K48: =I48-I48*J48 -> 0.7 | L48: =K48*D48 -> 691.8758 | M48: =F48-L48 -> 207.56274 | N48: =$N$2 -> 0.3 | O48: =M48/F48 -> 0.23076923 | P48: База
A49: M-ROF-007 | B49: Бітумна емульсія Imperkote F | C49: кг | D49: =SUMIF('Orcamento RU Viora Build'!$A:$A,A49,'Orcamento RU Viora Build'!$F:$F) -> 60.18 | E49: =K49+(K49*N49) -> 2.925 | F49: =D49*E49 -> 176.0265 | I49: 2.25 | J49: 0 | K49: =I49-I49*J49 -> 2.25 | L49: =K49*D49 -> 135.405 | M49: =F49-L49 -> 40.6215 | N49: =$N$2 -> 0.3 | O49: =M49/F49 -> 0.23076923 | P49: База
A50: Гідроізоляція
A51: M-IMP-002 | B51: Газ пропан-бутан в баллонах 40л | C51: шт | D51: =SUMIF('Orcamento RU Viora Build'!$A:$A,A51,'Orcamento RU Viora Build'!$F:$F) -> 7.0126526 | E51: =K51+(K51*N51) -> 140.4 | F51: =D51*E51 -> 984.57643 | I51: 108 | J51: 0 | K51: =I51-I51*J51 -> 108 | L51: =K51*D51 -> 757.36648 | M51: =F51-L51 -> 227.20995 | N51: =$N$2 -> 0.3 | O51: =M51/F51 -> 0.23076923 | P51: Ссылка
A52: M-IMP-006 | B52: Гидроизоляция Weber.tec 824 | C52: кг | D52: =SUMIF('Orcamento RU Viora Build'!$A:$A,A52,'Orcamento RU Viora Build'!$F:$F) -> 62.132 | E52: =K52+(K52*N52) -> 3.302 | F52: =D52*E52 -> 205.15986 | I52: 2.54 | J52: 0 | K52: =I52-I52*J52 -> 2.54 | L52: =K52*D52 -> 157.81528 | M52: =F52-L52 -> 47.344584 | N52: =$N$2 -> 0.3 | O52: =M52/F52 -> 0.23076923 | P52: База | Q52: Цена из прошлых смет
A53: M-IMP-007 | B53: Мембрана дренажна | C53: м2 | D53: =SUMIF('Orcamento RU Viora Build'!$A:$A,A53,'Orcamento RU Viora Build'!$F:$F) -> 333.817 | E53: =K53+(K53*N53) -> 2.574 | F53: =D53*E53 -> 859.24496 | I53: 1.98 | J53: 0 | K53: =I53-I53*J53 -> 1.98 | L53: =K53*D53 -> 660.95766 | M53: =F53-L53 -> 198.2873 | N53: =$N$2 -> 0.3 | O53: =M53/F53 -> 0.23076923 | P53: RECOM | Q53: MEMBR.DANODREN H25 2,10X20mts. 42m2/RL
A54: M-IMP-008 | B54: Притискна планка для дренажної мембрани | C54: м | D54: =SUMIF('Orcamento RU Viora Build'!$A:$A,A54,'Orcamento RU Viora Build'!$F:$F) -> 273 | E54: =K54+(K54*N54) -> 3.25 | F54: =D54*E54 -> 887.25 | I54: 2.5 | J54: 0 | K54: =I54-I54*J54 -> 2.5 | L54: =K54*D54 -> 682.5 | M54: =F54-L54 -> 204.75 | N54: =$N$2 -> 0.3 | O54: =M54/F54 -> 0.23076923 | P54: Ссылка
A55: M-IMP-009 | B55: Кріплення для дренажної мембрани | C55: шт | D55: =SUMIF('Orcamento RU Viora Build'!$A:$A,A55,'Orcamento RU Viora Build'!$F:$F) -> 1820.82 | E55: =K55+(K55*N55) -> 1.3 | F55: =D55*E55 -> 2367.066 | I55: 1 | J55: 0 | K55: =I55-I55*J55 -> 1 | L55: =K55*D55 -> 1820.82 | M55: =F55-L55 -> 546.246 | N55: =$N$2 -> 0.3 | O55: =M55/F55 -> 0.23076923 | P55: Ссылка
A56: M-IMP-010 | B56: Труба дренажна діаметром 200мм | C56: м | D56: =SUMIF('Orcamento RU Viora Build'!$A:$A,A56,'Orcamento RU Viora Build'!$F:$F) -> 273 | E56: =K56+(K56*N56) -> 7.839 | F56: =D56*E56 -> 2140.047 | I56: 6.03 | J56: 0 | K56: =I56-I56*J56 -> 6.03 | L56: =K56*D56 -> 1646.19 | M56: =F56-L56 -> 493.857 | N56: =$N$2 -> 0.3 | O56: =M56/F56 -> 0.23076923 | P56: Recom
A57: M-IMP-012 | B57: Труба дренажна діаметром 100мм | C57: м | D57: =SUMIF('Orcamento RU Viora Build'!$A:$A,A57,'Orcamento RU Viora Build'!$F:$F) -> 292.9185 | E57: =K57+(K57*N57) -> 2.639 | F57: =D57*E57 -> 773.01192 | I57: 2.03 | J57: 0 | K57: =I57-I57*J57 -> 2.03 | L57: =K57*D57 -> 594.62455 | M57: =F57-L57 -> 178.38737 | N57: =$N$2 -> 0.3 | O57: =M57/F57 -> 0.23076923 | P57: Recom
A58: M-IMP-011 | B58: Шумоізоляційна мембрана Impactodan | C58: м2 | D58: =SUMIF('Orcamento RU Viora Build'!$A:$A,A58,'Orcamento RU Viora Build'!$F:$F) -> 336.735 | E58: =K58+(K58*N58) -> 3.38 | F58: =D58*E58 -> 1138.1643 | I58: 2.6 | J58: 0 | K58: =I58-I58*J58 -> 2.6 | L58: =K58*D58 -> 875.511 | M58: =F58-L58 -> 262.6533 | N58: =$N$2 -> 0.3 | O58: =M58/F58 -> 0.23076923 | P58: Recom
A59: M-IMP-015 | B59: Щебень №2 | C59: м3 | D59: =SUMIF('Orcamento RU Viora Build'!$A:$A,A59,'Orcamento RU Viora Build'!$F:$F) -> 291.12307 | E59: =K59+(K59*N59) -> 31.07 | F59: =D59*E59 -> 9045.1939 | I59: 23.9 | J59: 0 | K59: =I59-I59*J59 -> 23.9 | L59: =K59*D59 -> 6957.8415 | M59: =F59-L59 -> 2087.3524 | N59: =$N$2 -> 0.3 | O59: =M59/F59 -> 0.23076923 | P59: JAM | Q59: Цена из прошлых смет
A60: M-IMP-020 | B60: Гравій №2 | C60: м3 | D60: =SUMIF('Orcamento RU Viora Build'!$A:$A,A60,'Orcamento RU Viora Build'!$F:$F) -> 7.9023 | E60: =K60+(K60*N60) -> 31.07 | F60: =D60*E60 -> 245.52446 | I60: 23.9 | J60: 0 | K60: =I60-I60*J60 -> 23.9 | L60: =K60*D60 -> 188.86497 | M60: =F60-L60 -> 56.659491 | N60: =$N$2 -> 0.3 | O60: =M60/F60 -> 0.23076923 | Q60: Цена из прошлых смет
A61: M-IMP-021 | B61: Соснова кора | C61: м3 | D61: =SUMIF('Orcamento RU Viora Build'!$A:$A,A61,'Orcamento RU Viora Build'!$F:$F) -> 1.8417 | E61: =K61+(K61*N61) -> 304.07 | F61: =D61*E61 -> 560.00572 | I61: 233.9 | J61: 0 | K61: =I61-I61*J61 -> 233.9 | L61: =K61*D61 -> 430.77363 | M61: =F61-L61 -> 129.23209 | N61: =$N$2 -> 0.3 | O61: =M61/F61 -> 0.23076923 | P61: plantalivre | Q61: возможно также заказать здесь намного дешевле
A62: M-IMP-018 | B62: Праймер битумный | C62: кг | D62: =SUMIF('Orcamento RU Viora Build'!$A:$A,A62,'Orcamento RU Viora Build'!$F:$F) -> 36.762 | E62: =K62+(K62*N62) -> 2.6 | F62: =D62*E62 -> 95.5812 | I62: 2 | J62: 0 | K62: =I62-I62*J62 -> 2 | L62: =K62*D62 -> 73.524 | M62: =F62-L62 -> 22.0572 | N62: =$N$2 -> 0.3 | O62: =M62/F62 -> 0.23076923 | P62: Obramat
A63: Термоізоляція
A64: M-TER-002 | B64: Экструдированный пенополистирол толщиной 80мм | C64: м2 | D64: =SUMIF('Orcamento RU Viora Build'!$A:$A,A64,'Orcamento RU Viora Build'!$F:$F) -> 622.3875 | E64: =K64+(K64*N64) -> 12.116 | F64: =D64*E64 -> 7540.847 | I64: 9.32 | J64: 0 | K64: =I64-I64*J64 -> 9.32 | L64: =K64*D64 -> 5800.6515 | M64: =F64-L64 -> 1740.1954 | N64: =$N$2 -> 0.3 | O64: =M64/F64 -> 0.23076923 | P64: Obramat
A65: M-TER-004 | B65: Экструдированный пенополистирол толщиной 70мм | C65: м2 | D65: =SUMIF('Orcamento RU Viora Build'!$A:$A,A65,'Orcamento RU Viora Build'!$F:$F) -> 138.054 | E65: =K65+(K65*N65) -> 10.712 | F65: =D65*E65 -> 1478.8344 | I65: 8.24 | J65: 0 | K65: =I65-I65*J65 -> 8.24 | L65: =K65*D65 -> 1137.565 | M65: =F65-L65 -> 341.26949 | N65: =$N$2 -> 0.3 | O65: =M65/F65 -> 0.23076923 | Q65: Цена из прошлых смет
A66: M-TER-010 | B66: Мінеральна вата товщиною 170мм | C66: м2 | D66: =SUMIF('Orcamento RU Viora Build'!$A:$A,A66,'Orcamento RU Viora Build'!$F:$F) -> 191.0055 | E66: =K66+(K66*N66) -> 20.8 | F66: =D66*E66 -> 3972.9144 | I66: 16 | J66: 0 | K66: =I66-I66*J66 -> 16 | L66: =K66*D66 -> 3056.088 | M66: =F66-L66 -> 916.8264 | N66: =$N$2 -> 0.3 | O66: =M66/F66 -> 0.23076923 | P66: Ссылка | Q66: Не смог найти цены на 170мм, нашел цену на 160мм, 14 евро, прикрепляю где можно заказать, но нет цены
A67: M-TER-011 | B67: Мінеральна вата товщиною 90мм | C67: м2 | D67: =SUMIF('Orcamento RU Viora Build'!$A:$A,A67,'Orcamento RU Viora Build'!$F:$F) -> 20.3175 | E67: =K67+(K67*N67) -> 4.004 | F67: =D67*E67 -> 81.35127 | I67: 3.08 | J67: 0 | K67: =I67-I67*J67 -> 3.08 | L67: =K67*D67 -> 62.5779 | M67: =F67-L67 -> 18.77337 | N67: =$N$2 -> 0.3 | O67: =M67/F67 -> 0.23076923 | P67: Ссылка
A68: M-TER-012 | B68: Мінеральна вата товщиною 50мм | C68: м2 | D68: =SUMIF('Orcamento RU Viora Build'!$A:$A,A68,'Orcamento RU Viora Build'!$F:$F) -> 79.6425 | E68: =K68+(K68*N68) -> 2.847 | F68: =D68*E68 -> 226.7422 | I68: 2.19 | J68: 0 | K68: =I68-I68*J68 -> 2.19 | L68: =K68*D68 -> 174.41708 | M68: =F68-L68 -> 52.325122 | N68: =$N$2 -> 0.3 | O68: =M68/F68 -> 0.23076923 | P68: Ссылка
A69: M-TER-013 | B69: Мінеральна вата товщиною 40мм | C69: м2 | D69: =SUMIF('Orcamento RU Viora Build'!$A:$A,A69,'Orcamento RU Viora Build'!$F:$F) -> 13.5555 | E69: =K69+(K69*N69) -> 3.627 | F69: =D69*E69 -> 49.165799 | I69: 2.79 | J69: 0 | K69: =I69-I69*J69 -> 2.79 | L69: =K69*D69 -> 37.819845 | M69: =F69-L69 -> 11.345954 | N69: =$N$2 -> 0.3 | O69: =M69/F69 -> 0.23076923 | P69: Ссылка
A70: M-TER-014 | B70: Мінеральна вата товщиною 30мм | C70: м2 | D70: =SUMIF('Orcamento RU Viora Build'!$A:$A,A70,'Orcamento RU Viora Build'!$F:$F) -> 11.5395 | E70: =K70+(K70*N70) -> 3.627 | F70: =D70*E70 -> 41.853766 | I70: 2.79 | J70: 0 | K70: =I70-I70*J70 -> 2.79 | L70: =K70*D70 -> 32.195205 | M70: =F70-L70 -> 9.6585615 | N70: =$N$2 -> 0.3 | O70: =M70/F70 -> 0.23076923 | P70: Ссылка
A71: M-TER-005 | B71: Дюбели для пенопласта | C71: шт | D71: =SUMIF('Orcamento RU Viora Build'!$A:$A,A71,'Orcamento RU Viora Build'!$F:$F) -> 788.88 | E71: =K71+(K71*N71) -> 0.078 | F71: =D71*E71 -> 61.53264 | I71: 0.06 | J71: 0 | K71: =I71-I71*J71 -> 0.06 | L71: =K71*D71 -> 47.3328 | M71: =F71-L71 -> 14.19984 | N71: =$N$2 -> 0.3 | O71: =M71/F71 -> 0.23076923 | P71: Recom | Q71: Цена из прошлых смет
A72: M-TER-006 | B72: Клей для пенопласта | C72: кг | D72: =SUMIF('Orcamento RU Viora Build'!$A:$A,A72,'Orcamento RU Viora Build'!$F:$F) -> 1577.76 | E72: =K72+(K72*N72) -> 0.897 | F72: =D72*E72 -> 1415.2507 | I72: 0.69 | J72: 0 | K72: =I72-I72*J72 -> 0.69 | L72: =K72*D72 -> 1088.6544 | M72: =F72-L72 -> 326.59632 | N72: =$N$2 -> 0.3 | O72: =M72/F72 -> 0.23076923 | P72: Recom
A73: Оздоблення
A74: M-FIN-001 | B74: Клей для плитки Weber.col flex M | C74: кг | D74: =SUMIF('Orcamento RU Viora Build'!$A:$A,A74,'Orcamento RU Viora Build'!$F:$F) -> 917.856 | E74: =K74+(K74*N74) -> 0.715 | F74: =D74*E74 -> 656.26704 | I74: 0.55 | J74: 0 | K74: =I74-I74*J74 -> 0.55 | L74: =K74*D74 -> 504.8208 | M74: =F74-L74 -> 151.44624 | N74: =$N$2 -> 0.3 | O74: =M74/F74 -> 0.23076923 | P74: Nepeli
A75: M-FIN-004 | B75: Клей для природного камня Kerakoll H40 | C75: кг | D75: =SUMIF('Orcamento RU Viora Build'!$A:$A,A75,'Orcamento RU Viora Build'!$F:$F) -> 31.16 | E75: =K75+(K75*N75) -> 0.871 | F75: =D75*E75 -> 27.14036 | I75: 0.67 | J75: 0 | K75: =I75-I75*J75 -> 0.67 | L75: =K75*D75 -> 20.8772 | M75: =F75-L75 -> 6.26316 | N75: =$N$2 -> 0.3 | O75: =M75/F75 -> 0.23076923 | P75: Nepeli
A76: M-FIN-005 | B76: Клей для плитки в басейні Adhere | C76: кг | D76: =SUMIF('Orcamento RU Viora Build'!$A:$A,A76,'Orcamento RU Viora Build'!$F:$F) -> 1604.8 | E76: =K76+(K76*N76) -> 1.313 | F76: =D76*E76 -> 2107.1024 | I76: 1.01 | J76: 0 | K76: =I76-I76*J76 -> 1.01 | L76: =K76*D76 -> 1620.848 | M76: =F76-L76 -> 486.2544 | N76: =$N$2 -> 0.3 | O76: =M76/F76 -> 0.23076923 | P76: DavidNuno
A77: M-FIN-007 | B77: Затирка для плитки Weber Premium | C77: кг | D77: =SUMIF('Orcamento RU Viora Build'!$A:$A,A77,'Orcamento RU Viora Build'!$F:$F) -> 76.488 | E77: =K77+(K77*N77) -> 1.937 | F77: =D77*E77 -> 148.15726 | I77: 1.49 | J77: 0 | K77: =I77-I77*J77 -> 1.49 | L77: =K77*D77 -> 113.96712 | M77: =F77-L77 -> 34.190136 | N77: =$N$2 -> 0.3 | O77: =M77/F77 -> 0.23076923 | P77: Recom
A78: M-FIN-002 | B78: Клей для паркету | C78: кг | D78: =SUMIF('Orcamento RU Viora Build'!$A:$A,A78,'Orcamento RU Viora Build'!$F:$F) -> 287.76 | E78: =K78+(K78*N78) -> 7.345 | F78: =D78*E78 -> 2113.5972 | I78: 5.65 | J78: 0 | K78: =I78-I78*J78 -> 5.65 | L78: =K78*D78 -> 1625.844 | M78: =F78-L78 -> 487.7532 | N78: =$N$2 -> 0.3 | O78: =M78/F78 -> 0.23076923 | P78: Ссылка
A79: M-FIN-003 | B79: Фарба епоксидна SIKAFLOOR-264 | C79: кг | D79: =SUMIF('Orcamento RU Viora Build'!$A:$A,A79,'Orcamento RU Viora Build'!$F:$F) -> 55.092 | E79: =K79+(K79*N79) -> 15.262 | F79: =D79*E79 -> 840.8141 | I79: 11.74 | J79: 0 | K79: =I79-I79*J79 -> 11.74 | L79: =K79*D79 -> 646.78008 | M79: =F79-L79 -> 194.03402 | N79: =$N$2 -> 0.3 | O79: =M79/F79 -> 0.23076923 | P79: Ссылка
A80: M-FIN-008 | B80: Система выравнивания плитки СВП (300шт) | C80: уп | D80: =SUMIF('Orcamento RU Viora Build'!$A:$A,A80,'Orcamento RU Viora Build'!$F:$F) -> 5 | E80: =K80+(K80*N80) -> 17.94 | F80: =D80*E80 -> 89.7 | I80: 13.8 | J80: 0 | K80: =I80-I80*J80 -> 13.8 | L80: =K80*D80 -> 69 | M80: =F80-L80 -> 20.7 | N80: =$N$2 -> 0.3 | O80: =M80/F80 -> 0.23076923 | P80: Sulcave
A81: M-FIN-009 | B81: Кутник з нержавіючої сталі розміром 15х15см | C81: м | D81: =SUMIF('Orcamento RU Viora Build'!$A:$A,A81,'Orcamento RU Viora Build'!$F:$F) -> 257.229 | E81: =K81+(K81*N81) -> 20.787 | F81: =D81*E81 -> 5347.0192 | I81: 15.99 | J81: 0 | K81: =I81-I81*J81 -> 15.99 | L81: =K81*D81 -> 4113.0917 | M81: =F81-L81 -> 1233.9275 | N81: =$N$2 -> 0.3 | O81: =M81/F81 -> 0.23076923 | P81: Casapeixoto
A82: M-FIN-030 | B82: Лист гипсокартонный влагостойкий размером 2500х1200х12,5 мм | C82: шт | D82: =SUMIF('Orcamento RU Viora Build'!$A:$A,A82,'Orcamento RU Viora Build'!$F:$F) -> 69.9955 | E82: =K82+(K82*N82) -> 16.9 | F82: =D82*E82 -> 1182.924 | I82: 13 | J82: 0 | K82: =I82-I82*J82 -> 13 | L82: =K82*D82 -> 909.9415 | M82: =F82-L82 -> 272.98245 | N82: =$N$2 -> 0.3 | O82: =M82/F82 -> 0.23076923 | P82: тут
A83: M-FIN-043 | B83: Лист гипсокартонный размером 2500х1200х12,5 мм | C83: шт | D83: =SUMIF('Orcamento RU Viora Build'!$A:$A,A83,'Orcamento RU Viora Build'!$F:$F) -> 104.9985 | E83: =K83+(K83*N83) -> 13.494 | F83: =D83*E83 -> 1416.8498 | I83: 10.38 | J83: 0 | K83: =I83-I83*J83 -> 10.38 | L83: =K83*D83 -> 1089.8844 | M83: =F83-L83 -> 326.96533 | N83: =$N$2 -> 0.3 | O83: =M83/F83 -> 0.23076923 | P83: Ссылка
A84: M-FIN-044 | B84: Плити МДФ товщиною 19мм | C84: м2 | D84: =SUMIF('Orcamento RU Viora Build'!$A:$A,A84,'Orcamento RU Viora Build'!$F:$F) -> 13.5555 | E84: =K84+(K84*N84) -> 8.593 | F84: =D84*E84 -> 116.48241 | I84: 6.61 | J84: 0 | K84: =I84-I84*J84 -> 6.61 | L84: =K84*D84 -> 89.601855 | M84: =F84-L84 -> 26.880557 | N84: =$N$2 -> 0.3 | O84: =M84/F84 -> 0.23076923 | P84: Mundimat
A85: M-FIN-042 | B85: Профіль для гіпсокартонних перегородок | C85: м | D85: =SUMIF('Orcamento RU Viora Build'!$A:$A,A85,'Orcamento RU Viora Build'!$F:$F) -> 432.275 | E85: =K85+(K85*N85) -> 2.587 | F85: =D85*E85 -> 1118.2954 | I85: 1.99 | J85: 0 | K85: =I85-I85*J85 -> 1.99 | L85: =K85*D85 -> 860.22725 | M85: =F85-L85 -> 258.06817 | N85: =$N$2 -> 0.3 | O85: =M85/F85 -> 0.23076923 | P85: MaxMat
A86: M-FIN-031 | B86: Уголок направляющий размером 30х30 мм | C86: м | D86: =SUMIF('Orcamento RU Viora Build'!$A:$A,A86,'Orcamento RU Viora Build'!$F:$F) -> 266.803 | E86: =K86+(K86*N86) -> 0.429 | F86: =D86*E86 -> 114.45849 | I86: 0.33 | J86: 0 | K86: =I86-I86*J86 -> 0.33 | L86: =K86*D86 -> 88.04499 | M86: =F86-L86 -> 26.413497 | N86: =$N$2 -> 0.3 | O86: =M86/F86 -> 0.23076923 | Q86: Эти цены были проставленны Алленой в прошлых просчетах из чека
A87: M-FIN-032 | B87: Профиль потолочный | C87: м | D87: =SUMIF('Orcamento RU Viora Build'!$A:$A,A87,'Orcamento RU Viora Build'!$F:$F) -> 724.2085 | E87: =K87+(K87*N87) -> 0.611 | F87: =D87*E87 -> 442.49139 | I87: 0.47 | J87: 0 | K87: =I87-I87*J87 -> 0.47 | L87: =K87*D87 -> 340.37799 | M87: =F87-L87 -> 102.1134 | N87: =$N$2 -> 0.3 | O87: =M87/F87 -> 0.23076923 | Q87: Эти цены были проставленны Алленой в прошлых просчетах из чека
A88: M-FIN-033 | B88: Резьба М6 длиной 1м | C88: шт | D88: =SUMIF('Orcamento RU Viora Build'!$A:$A,A88,'Orcamento RU Viora Build'!$F:$F) -> 58.32072 | E88: =K88+(K88*N88) -> 0.338 | F88: =D88*E88 -> 19.712403 | I88: 0.26 | J88: 0 | K88: =I88-I88*J88 -> 0.26 | L88: =K88*D88 -> 15.163387 | M88: =F88-L88 -> 4.5490162 | N88: =$N$2 -> 0.3 | O88: =M88/F88 -> 0.23076923 | Q88: Эти цены были проставленны Алленой в прошлых просчетах из чека
A89: M-FIN-034 | B89: Латунная втулка | C89: шт | D89: =SUMIF('Orcamento RU Viora Build'!$A:$A,A89,'Orcamento RU Viora Build'!$F:$F) -> 526.5065 | E89: =K89+(K89*N89) -> 0.078 | F89: =D89*E89 -> 41.067507 | I89: 0.06 | J89: 0 | K89: =I89-I89*J89 -> 0.06 | L89: =K89*D89 -> 31.59039 | M89: =F89-L89 -> 9.477117 | N89: =$N$2 -> 0.3 | O89: =M89/F89 -> 0.23076923 | Q89: Эти цены были проставленны Алленой в прошлых просчетах из чека
A90: M-FIN-035 | B90: Крепление типа "бабочка" | C90: шт | D90: =SUMIF('Orcamento RU Viora Build'!$A:$A,A90,'Orcamento RU Viora Build'!$F:$F) -> 526.5065 | E90: =K90+(K90*N90) -> 0.078 | F90: =D90*E90 -> 41.067507 | I90: 0.06 | J90: 0 | K90: =I90-I90*J90 -> 0.06 | L90: =K90*D90 -> 31.59039 | M90: =F90-L90 -> 9.477117 | N90: =$N$2 -> 0.3 | O90: =M90/F90 -> 0.23076923 | Q90: Эти цены были проставленны Алленой в прошлых просчетах из чека
A91: M-FIN-036 | B91: Гвозди Hilti для крепления уголка направляющего 1000шт | C91: уп | D91: =SUMIF('Orcamento RU Viora Build'!$A:$A,A91,'Orcamento RU Viora Build'!$F:$F) -> 2.706328 | E91: =K91+(K91*N91) -> 81.9 | F91: =D91*E91 -> 221.64826 | I91: 63 | J91: 0 | K91: =I91-I91*J91 -> 63 | L91: =K91*D91 -> 170.49866 | M91: =F91-L91 -> 51.149599 | N91: =$N$2 -> 0.3 | O91: =M91/F91 -> 0.23076923 | P91: тут
A92: M-FIN-037 | B92: Саморез для гипсокартона размером 3,5х25мм 1000шт | C92: уп | D92: =SUMIF('Orcamento RU Viora Build'!$A:$A,A92,'Orcamento RU Viora Build'!$F:$F) -> 9.83926 | E92: =K92+(K92*N92) -> 8.84 | F92: =D92*E92 -> 86.979058 | I92: 6.8 | J92: 0 | K92: =I92-I92*J92 -> 6.8 | L92: =K92*D92 -> 66.906968 | M92: =F92-L92 -> 20.07209 | N92: =$N$2 -> 0.3 | O92: =M92/F92 -> 0.23076923 | P92: тут
A93: M-FIN-038 | B93: Саморез для гипсокартона размером 3,5х9,5мм 1000шт | C93: уп | D93: =SUMIF('Orcamento RU Viora Build'!$A:$A,A93,'Orcamento RU Viora Build'!$F:$F) -> 2.807088 | E93: =K93+(K93*N93) -> 11.037 | F93: =D93*E93 -> 30.98183 | I93: 8.49 | J93: 0 | K93: =I93-I93*J93 -> 8.49 | L93: =K93*D93 -> 23.832177 | M93: =F93-L93 -> 7.1496531 | N93: =$N$2 -> 0.3 | O93: =M93/F93 -> 0.23076923 | P93: тут
A94: M-FIN-039 | B94: Сверла по бетону диаметром 6мм | C94: шт | D94: =SUMIF('Orcamento RU Viora Build'!$A:$A,A94,'Orcamento RU Viora Build'!$F:$F) -> 18.27513 | E94: =K94+(K94*N94) -> 2.86 | F94: =D94*E94 -> 52.266872 | I94: 2.2 | J94: 0 | K94: =I94-I94*J94 -> 2.2 | L94: =K94*D94 -> 40.205286 | M94: =F94-L94 -> 12.061586 | N94: =$N$2 -> 0.3 | O94: =M94/F94 -> 0.23076923 | P94: тут
A95: M-FIN-040 | B95: Лента бумажная для швов гипсокартона | C95: м | D95: =SUMIF('Orcamento RU Viora Build'!$A:$A,A95,'Orcamento RU Viora Build'!$F:$F) -> 458.8795 | E95: =K95+(K95*N95) -> 0.0351 | F95: =D95*E95 -> 16.10667 | I95: 0.027 | J95: 0 | K95: =I95-I95*J95 -> 0.027 | L95: =K95*D95 -> 12.389746 | M95: =F95-L95 -> 3.7169239 | N95: =$N$2 -> 0.3 | O95: =M95/F95 -> 0.23076923 | P95: Leroy Merlin
A96: M-FIN-041 | B96: Шпаклевка для швов гипсокартона Semin CE-78 25кг | C96: шт | D96: =SUMIF('Orcamento RU Viora Build'!$A:$A,A96,'Orcamento RU Viora Build'!$F:$F) -> 10.014122 | E96: =K96+(K96*N96) -> 15.262 | F96: =D96*E96 -> 152.83553 | I96: 11.74 | J96: 0 | K96: =I96-I96*J96 -> 11.74 | L96: =K96*D96 -> 117.56579 | M96: =F96-L96 -> 35.269738 | N96: =$N$2 -> 0.3 | O96: =M96/F96 -> 0.23076923 | P96: Mundimat S.A.
A97: M-FIN-052 | B97: Раствор для черновой стяжки | C97: м3 | D97: =SUMIF('Orcamento RU Viora Build'!$A:$A,A97,'Orcamento RU Viora Build'!$F:$F) -> 51.02856 | E97: =K97+(K97*N97) -> 116.493 | F97: =D97*E97 -> 5944.47 | I97: 89.61 | J97: 0 | K97: =I97-I97*J97 -> 89.61 | L97: =K97*D97 -> 4572.6693 | M97: =F97-L97 -> 1371.8008 | N97: =$N$2 -> 0.3 | O97: =M97/F97 -> 0.23076923 | P97: geradordeprecos
A98: M-FIN-055 | B98: Сітка штукатурна | C98: м2 | D98: =SUMIF('Orcamento RU Viora Build'!$A:$A,A98,'Orcamento RU Viora Build'!$F:$F) -> 231.3945 | E98: =K98+(K98*N98) -> 0.845 | F98: =D98*E98 -> 195.52835 | I98: 0.65 | J98: 0 | K98: =I98-I98*J98 -> 0.65 | L98: =K98*D98 -> 150.40643 | M98: =F98-L98 -> 45.121927 | N98: =$N$2 -> 0.3 | O98: =M98/F98 -> 0.23076923 | P98: obras360
A99: M-FIN-060 | B99: Смесь для штукатурки 25кг | C99: шт | D99: =SUMIF('Orcamento RU Viora Build'!$A:$A,A99,'Orcamento RU Viora Build'!$F:$F) -> 1630.248 | E99: =K99+(K99*N99) -> 2.977 | F99: =D99*E99 -> 4853.2483 | I99: 2.29 | J99: 0 | K99: =I99-I99*J99 -> 2.29 | L99: =K99*D99 -> 3733.2679 | M99: =F99-L99 -> 1119.9804 | N99: =$N$2 -> 0.3 | O99: =M99/F99 -> 0.23076923 | P99: тут
A100: M-FIN-061 | B100: Уголки штукатурные | C100: м | D100: =SUMIF('Orcamento RU Viora Build'!$A:$A,A100,'Orcamento RU Viora Build'!$F:$F) -> 96 | E100: =K100+(K100*N100) -> 1.209 | F100: =D100*E100 -> 116.064 | I100: 0.93 | J100: 0 | K100: =I100-I100*J100 -> 0.93 | L100: =K100*D100 -> 89.28 | M100: =F100-L100 -> 26.784 | N100: =$N$2 -> 0.3 | O100: =M100/F100 -> 0.23076923 | P100: тут
...

Sheet Orcamento RU ЧЕРНОВИК 26.06.202
A1: № M | B1: № V | C1: ОПИСАНИЕ РАБОТ | D1: ЕД. ИЗМ. | E1: КОЛ-ВО | F1: ЦЕНА ЗА ЕДИНИЦУ | G1: Наша СТОИМОСТЬ | H1: На сколько дешевле Коментарий | J1: Их стоимость
B4: 1 | C4: СТРОИТЕЛЬНАЯ ПЛОЩАДКА И ДОПОЛНИТЕЛЬНЫЕ РАБОТЫ | D4: =G8 | G4: =SUM(G10:G46) -> 108116 | H4: =G4-('Orcamento RU'!C4+'Orcamento RU'!C2206) -> -70094.4
C6: СТРОИТЕЛЬНАЯ ПЛОЩАДКА | F6: =SUM(G10:G38) -> 73616
A8: 1.1.1 (1) | B8: 1.1 | C8: Монтаж, строительство, обслуживание, демонтаж и снос строительной площадки, включая соответствующие установки, временные сети водоснабжения, канализации, электричества и средства телекоммуникаций, внутренние пути движения и все остальное необходимое в соответствии с Декретом-Законом № 18/08 от 29 января, удовлетворяющее предписаниям по безопасности, гигиене и охране труда, в соответствии с Декретом-Законом № 273/2003 от 29 октября и прочим действующим законодательством, разработка и внедрение плана предотвращения и управления отходами строительства и сноса (в понимании Д.З. № 46/2008 от 12 марта).
A10: 1.1.1 (1) | B10: 1.1.1 | C10: Поставка и установка, обслуживание и демонтаж ограждения вокруг участка с непрозрачными панелями из профилированного оцинкованного стального листа толщиной 0,6 мм, с ребрами высотой от 40 до 50 мм, расположенными на расстоянии от 250 до 270 мм, и профилями в S из согнутого оцинкованного стального листа размером 102x33x1,5 мм, с отделкой сендзимир, длиной 2,8 м, закрепленными в земле с помощью кубов бетона C20/25 XC0 Cl0.40 Dmax 25mm S2 размером 102x33x1,5 см, каждые 2,0 м, включая все работы и материалы, которые к ним относятся. | D10: ml | E10: 260 | F10: 100 | G10: =F10*E10 -> 26000 | H10: Можно строить сразу забор, экономит 268000. Если мы утревдим что забор сразу строим
A12: 1.1.1 (1) | B12: 1.1.2 | C12: Поставка и монтаж, обслуживание и разборка раздвижных ворот для доступа транспортных средств из оцинкованной стали из двух створок с приблизительными размерами 4,0x2,0м с защелкой для замка и фурнитурой для крепления к полу, установленные в временном ограждении территории, закрепленные с помощью столбов из того же материала, анкерованных в грунте с помощью бетонных кубов C20/25 XC0 Cl0.40 Dmáx 25mm S2, включая все работы и материалы, связанные с этим. | D12: vg | E12: 1 | F12: 800 | G12: =F12*E12 -> 800
A14: 1.1.1 (1) | B14: 1.1.3 | C14: Поставка и установка информационного щита, рекламирующего строительство, включая все работы и материалы, относящиеся к этому. | D14: vg | E14: 1 | F14: 120 | G14: =F14*E14 -> 120
A16: 1.1.1 (1) | B16: 1.1.4 | C16: Поставка и выполнение первичных сетей электричества, воды и канализации, включая ежемесячное потребление в течение всего срока выполнения работ до предварительного приемки, включая связанные работы и материалы. | D16: месяцы | E16: 18 | F16: 200 | G16: =F16*E16 -> 3600 | H16: Этот пункт будет урегулироваться по факту
A18: 1.1.1 (1) | B18: 1.1.5 | C18: Поставка и монтаж офисного модуля размером 6,0x3,0 м для строительных совещаний, установленного на выровненной основе из щебня, с туалетом и кондиционером, включая заземление и все сопутствующие работы и материалы. | D18: vg | E18: 1 | F18: 0 | G18: =F18*E18 -> 0 | H18: По желанию клиента для его удобства. Цена 12 000 Евро
A20: 1.1.1 (1) | B20: 1.1.6 | C20: Поставка и монтаж модуля общего инструмента размером 3,0x2,40 м типа морского контейнера, установленного на выровненной основе из щебня, включая все работы и материалы, связанные с этим. | D20: vg | E20: 1 | F20: 5200 | G20: =F20*E20 -> 5200
A22: 1.1.1 (1) | B22: 1.1.7 | C22: Поставка и установка портативного санитарного блока из полиэтилена размером 1,20x1,20x2,35м серого цвета или другого, без подключений, с анаэробным химическим туалетом с системой сброса на ножном приводе, зеркалом, дверью с замком и полупрозрачным потолком для пропуска внешнего света, включая еженедельную уборку и все сопутствующие работы и материалы. | D22: месяцы | E22: 18 | F22: 147 | G22: =F22*E22 -> 2646
A24: 1.1.1 (1) | B24: 1.8 | C24: Поставка и выполнение топографической разбивки через специализированного техника уровней установки строительства, включая бассейн и границы, а также все работы и материалы, связанные с этим. | D24: vg | E24: 1 | F24: 1530 | G24: =F24*E24 -> 1530
A26: 1.1.1 (1) | B26: 1.9 | C26: Поставка и монтаж строительных лесов из стандартных труб, многофункционального типа, высотой до 9 м, состоящих из стальной трубной конструкции из горячекатаной оцинкованной стали диаметром 48,3 мм и толщиной 3,2 мм, без дублирования вертикальных элементов, состоящих из рабочих платформ шириной 60 см, размещенных каждые 2 м по высоте, внутренней лестницы с люком, задних ограждений с двумя перекладинами и нижней планкой, и передних ограждений с одной перекладиной, для выполнения фасада(ов) с конструктивными элементами (крытые и открытые террасы, карнизы и другие и т. д.), размещенными на более чем 50% их периметра и выступающими более чем на 30 см от плоскости фасада. Примечание (1): строительные леса должны полностью соответствовать действующему законодательству, в частности, EN 12811 и EN 12810. | D26: месяцы | E26: 18 | F26: 500 | G26: =F26*E26 -> 9000 | H26: Аренда строительных лесов
A28: 1.1.1 (1) | B28: 1.10 | C28: Поставка, выполнение и внедрение/адаптация плана безопасности и здоровья (ПБЗ) на этапе строительства, включая все работы и материалы, связанные с этим. | D28: месяцы | E28: 18 | F28: 390 | G28: =F28*E28 -> 7020 | H28: Страховка обьекта может отличаться от 300-500 евро. Написали последнюю информацию
A30: 1.1.1 (1) | B30: 1.11 | C30: Поставка, выполнение и внедрение/адаптация плана управления отходами (ПГО), его классификация (ЛЕР), сортировка и разделение на его перерабатываемые компоненты и соответствующая утилизация или транспортировка в зоны переработки и к уполномоченным и лицензированным операторам, в соответствии с действующим законодательством. | D30: месяцы | E30: 18 | F30: 300 | G30: =F30*E30 -> 5400 | H30: Этот пункт будет урегулироваться по факту
A32: 1.1.1 (1) | B32: 1.12 | C32: Подготовка и передача владельцу строительного проекта технической компиляции работ, которая включает полезные элементы, которые следует учитывать при их будущем использовании, а также работы, выполняемые после их завершения для сохранения безопасности и здоровья тех, кто их выполняет, в соответствии с положениями статьи 16 Декрета-Закона № 273/2003 от 29 октября, с учетом итоговых чертежей всех специальностей на бумажном и цифровом носителе, всех исследований, проектов, сопутствующей и связанной документации. | D32: vg | E32: 1 | F32: 0 | G32: =F32*E32 -> 0 | H32: Входить в стоимость самого проекта
A34: 1.1.1 (1) | B34: 1.13 | C34: Обеспечение и координация человеческих и материальных ресурсов, необходимых для уборки и обслуживания строительной площадки, включая установку всего оборудования безопасности, такого как ограждения и линии жизни и т.д., все в соответствии с действующим законодательством. | D34: месяцы | E34: 18 | F34: 150 | G34: =F34*E34 -> 2700
A36: 1.1.1 (1) | B36: 1.14 | C36: Поставка специализированного персонала, а именно директора проекта (гражданский инженер), главного прораба, подготовителя проекта. | D36: месяцы | E36: 18 | F36: 450 | G36: =F36*E36 -> 8100
A38: 1.1.1 (1) | B38: 1.15 | C38: Поставка и установка оборудования и материалов безопасности, расположенных в видимых местах, включая все работы и материалы, связанные с этим. | D38: vg | E38: 1 | F38: 1500 | G38: =F38*E38 -> 1500
C40: КРАН | F40: =SUM(G42:G46) -> 34500
B42: 1.16 | C42: Поставка и выполнение земляных работ на любом типе грунта для основания крана, включая укладку земли в хранилище для насыпей, уплотнение и выравнивание основания рабочей платформы, а также все работы и материалы, связанные с этим. | D42: vg | E42: 1 | F42: 0 | G42: =F42*E42 -> 0 | H42: Включено в стоимость земелных работ
B44: 1.17 | C44: Поставка и выполнение элементов бетонной конструкции типа C25/30 XC2(P) Dmáx 20mm S3, изготовленных, транспортированных и уложенных на объекте в соответствии с NP EN 206-1 и NP ENV 13670-1 для основания установки крана, включая выполнение опалубки и арматур из стали типа A500NR SD и все работы, необходимые для качественной отделки, всё в соответствии с проектом устойчивости, включая все работы и материалы, связанные с этим. Примечание (1): необходимо учитывать демонтаж фундамента крана. | D44: vg | E44: 1 | F44: 8000 | G44: =F44*E44 -> 8000
B46: 1.18 | C46: Поставка и эксплуатация башенного крана с выдвижной стрелой длиной 50 м с характеристиками, соответствующими объекту, включая радиоуправление и управление по кабелю, ковш-санки на 300 литров и поддон для 2000 кг. | D46: vg | E46: 1 | F46: =SUM(G48:G52) -> 26500 | G46: =F46*E46 -> 26500
B48: 1.18.1 | C48: Монтаж крана. | D48: vg | E48: 1 | F48: 1700 | G48: =F48*E48 -> 1700
B49: 1.18.2 | C49: Эксплуатация крана. | D49: месяцы | E49: 14 | F49: 1500 | G49: =F49*E49 -> 21000
B50: 1.18.3 | C50: Демонтаж крана | D50: vg | E50: 1 | F50: 1700 | G50: =F50*E50 -> 1700
B51: 1.18.4 | C51: Доставка крана | D51: Шт | E51: 1 | F51: 1050 | G51: =F51*E51 -> 1050
B52: 1.18.5 | C52: Вывоз крана | D52: Шт | E52: 1 | F52: 1050 | G52: =F52*E52 -> 1050
B55: 2 | C55: ЗЕМЛЯНЫЕ РАБОТЫ | G55: =SUM(G59:G71) -> 34482.88 | H55: =G55-('Orcamento RU'!C749+'Orcamento RU'!C2217) -> -39311.59 | I55: =('Orcamento RU'!C749+'Orcamento RU'!C2217) -> 73794.47
C57: ЗЕМЛЯНЫЕ РАБОТЫ | F57: =SUM(G59:G71) -> 34482.88
A59: 1,1 (2) | B59: 2.1 | C59: Общая очистка участка, включающая все виды работ по очистке, удалению, расчистке и вырубке древесных пород, существующих и необходимых для общего выполнения проектов. | D59: un | E59: 1 | F59: 4000 | G59: =F59*E59 -> 4000
A61: 1,2 (2) | B61: 2.2 | C61: Выполнение общих земляных работ для размещения конструкции жилого дома, бассейна и стен на грунте любого типа (включая скальный), чтобы достичь начальных отметок фундамента, а также выполнение работ по креплению, подпоркам, канализации, включая все сопутствующие работы. | D61: m³ | E61: 2234.27 | F61: 4 | G61: =F61*E61 -> 8937.08
A63: 1,3 (2) | B63: 2.3 | C63: Выполнение насыпей в зоне жилого дома, бассейна и внешних террас с использованием материалов из выемки, включая распределение и надлежащее уплотнение, выполняемое механическими средствами, слоями максимальной толщиной 0,30 м, с использованием воды в количестве, необходимом для правильного уплотнения, для достижения проектных уровней, включая все сопутствующие работы. | D63: m³ | E63: 482.44 | F63: 5 | G63: =F63*E63 -> 2412.2
A65: 1.4.1 (2) | B65: 2.4 | C65: Транспортировка, погрузка и разгрузка излишков грунта из зоны жилого дома на свалку, включая 20% разрыхление, а также все сопутствующие работы. | D65: m³ | E65: 2102.2 | F65: 8 | G65: =F65*E65 -> 16817.6
A67: 1.2.1.1 (3) | B67: 2.5 | C67: Выемка грунта любого характера до проектных отметок, включая транспортировку в зоны насыпи, остальные должны транспортироваться на авторизованный склад, включая транспортировку, компенсации, а также все средства, работы, материалы, необходимые. | D67: m3 | E67: 68 | F67: 3 | G67: =F67*E67 -> 204
A69: 1.2.2.1 (3) | B69: 2.6 | C69: Насыпь слоями до проектных отметок отборным грунтом из выемок или из зон заимствования вне зоны вмешательства, включая транспортировку, все средства, работы, материалы, необходимые. | D69: m3 | E69: 386 | F69: 3 | G69: =F69*E69 -> 1158
A71: 1.2.3.1 (3) | B71: 2.7 | C71: Поставка, погрузка, транспортировка, разгрузка, распределение заимствованного грунта, а также все средства, работы, материалы, необходимые. | D71: m3 | E71: 318 | F71: 3 | G71: =F71*E71 -> 954
B73: 3 | C73: ЖЕЛЕЗОБЕТОННАЯ КОНСТРУКЦИЯ | G73: =SUM(G79:G269) -> 567388.82 | H73: =G73-'Orcamento RU'!C761 -> 8996.574 | I73: ='Orcamento RU'!C761 -> 558392.25
C75: Бетон | F75: =SUM(G79:G111) -> 78362.8
A77: 2.1.1 (2) | B77: 3.1 | C77: Поставка и укладка подбетонки из бетона C12/15, с классом воздействия X0, Cl 1.0, Dmax 25мм, S3, толщиной 5 см под элементы фундамента, включая предварительное выравнивание и уплотнение дна котлованов, уложенной в геометрической форме следующих элементов:
A79: 2.1.1.1 (2) | B79: 3.1.1 | C79: В фундаментах, фундаментах стен, ограничительных стенах, фундаментных балках и фундаментных плитах | D79: m2 | E79: 329.7 | F79: 12 | G79: =F79*E79 -> 3956.4
A81: 2.1.2 (2) | B81: 3.2 | C81: Поставка и укладка бетона C30/37, с классом воздействия XC2, Cl 0.4, Dmax 20мм, S3, включая вибрирование и все сопутствующие работы, необходимые для идеального завершения в следующих элементах:
A83: 2.1.2.1 (2) | B83: 3.2.1 | C83: В фундаментных балках | D83: m³ | E83: 29.25 | F83: 140 | G83: =F83*E83 -> 4095
A84: 2.1.2.2 (2) | B84: 3.2.2 | C84: В фундаментах | D84: m³ | E84: 8.94 | F84: 140 | G84: =F84*E84 -> 1251.6
A85: 2.1.2.3(2) | B85: 3.2.3 | C85: В фундаментах стен и перегородок | D85: m³ | E85: 106.22 | F85: 140 | G85: =F85*E85 -> 14870.8
A86: 2.1.2.4 (2) | B86: 3.2.4 | C86: В фундаментной плите | D86: m³ | E86: 3.02 | F86: 140 | G86: =F86*E86 -> 422.8
A88: 2.1.3(2) | B88: 3.3 | C88: Поставка и укладка бетона C30/37, с классом воздействия XC2, Cl 0.4, Dmax 20мм, S4, включая вибрирование и все сопутствующие работы, необходимые для идеального завершения в следующих элементах:
A90: 2.1.3.1 (2) | B90: 3.3.1 | C90: Столбы стен подвала | D90: m³ | E90: 2.51 | F90: 140 | G90: =F90*E90 -> 351.4
A91: 2.1.3.2 (2) | B91: 3.3.2 | C91: Стены подвала/опорные/перегородки | D91: m³ | E91: 88.26 | F91: 140 | G91: =F91*E91 -> 12356.4
A92: 2.1.3.2(2) | B92: 3.3.3 | C92: Наружная лестница | D92: m³ | E92: 1.32 | F92: 140 | G92: =F92*E92 -> 184.8
A94: 2.1.4 (2) | B94: 3.4 | C94: Поставка и укладка бетона C40/50, с классом воздействия XS1, Cl 0.2, Dmax 20мм, S4, включая вибрирование и все сопутствующие работы, необходимые для идеального завершения в следующих элементах:
A96: 2.1.4.1 (2) | B96: 3.4.1 | C96: В столбах | D96: m³ | E96: 7.28 | F96: 160 | G96: =F96*E96 -> 1164.8
A97: 2.1.4.2 (2) | B97: 3.4.2 | C97: В стенах | D97: m³ | E97: 27.46 | F97: 160 | G97: =F97*E97 -> 4393.6
A99: 2.1.4 (2) | B99: 3.5 | C99: Поставка и укладка бетона C40/50, с классом воздействия XS1, Cl 0.2, Dmax 16мм, S4, включая вибрирование и все сопутствующие работы, необходимые для идеального завершения в следующих элементах:
A101: 2.1.4.3 (2) | B101: 3.5.1 | C101: В балках | D101: m³ | E101: 52.37 | F101: 160 | G101: =F101*E101 -> 8379.2
A102: 2.1.4.4 (2) | B102: 3.5.2 | C102: В монолитных плитах | D102: m³ | E102: 60.12 | F102: 160 | G102: =F102*E102 -> 9619.2
A103: 2.1.4.5 (2) | B103: 3.5.3 | C103: В облегченных монолитных плитах (Cobiax) | D103: m³ | E103: 50.41 | F103: 160 | G103: =F103*E103 -> 8065.6
A104: 2.1.4.6 (2) | B104: 3.5.4 | C104: В лестницах Лестница E1 | D104: m³ | E104: 1.91 | F104: 160 | G104: =F104*E104 -> 305.6
A106: 2.1.5 (2) | B106: 3.6 | C106: Поставка и укладка бетона C40/50, с классом воздействия XD2, Cl 0.2, Dmax 20мм, S4, в элементах бассейна, компенсационного бака и водного зеркала, включая вибрирование и все сопутствующие работы, необходимые для идеального завершения в следующих элементах:
A108: 2.1.5.1 (2) | B108: 3.6.1 | C108: В стенах | D108: m³ | E108: 30.26 | F108: 160 | G108: =F108*E108 -> 4841.6
A109: 2.1.5.2 (2) | B109: 3.6.2 | C109: В плитах | D109: m³ | E109: 21.41 | F109: 160 | G109: =F109*E109 -> 3425.6
A110: 2.1.5.3 (2) | B110: 3.6.3 | C110: В балках/усилениях | D110: m³ | E110: 3.06 | F110: 160 | G110: =F110*E110 -> 489.6
A111: 2.1.5.4 (2) | B111: 3.6.4 | C111: В лестницах (Лестница E3) | D111: m³ | E111: 1.18 | F111: 160 | G111: =F111*E111 -> 188.8
C113: Сталь/Арматура | F113: =SUM(G118:G164) -> 125531.59
A115: 2.2.1 (2) | B115: 3.7 | C115: Поставка, изготовление и установка стали A500NR SD в арматуре конструктивных элементов, включая отходы, стыки, отожженную проволоку, средства и оборудование и все сопутствующие работы, необходимые для идеального завершения в следующих элементах:
A117: 2.2.1.1 | B117: 3.7.1 | C117: Фундаменты
B118: 3.7.1.1 | C118: Ø10 | D118: kg | E118: 421.74 | F118: 1.9 | G118: =F118*E118 -> 801.306
A120: 2.2.1.2 | B120: 3.7.2 | C120: Фундаменты стен/перегородок
B121: 3.7.2.1 | C121: Ø8 | D121: kg | E121: 1572.83 | F121: 1.9 | G121: =F121*E121 -> 2988.377
B122: 3.7.2.2 | C122: Ø10 | D122: kg | E122: 3799.07 | F122: 1.9 | G122: =F122*E122 -> 7218.233
A124: 2.2.1.3 | B124: 3.7.3 | C124: Фундаментная плита
B125: 3.7.3.1 | C125: Ø10 | D125: kg | E125: 289.81 | F125: 1.9 | G125: =F125*E125 -> 550.639
B126: 3.7.3.2 | C126: Ø12 | D126: kg | E126: 412.85 | F126: 1.9 | G126: =F126*E126 -> 784.415
A128: 2.2.1.4 | B128: 3.7.4 | C128: Фундаментные балки
B129: 3.7.4.1 | C129: Ø8 | D129: kg | E129: 651.95 | F129: 1.9 | G129: =F129*E129 -> 1238.705
B130: 3.7.4.2 | C130: Ø10 | D130: kg | E130: 132.8 | F130: 1.9 | G130: =F130*E130 -> 252.32
B131: 3.7.4.3 | C131: Ø12 | D131: kg | E131: 477.82 | F131: 1.9 | G131: =F131*E131 -> 907.858
B132: 3.7.4.4 | C132: Ø16 | D132: kg | E132: 1878.6 | F132: 1.9 | G132: =F132*E132 -> 3569.34
A134: 2.2.1.5 | B134: 3.7.5 | C134: Стены подвала/опорные и перегородки
B135: 3.7.5.1 | C135: Ø8 | D135: kg | E135: 861.38 | F135: 1.9 | G135: =F135*E135 -> 1636.622
B136: 3.7.5.2 | C136: Ø10 | D136: kg | E136: 4610.89 | F136: 1.9 | G136: =F136*E136 -> 8760.691
B137: 3.7.5.3 | C137: Ø12 | D137: kg | E137: 12447.9 | F137: 1.9 | G137: =F137*E137 -> 23651.01
A139: 2.2.1.6 | B139: 3.7.6 | C139: Столбы
B140: 3.7.6.1 | C140: Ø8 | D140: kg | E140: 873.77 | F140: 1.9 | G140: =F140*E140 -> 1660.163
B141: 3.7.6.2 | C141: Ø12 | D141: kg | E141: 1173.14 | F141: 1.9 | G141: =F141*E141 -> 2228.966
B142: 3.7.6.3 | C142: Ø16 | D142: kg | E142: 851.86 | F142: 1.9 | G142: =F142*E142 -> 1618.534
A144: 2.2.1.7 | B144: 3.7.7 | C144: Балки и усиления
B145: 3.7.7.1 | C145: Ø8 | D145: kg | E145: 2505.02 | F145: 1.9 | G145: =F145*E145 -> 4759.538
B146: 3.7.7.2 | C146: Ø10 | D146: kg | E146: 113.14 | F146: 1.9 | G146: =F146*E146 -> 214.966
B147: 3.7.7.3 | C147: Ø12 | D147: kg | E147: 145.88 | F147: 1.9 | G147: =F147*E147 -> 277.172
B148: 3.7.7.4 | C148: Ø16 | D148: kg | E148: 6059.68 | F148: 1.9 | G148: =F148*E148 -> 11513.392
A150: 2.2.1.8 | B150: 3.7.8 | C150: Плиты
B151: 3.7.8.1 | C151: Ø10 | D151: kg | E151: 3007.17 | F151: 1.9 | G151: =F151*E151 -> 5713.623
B152: 3.7.8.2 | C152: Ø12 | D152: kg | E152: 14406.06 | F152: 1.9 | G152: =F152*E152 -> 27371.514
A154: 2.2.1.9 | B154: 3.7.9 | C154: Лестницы
B155: 3.7.9.1 | C155: Ø10 | D155: kg | E155: 601.06 | F155: 1.9 | G155: =F155*E155 -> 1142.014
A157: 2.2.1.10 | B157: 3.7.10 | C157: Бассейн (плиты, стены и компенсационный бак)
B158: 3.7.10.1 | C158: Ø8 | D158: kg | E158: 977.88 | F158: 1.9 | G158: =F158*E158 -> 1857.972
B159: 3.7.10.2 | C159: Ø10 | D159: kg | E159: 2445.29 | F159: 1.9 | G159: =F159*E159 -> 4646.051
B160: 3.7.10.3 | C160: Ø12 | D160: kg | E160: 4767.93 | F160: 1.9 | G160: =F160*E160 -> 9059.067
...

Sheet Sheet1
D4: 750000 | E4: Первая фаза | F4: =D4+D4*23% -> 922500
D5: 1400000 | E5: Вторая фаза | F5: =D5+D5*23% -> 1722000
D6: -210000 | E6: 0.15
D7: =D5+D6 -> 1190000 | F7: =D7+D7*23% -> 1463700

Sheet Дорожняя карта
C2: От | D2: До
B3: СТРОИТЕЛЬНАЯ ПЛОЩАДКА И ДОПОЛНИТЕЛЬНЫЕ РАБОТЫ | C3: 82000 | D3: 110000
B4: ЗЕМЛЯНЫЕ РАБОТЫ | C4: 34000 | D4: 37000
B5: ЖЕЛЕЗОБЕТОННАЯ КОНСТРУКЦИЯ | C5: 550000 | D5: 650000
B6: ГИДРОИЗОЛЯЦИЯ И ТЕПЛОИЗОЛЯЦИЯ | C6: 23000 | D6: 25000
B7: КАМЕННАЯ КЛАДКА И ОГРАЖДАЮЩИЕ КОНСТРУКЦИИ | C7: 28000 | D7: 33000
B8: КРОВЛЯ | C8: 30000 | D8: 61000
B9: ОТДЕЛКА ПОТОЛКОВ | C9: 15000 | D9: 17000
B10: ОТДЕЛКА СТЕН | C10: 70000 | D10: 110000
B11: ОТДЕЛКА ПОЛОВ И ПЛИНТУСОВ | C11: 80000 | D11: 126000
B12: МЕТАЛЛОКОНСТРУКЦИИ И ОКОННЫЕ РАМЫ | C12: 150000 | D12: 300000
B13: СТОЛЯРНЫЕ РАБОТЫ | C13: 60000 | D13: 100000
B14: САНТЕХНИЧЕСКОЕ ОБОРУДОВАНИЕ | C14: 35000 | D14: 60000
... B27: ПРОЧЕЕ | C27: 25000 | D27: 35000
B28: Без Ива | C28: =SUM(C3:C27) -> 1597000 | D28: =SUM(D3:D27) -> 2403000
B29: С Ива | C29: =C28+C28*0.23 -> 1964310 | D29: =D28+D28*0.23 -> 2955690

Sheet Альтернативы
A1: Альтернативы Архитектура | O1: № в смете | P1: Текущее покрытие / отделка | Q1: Площадь / пог.м | R1: Цена сейчас | S1: Предлагаемая альтернатива | T1: Новая цена | U1: Экономия*
A2: #K | B2: # | C2: Описание | D2: Ед.изм | E2: Кол-во | F2: Цена | G2: Итого | I2: Цена за штуку Альтернативы | J2: Экономия | O2: 9.13 | P2: Паркет: дубовые рейки 20×220×2200 мм (ALVA Ribadão, отделка Bona) | Q2: 239,8 м² | R2: 145 €/м² | S2: Премиальный 12-мм ламинат AC5/33 класса с фаской (eg. Quick-Step Majestic) | T2: ≈ 50 €/м² | U2: ≈ 22 800 €
A3: 2.6.1.4 | B3: 8.4 | C3: Поставка и монтаж фасадной системы с отделкой алюминиевым листом 5мм, окрашенным в белый цвет RAL 9003, с клеевой системой марки "CORTIZO" и подконструкцией Т-профиля и теплоизоляцией XPS 7см, включая резку, отделку и все подготовительные и вспомогательные работы, необходимые для идеальной отделки. (PR11) | D3: m2 | E3: 106.79 | F3: 230 | G3: =E3*F3 -> 24561.7 | H3: Мы предлагаем систему алюминеввой отделки сделать так же саммо как пункт 8.3 используя RAL 9003. Цена уменьшается с 234 Евро за м2 до 75 Евро | I3: 75 | J3: =I3*E3-G3 -> -16552.45 | O3: 8.4 | P3: Алюминиевый лист 5 мм RAL 9003 (вентилируемый фасад) | Q3: 106,8 м² | R3: 230 €/м² | S3: ETICS + минеральная штукатурка RAL 9003 (как в п. 8.3) | T3: 75 €/м² | U3: ≈ 16 550 €
A4: 2.5.2.2 | B4: 7.3 | C4: Поставка и монтаж сплошных подвесных потолков с гипсокартонными плитами толщиной 12мм "KNAUF KS STANDARD", включая кромку 10ммx10мм с профилем системы, несущую конструкцию, систему крепления, выполнение отверстий для размещения различного оборудования, ниши, обработку швов, шпатлевку и финишную подготовку под покраску и все подготовительные работы и аксессуары, необходимые для идеального завершения. (TE02) | D4: m2 | E4: 170.41 | F4: 32.2 | G4: =E4*F4 -> 5487.202 | H4: Будет зеленный влагостойикй гипсокартон | I4: 33 | J4: =I4*E4-G4 -> 136.328 | O4: 9.6 | P4: Сосновая террасная доска 20 × 220 мм | Q4: 50 м² | R4: 145 €/м² | S4: WPC-доска (co-extruded, скрытый крепёж) | T4: ≈ 115 €/м² | U4: ≈ 1 500 €
A5: 2.7.2.2 | B5: 9.13 | C5: Поставка и укладка покрытия из паркета - дубовые рейки 20x220x2200 (вxшxд) - модель ALVA RIBADÃO, обработка "NORDIC NATURAL" марки BONA, включая стяжку заполнения/выравнивания с затертой поверхностью, резку, отделку, крепления и все подготовительные работы и аксессуары, необходимые для идеального завершения. (PV03) | D5: m2 | E5: 239.8 | F5: 145 | G5: =E5*F5 -> 34771 | H5: Предлагаем ламинат ТОП класса стоимостью 50 ЕВРО. | I5: 90 | J5: =I5*E5-G5 -> -13189 | O5: Тёплый пол 16.10–16.11 | P5: Водяной по всем помещениям | Q5: ~ 300 м² | R5: ≈ 68 000 € | S5: Оставить только санузлы + спальни или уложить электрические маты под плитку | T5: ≈ 25 000 € | U5: ≈ 43 000 €
A6: 2.7.1.6 | B6: 9.6 | C6: Поставка и укладка настила, состоящего из сосновых досок 20x220x2200мм, автоклавная обработка, матовое лаковое покрытие натурального цвета, симметричное крепление винтами, включая основание из стяжки заполнения/выравнивания с затертой поверхностью, выравнивание, резку, отделку и все подготовительные работы и аксессуары, необходимые для идеального завершения. (PV11) | D6: m2 | E6: 50 | F6: 145 | G6: =E6*F6 -> 7250 | H6: Предлашаем вместо панелей использовать сосновые доски DECK. Цена за м2 уменьшается со 151 до 115 евро м2 | I6: 115 | J6: =I6*E6-G6 -> -1500 | O6: 8.9/8.10 | P6: Мозаика 30 × 30 см RUBICER | Q6: 127,5 м² | R6: 87 €/м² | S6: Керамогранит 60 × 60 см III сорт (складские позиции) | T6: 45 €/м² | U6: ≈ 5 350 €
A7: 2.4.1 | B7: 6.1 | C7: Поставка и монтаж покрытия кровли #1 цинковыми листами, лакированными в белый цвет RAL 9003, с фальцевым соединением типа "Double Lock", уложенными на вентиляционный слой типа "AGUADRAIN GEO" и гидроизоляционную мембрану типа "RHENOFOL CV", теплоизоляция XPS толщиной 8см изнутри и слой минеральной ваты толщиной 17см между OSB, согласно детальному чертежу, включая выполнение желоба и перекрытий из цинка, резку, отделку, элементы крепления и все подготовительные работы и аксессуары, необходимые для идеального завершения. (PV15) | D7: m2 | E7: 181.91 | F7: 290.82 | G7: =E7*F7 -> 52903.066 | H7: Будем делать перерасчет с учетом того какой камень будет использоваться и Щебень | I7: 150 | J7: =I7*E7-G7 -> -25616.566 | O7: 9.16 | P7: Плинтус из уголка шлиф. нерж. стали 20×10 мм | Q7: 130 п.м | R7: 28 €/п.м | S7: МДФ/ламин. плинтус в цвет пола (клип-система) | T7: ≈ 5 €/п.м | U7: ≈ 3 000 €
A8: 2.4.3 | B8: 6.3 | C8: Поставка и выполнение перекрытий парапетов кровли #2 и #3 (недоступной) оцинкованным металлическим листом, включая резку, отделку, элементы крепления, создание уклонов, согласно проектным элементам, и все подготовительные работы и аксессуары, необходимые для идеального завершения. | D8: m2 | E8: 15.09 | F8: 323.28 | G8: =E8*F8 -> 4878.2952 | H8: Предлагаем сделать из камня moleanos amaciado толщина 2 см | I8: 200 | J8: =I8*E8-G8 -> -1860.2952 | O8: 9.14/9.15 | P8: Эпоксидное покрытие SIKAFLOOR 264 | Q8: 46 м² | R8: 50 €/м² | S8: Микроцемент или PU-наливной пол | T8: ≈ 35 €/м² | U8: ≈ 690 €
A9: 2.7.2.3 | B9: 9.14 | C9: Поставка и выполнение эпоксидной покраски бежевый глянцевый RAL по образцу, SIKAFLOOR-264, марки SIKA, включая все необходимые компоненты и противоскользящую отделку, стяжку заполнения/выравнивания с затертой поверхностью, отделку и все подготовительные работы и аксессуары, необходимые для идеального завершения. (PV04) | D9: m2 | E9: 16.81 | F9: 50 | G9: =E9*F9 -> 840.5 | H9: В таком случае не нужен | I9: 0 | J9: =I9*E9-G9 -> -840.5
A10: 2.7.2.4 | B10: 9.15 | C10: Поставка и выполнение эпоксидной покраски белый матовый RAL 9003 SIKAFLOOR-264, марки SIKA, включая все необходимые компоненты и противоскользящую отделку, стяжку заполнения/выравнивания с затертой поверхностью, понижение в зоне душей с созданием уклонов, отделку и все подготовительные работы и аксессуары, необходимые для идеального завершения. (PV04) | D10: m2 | E10: 29.1 | F10: 50 | G10: =E10*F10 -> 1455 | H10: В таком случае не нужен | I10: 0 | J10: =I10*E10-G10 -> -1455
A11: 2.7.3.1 | B11: 9.16 | C11: Поставка и укладка плинтуса из уголка шлифованной нержавеющей стали 20x10x5мм (вxшxт), включая систему крепления, резку, отделку и все подготовительные работы и аксессуары, необходимые для идеального завершения. (RD01) | D11: ml | E11: 130.01 | F11: 28 | G11: =E11*F11 -> 3640.28 | H11: Плинтус под ламинат | I11: 18 | J11: =I11*E11-G11 -> -1300.1
C12: Шкафы: Стоит пересмотреть чистовые материалы и констуркцию мебели, провести встречу с производителями
C14: Есть еще шкафы на кухне в ванной и в доп.работах.

Sheet Альтернативы ENG
A1: Альтернативы Архитектура | O1: № в смете | P1: Текущее покрытие / отделка | Q1: Площадь / пог.м | R1: Цена сейчас | S1: Предлагаемая альтернатива | T1: Новая цена | U1: Экономия*
A2: #K | B2: # | C2: Description | D2: Unit | E2: Quantity | F2: Price Before | G2: Total | H2: Notice | I2: Price After (Alternative) | J2: Savings | O2: 9.13 | P2: Паркет: дубовые рейки 20×220×2200 мм (ALVA Ribadão, отделка Bona) | Q2: 239,8 м² | R2: 145 €/м² | S2: Премиальный 12-мм ламинат AC5/33 класса с фаской (eg. Quick-Step Majestic) | T2: ≈ 50 €/м² | U2: ≈ 22 800 €
A3: 2.6.1.4 | B3: 8.4 | C3: Supply and installation of a façade system finished with 5mm thick aluminum sheets, painted white RAL 9003, using the "CORTIZO" adhesive system, with a substructure of T-profile and 7cm XPS thermal insulation, including cutting, finishing, and all preparatory and auxiliary works necessary for a perfect finish. (PR11) | D3: m2 | E3: 106.79 | F3: 230 | G3: =E3*F3 -> 24561.7 | H3: We propose to apply the aluminum cladding system the same way as in item 8.3, using RAL 9003. The price is reduced from €234/m² to €75/m². | I3: 75 | J3: =I3*E3-G3 -> -16552.45 | O3: 8.4 | P3: Алюминиевый лист 5 мм RAL 9003 (вентилируемый фасад) | Q3: 106,8 м² | R3: 230 €/м² | S3: ETICS + минеральная штукатурка RAL 9003 (как в п. 8.3) | T3: 75 €/м² | U3: ≈ 16 550 €
A4: 2.5.2.2 | B4: 7.3 | C4: Supply and installation of continuous suspended ceilings with 12mm thick gypsum plasterboards "KNAUF KS STANDARD", including 10x10mm edge with profile system, supporting structure, fastening system, creation of openings for various equipment, recesses, joint treatment, puttying, and final preparation for painting, as well as all preparatory works and accessories necessary for a perfect finish. (TE02) | D4: m2 | E4: 170.41 | F4: 32.2 | G4: =E4*F4 -> 5487.202 | H4: Moisture-resistant green plasterboard will be used. | I4: 33 | J4: =I4*E4-G4 -> 136.328 | O4: 9.6 | P4: Сосновая террасная доска 20 × 220 мм | Q4: 50 м² | R4: 145 €/м² | S4: WPC-доска (co-extruded, скрытый крепёж) | T4: ≈ 115 €/м² | U4: ≈ 1 500 €
A5: 2.7.2.2 | B5: 9.13 | C5: Supply and installation of oak parquet flooring – planks 20x220x2200mm (thxwxl) – model ALVA RIBADÃO, finish "NORDIC NATURAL" by BONA, including filling/leveling screed with troweled surface, cutting, finishing, fastenings, and all preparatory works and accessories necessary for a perfect finish. (PV03) | D5: m2 | E5: 239.8 | F5: 145 | G5: =E5*F5 -> 34771 | H5: We propose using top-class laminate flooring at a cost of €50. | I5: 90 | J5: =I5*E5-G5 -> -13189 | O5: Тёплый пол 16.10–16.11 | P5: Водяной по всем помещениям | Q5: ~ 300 м² | R5: ≈ 68 000 € | S5: Оставить только санузлы + спальни или уложить электрические маты под плитку | T5: ≈ 25 000 € | U5: ≈ 43 000 €
A6: 2.7.1.6 | B6: 9.6 | C6: Supply and installation of flooring made of pine boards 20x220x2200mm, autoclave-treated, with a matte natural color lacquer finish, symmetrical screw fixing, including sub-base of filling/leveling screed with troweled surface, leveling, cutting, finishing, and all preparatory works and accessories necessary for a perfect finish. (PV11) | D6: m2 | E6: 50 | F6: 145 | G6: =E6*F6 -> 7250 | H6: We suggest using pine DECK boards instead of panels. The price per m² is reduced from €151 to €115/m². | I6: 115 | J6: =I6*E6-G6 -> -1500 | O6: 8.9/8.10 | P6: Мозаика 30 × 30 см RUBICER | Q6: 127,5 м² | R6: 87 €/м² | S6: Керамогранит 60 × 60 см III сорт (складские позиции) | T6: 45 €/м² | U6: ≈ 5 350 €
A7: 2.4.1 | B7: 6.1 | C7: Supply and installation of Roof #1 covering with zinc sheets, lacquered white RAL 9003, with “Double Lock” seam, laid over a ventilated layer "AGUADRAIN GEO" and waterproof membrane "RHENOFOL CV", internal 8cm XPS thermal insulation and 17cm mineral wool layer between OSB, according to detailed drawings, including fabrication of gutters and zinc flashings, cutting, finishing, fixings, and all preparatory works and accessories necessary for a perfect finish. (PV15) | D7: m2 | E7: 181.91 | F7: 290.82 | G7: =E7*F7 -> 52903.066 | H7: We will recalculate the cost depending on the type of stone and gravel to be used. | I7: 150 | J7: =I7*E7-G7 -> -25616.566 | O7: 9.16 | P7: Плинтус из уголка шлиф. нерж. стали 20×10 мм | Q7: 130 п.м | R7: 28 €/п.м | S7: МДФ/ламин. плинтус в цвет пола (клип-система) | T7: ≈ 5 €/п.м | U7: ≈ 3 000 €
A8: 2.4.3 | B8: 6.3 | C8: Supply and execution of parapet coverings on roofs #2 and #3 (non-accessible) with galvanized metal sheet, including cutting, finishing, fixings, slope formation as per design elements, and all preparatory works and accessories necessary for a perfect finish. | D8: m2 | E8: 15.09 | F8: 323.28 | G8: =E8*F8 -> 4878.2952 | H8: We propose using Moleanos Amaciado stone with a thickness of 2 cm. | I8: 200 | J8: =I8*E8-G8 -> -1860.2952 | O8: 9.14/9.15 | P8: Эпоксидное покрытие SIKAFLOOR 264 | Q8: 46 м² | R8: 50 €/м² | S8: Микроцемент или PU-наливной пол | T8: ≈ 35 €/м² | U8: ≈ 690 €
A9: 2.7.2.3 | B9: 9.14 | C9: Supply and application of glossy beige epoxy paint (RAL as per sample), SIKAFLOOR-264 by SIKA, including all required components and anti-slip finish, filling/leveling screed with troweled surface, finishing, and all preparatory works and accessories necessary for a perfect finish. (PV04) | D9: m2 | E9: 16.81 | F9: 50 | G9: =E9*F9 -> 840.5 | H9: In this case, it is not needed. | I9: 0 | J9: =I9*E9-G9 -> -840.5
A10: 2.7.2.4 | B10: 9.15 | C10: Supply and application of matte white epoxy paint RAL 9003, SIKAFLOOR-264 by SIKA, including all required components and anti-slip finish, filling/leveling screed with troweled surface, slope formation in shower areas, finishing, and all preparatory works and accessories necessary for a perfect finish. (PV04) | D10: m2 | E10: 29.1 | F10: 50 | G10: =E10*F10 -> 1455 | H10: In this case, it is not needed. | I10: 0 | J10: =I10*E10-G10 -> -1455
A11: 2.7.3.1 | B11: 9.16 | C11: Supply and installation of skirting made of polished stainless steel angle 20x10x5mm (hxwxt), including fixing system, cutting, finishing, and all preparatory works and accessories necessary for a perfect finish. (RD01) | D11: ml | E11: 130.01 | F11: 28 | G11: =E11*F11 -> 3640.28 | H11: Skirting board matching the laminate. | I11: 18 | J11: =I11*E11-G11 -> -1300.1
C12: Cabinets: It is necessary to reconsider the finishing materials and the furniture construction, and to hold a meeting with the manufacturers

Sheet Sheet8
A1: СТРОИТЕЛЬНАЯ ПЛОЩАДКА И ДОПОЛНИТЕЛЬНЫЕ РАБОТЫ | B1: 82116 | C1: СТРОИТЕЛЬНАЯ ПЛОЩАДКА И ПОДГОТОВИТЕЛЬНЫЕ РАБОТЫ | D1: 178210.4
A2: ЗЕМЛЯНЫЕ РАБОТЫ | B2: 34482.88 | C2: ЗЕМЛЯНЫЕ РАБОТЫ | D2: 103424
A3: ЖЕЛЕЗОБЕТОННАЯ КОНСТРУКЦИЯ | B3: 567388.82 | C3: ЖЕЛЕЗОБЕТОННЫЕ И МЕТАЛИЧЕСКИЕ КОНСТРУКЦИИ | D3: 590738.6
A4: ГИДРОИЗОЛЯЦИЯ И ТЕПЛОИЗОЛЯЦИЯ | B4: 33338.56 | C4: СТІНИ І ПЕРЕГОРОДКИ З ЦЕГЛИ І ГІПСОКАРТОНУ | D4: 43006.935
A5: КАМЕННАЯ КЛАДКА И ОГРАЖДАЮЩИЕ КОНСТРУКЦИИ | B5: 33321.22 | C5: ПІДЛОГА | D5: 153285.45
A6: КРОВЛЯ | B6: 55010.63 | C6: ГІДРОІЗОЛЯЦЯ І ТЕПЛОІЗОЛЯЦІЯ | D6: 51977.283
A7: ОТДЕЛКА ПОТОЛКОВ | B7: 16547.615 | C7: ПОКРІВЛЯ | D7: 52781.87
A8: ОТДЕЛКА СТЕН | B8: 82409.94 | C8: ОЗДОБЛЕННЯ ПРИМІЩЕНЬ | D8: 137489.87
A9: ОТДЕЛКА ПОЛОВ И ПЛИНТУСОВ | B9: 95116.02 | C9: ОПОРЯДЖЕННЯ БАСЕЙНУ | D9: 51308.979
A10: МЕТАЛЛОКОНСТРУКЦИИ И ОКОННЫЕ РАМЫ | B10: 243804.03 | C10: ВІКНА, ДВЕРІ, МЕБЛІ | D10: 383599.88
A11: СТОЛЯРНЫЕ РАБОТЫ | B11: 72157.2 | C11: САНТЕХНИКА | D11: 175306.66
A12: САНТЕХНИЧЕСКОЕ ОБОРУДОВАНИЕ | B12: 51642.25 | C12: СИСТЕМА ВЕТНИЛЯЦІЇ І КОНДИЦІОНУВАННЯ | D12: 181241
... A16: ПОСТАВКА И МОНТАЖ ОБОРУДОВАНИЯ И СИСТЕМ КОНДИЦИОНИРОВАНИЯ И ПРОИЗВОДСТВА ГОРЯЧЕЙ САНИТАРНОЙ ВОДЫ | B16: 168999.44 | C16: БЛАГОУСТРІЙ | D16: 267431.05
A17: ЭЛЕКТРИЧЕСКАЯ СЕТЬ | B17: 211533.09
A18: ТЕЛЕКОММУНИКАЦИОННЫЕ УСТАНОВКИ ITED | B18: 9077
A19: ПОЛЫ, ПОКРЫТИЯ И СТРОИТЕЛЬНЫЕ ЭЛЕМЕНТЫ | B19: 38085
A20: ОСВЕЩЕНИЕ - СВЕТОВЫЕ ТОЧКИ | B20: 0
A21: ОБОРУДОВАНИЕ | B21: 10648
A22: ПОСАДКИ И ПОСЕВЫ (ИСКЛЮЧЕН) | B22: 0
A23: ПОЛИВ (ИСКЛЮЧЕН) | B23: 0
A24: ОБСЛУЖИВАНИЕ ЗЕЛЕНЫХ ЗОН (ИСКЛЮЧЕН) | B24: 0
A25: БЛАГОУСТРОЙСТВО УЧАСТКА | B25: 40186.18
A26: ПРОЧЕЕ | B26: 25469
A27: ВНУТРЕННЯЯ СЕТЬ БЫТОВЫХ И ДОЖДЕВЫХ СТОЧНЫХ ВОД | B27: 70131.07

Sheet Sheet5
A1: 2.9 | B1: SERRALHARIAS E CAIXILHARIAS | C1: LOCKWORKS AND FIXTURES, Metal works and frames
A3: 2.9.1 | B3: CAIXILHARIA DE ALUMÍNIO | C3: ALUMINUM FRAME
A5: 2.9.1.1 | B5: Fornecimento e montagem de vãos exteriores em caixilharia de alumínio CORTIZO, incluindo acabamento, vidros duplos, vedações, soleiras metálicas, sistema de abertura e ferragens conforme descrito no mapa de vãos e elementos do projecto e todos os trabalhos preparatórios e acessórios necessários a um perfeito funcionamento. | C5: Supply and assembly of exterior openings in CORTIZO aluminum frames, including finishing, double glazing, seals, metal thresholds, opening system and hardware as described in the map of openings and project elements and all preparatory work and accessories necessary for perfect operation.
A7: 2.9.1.1.1 | B7: VE 01.1 - Dimensão de 1.10x2.88m, Vão de Sacada 1 Folha oscilo-batente + 1 bandeira, série "COR 70", Folha Oculta C16 ST, Lacada segundo alçados (RAL9003, por confirmar), incluindo soleira em chapa de alumínio anodizado (acabamento natural) quinada 3mm esp. | C7: VE 01.1 - Dimensions 1.10x2.88m, Balcony Opening 1 tilt-and-turn leaf + 1 flag, series "COR 70", Concealed Leaf C16 ST, Lacquered according to elevations (RAL9003, to be confirmed), including threshold in anodized aluminum sheet (natural finish) bent 3mm thick. | E7: un | F7: 1
A9: 2.9.1.1.2 | B9: VE 01.2 - Dimensão de 4.68x2.92m, Vão de Sacada 1 Folha de correr + 1 Folha fixa, série "COR VISION PLUS", Lacada segundo alçados (RAL9003, por confirmar), incluindo soleira em chapa de alumínio anodizado (acabamento natural) quinada 3mm esp., estruturada com tubos facar ao critério do executante, sobre-elevada 1cm com apoios de borracha ao critério do executante. | C9: VE 01.2 - Dimensions 4.68x2.92m, Balcony span 1 sliding leaf + 1 fixed leaf, "COR VISION PLUS" series, Lacquered according to elevations (RAL9003, to be confirmed), including threshold in anodised aluminum sheet (natural finish) bent 3mm thick, structured with knife tubes at the discretion of the contractor, raised 1cm with rubber supports at the discretion of the contractor. | E9: un | F9: 1
A11: 2.9.1.1.3 | B11: VE 01.3 - Dimensão de 4.61x2.92m, Vão de Sacada 1 Folha de correr + 1 Folha fixa, série "COR VISION PLUS", Lacada segundo alçados (RAL9003, por confirmar), incluindo soleira em chapa de alumínio anodizado (acabamento natural) quinada 3mm esp., estruturada com tubos facar ao critério do executante, sobre-elevada 1cm com apoios de borracha ao critério do executante. | C11: VE 01.3 - Dimensions of 4.61x2.92m, Balcony span 1 sliding leaf + 1 fixed leaf, "COR VISION PLUS" series, Lacquered according to elevations (RAL9003, to be confirmed), including threshold in anodised aluminum sheet (natural finish) bent 3mm thick, structured with knife tubes at the discretion of the contractor, raised 1cm with rubber supports at the discretion of the contractor. | E11: un | F11: 1
A13: 2.9.1.1.4 | B13: VE 01.4 - Dimensão de 3.04x2.92m, Vão de Sacada 2 Folhas de correr, série "COR VISION PLUS", Lacada segundo alçados (RAL9003, por confirmar), incluindo soleira em chapa de alumínio anodizado (acabamento natural) quinada 3mm esp., estruturada com tubos facar ao critério do executante. | C13: VE 01.4 - Dimensions 3.04x2.92m, Balcony Opening 2 Sliding Leaves, "COR VISION PLUS" series, Lacquered according to elevations (RAL9003, to be confirmed), including threshold in anodized aluminum sheet (natural finish) bent 3mm thick, structured with tubes made at the discretion of the developer. | E13: un | F13: 1
A15: 2.9.1.1.5 | B15: VE 01.5 - Dimensão de 5.93x2.92m, Vão de Sacada 1 Folha de correr e 2 Folhas fixas, série "COR VISION PLUS", Lacada segundo alçados (RAL9003, por confirmar), incluindo Perfis estruturais de ligação entre VE05 e VE06 forrados a chapa de aluminio anodizado igual aos caixilhos, nas faces visiveis. Consultar PORM04 na folha EXE33. | C15: VE 01.5 - Dimensions 5.93x2.92m, Balcony span 1 sliding leaf and 2 fixed leaves, "COR VISION PLUS" series, Lacquered according to elevations (RAL9003, to be confirmed), including structural connecting profiles between VE05 and VE06 lined with anodized aluminum sheet equal to the frames, on the visible sides. See PORM04 on sheet EXE33. | E15: un | F15: 1
A17: 2.9.1.1.6 | B17: VE 01.6 - Dimensão de 6.19x2.92m, Vão de Sacada 1 Folha de correr e 2 Folhas fixas, série "COR VISION PLUS", Lacada segundo alçados (RAL9003, por confirmar), incluindo Perfis estruturais de ligação entre VE05 e VE06 + VE06 e VE07 forrados a chapa de aluminio anodizado igual aos caixilhos, nas faces visiveis. Consultar PORM04 na folha EXE33. | C17: VE 01.6 - Dimensions 6.19x2.92m, Balcony span 1 sliding leaf and 2 fixed leaves, "COR VISION PLUS" series, Lacquered according to elevations (RAL9003, to be confirmed), including structural connecting profiles between VE05 and VE06 + VE06 and VE07 lined with anodized aluminum sheet equal to the frames, on the visible sides. See PORM04 on sheet EXE33. | E17: un | F17: 1
A19: 2.9.1.1.7 | B19: VE 01.7 - Dimensão de 4.94x2.92m, Vão de Sacada 1 Folha de correr e 1 Folha fixa, série "COR VISION PLUS", Lacada segundo alçados (RAL9003, por confirmar), incluindo Perfis estruturais de ligação entre VE06 e VE07 + VE07 e VE08 forrados a chapa de aluminio anodizado igual aos caixilhos, nas faces visiveis. Consultar PORM04 na folha EXE33. | C19: VE 01.7 - Dimensions 4.94x2.92m, Balcony span 1 sliding leaf and 1 fixed leaf, "COR VISION PLUS" series, Lacquered according to elevations (RAL9003, to be confirmed), including structural connecting profiles between VE06 and VE07 + VE07 and VE08 lined with anodized aluminum sheet equal to the frames, on the visible sides. See PORM04 on sheet EXE33. | E19: un | F19: 1
A21: 2.9.1.1.8 | B21: VE 01.8 - Dimensão de 7.18x2.92m, Vão de Sacada 1 Folha de correr e 2 Folhas fixas, série "COR VISION PLUS", Lacada segundo alçados (RAL9003, por confirmar), incluindo Perfis estruturais de ligação entre VE07 e VE08 forrados a chapa de aluminio anodizado igual aos caixilhos, nas faces visiveis. Consultar PORM04 na folha EXE33. | C21: VE 01.8 - Dimensions 7.18x2.92m, Balcony span 1 sliding leaf and 2 fixed leaves, "COR VISION PLUS" series, Lacquered according to elevations (RAL9003, to be confirmed), including structural connecting profiles between VE07 and VE08 lined with anodized aluminum sheet equal to the frames, on the visible sides. See PORM04 on sheet EXE33. | E21: un | F21: 1
A23: 2.9.1.1.9 | B23: VE 00.1 - Dimensão de 7.24x2.94m, Vão de Sacada 1 Folha de correr e 2 Folhas fixas, série "COR VISION PLUS", Lacada segundo alçados (RAL9003, por confirmar), incluindo soleira em cantoneira de Alumínio L 210x60mm, acabamento escovado. | C23: VE 00.1 - Dimensions 7.24x2.94m, Balcony span 1 sliding leaf and 2 fixed leaves, "COR VISION PLUS" series, Lacquered according to elevations (RAL9003, to be confirmed), including aluminum corner threshold L 210x60mm, brushed finish. | E23: un | F23: 1
A25: 2.9.1.1.10 | B25: VE 00.2 - Dimensão de 2.23x2.94m, Vão de Sacada 1 Folha pivotante, Porta de Entrada CORTIZO, série "MILLENNIUM PLUS PIVOT", acabamento Anodizado, incluindo soleira em chapa de aço inox quinada 3mm esp. sobre-elevada 1cm com apoios de borracha ao critério do executante, incluindo Perfis estruturais de ligação entre VE02 e VE03 forrados a chapa de aluminio anodizado igual aos caixilhos, nas faces visiveis. Consultar PORM07 na folha EXE34. | C25: VE 00.2 - Dimensions of 2.23x2.94m, Balcony span 1 pivoting leaf, CORTIZO Entrance Door, "MILLENNIUM PLUS PIVOT" series, Anodized finish, including threshold in bent stainless steel sheet 3mm thick. raised 1cm with rubber supports at the discretion of the executor, including structural connection profiles between VE02 and VE03 lined with anodized aluminum sheet equal to the frames, on the visible sides. See PORM07 on sheet EXE34. | E25: un | F25: 1
A27: 2.9.1.1.11 | B27: VE 00.3 - Dimensão de 2.15x2.89m, Vão de Sacada 1 Folha fixa, série "COR 70", acabamento Anodizado, incluindo soleira em chapa de alumínio anodizado (acabamento natural) quinada 3mm esp., estruturada com tubos facar ao critério do executante - Ver PORM12, incluindo Perfis estruturais de ligação entre VE02 e VE03 forrados a chapa de aluminio anodizado igual aos caixilhos, nas faces visiveis. Consultar PORM07 na folha EXE34. | C27: VE 00.3 - Dimensions 2.15x2.89m, Balcony Opening 1 Fixed leaf, "COR 70" series, Anodized finish, including sill in anodized aluminum sheet (natural finish) bent 3mm thick, structured with pipes made at the discretion of the contractor - See PORM12, including Structural connecting profiles between VE02 and VE03 lined with the same anodized aluminum sheet to the frames, on the visible sides. See PORM07 on sheet EXE34. | E27: un | F27: 1
A29: 2.9.1.1.12 | B29: VE 00.4 - Dimensão de 2.58x2.92m, Vão de Sacada 1 Folha fixa, série "COR 70", acabamento Anodizado, incluindo soleira em chapa de alumínio anodizado, quinada em Z, 3mm esp. DIM abas, sequencialmente: 20mm, 260mm, 45mm, apoiada sobre estrutura ao critério do executante, conforme detalhes. | C29: VE 00.4 - Dimensions 2.58x2.92m, Balcony span 1 fixed leaf, "COR 70" series, Anodized finish, including sill in anodized aluminum sheet, bent in Z, 3mm in width. DIM flaps, sequentially: 20mm, 260mm, 45mm, supported on a structure at the discretion of the performer, according to details. | E29: un | F29: 1
... A47: 2.9.1.1.21 | B47: VE-01.4 - Dimensão de 0.97x2.30m, Vão de Sacada 1 Folha oscilo-batente, série "COR 70", acabamento Anodizado, incluindo soleira em chapa de alumínio anodizado, quinada em Z, 3mm esp. DIM abas, sequencialmente: 20mm, 260mm, 45mm, apoiada sobre estrutura ao critério do executante, conforme detalhes. | C47: VE-01.4 - Dimensions 0.97x2.30m, Balcony Opening 1 tilt-and-turn leaf, "COR 70" series, Anodized finish, including threshold in anodized aluminum sheet, bent in Z, 3mm in width. DIM flaps, sequentially: 20mm, 260mm, 45mm, supported on a structure at the discretion of the performer, according to details. | E47: un | F47: 1
A49: 2.9.1.2 | B49: Fornecimento e montagem de portinhola de acesso a tanque de compensação da piscina em alumínio anodizado a RAL 9003 com guarnição, espessura total = 50mm, incluindo dobradiças ao critério do executante, fechadura de cacifo JNF IN.20.07715 e todos os trabalhos preparatórios e acessórios necessários a um perfeito acabamento. | C49: Supply and assembly of access door to the pool's compensation tank in anodised aluminum to RAL 9003 with trim, total thickness = 50mm, including hinges at the discretion of the contractor, locker lock JNF IN.20.07715 and all preparatory work and accessories necessary for a perfect finish.
A51: 2.9.1.2.1 | B51: VI -01.6 - Portinhola de 1 folha de batente, com a dimensão de 1.00x0.60m. | C51: VI -01.6 - Door with 1 hinged leaf, measuring 1.00x0.60m. | E51: un | F51: 1
A53: 2.9.2 | B53: PORTAS METÁLICAS | C53: METALLIC DOORS
